Workbook
Name CARENCIA: [1]Planilha1!$E$2:$E$9
Name Carenciaa: [2]Planilha1!$E$2:$E$9
Name Cidade: [3]Dados!$B$4:$B$362
Name valuevx: 42.314159

Sheet Inputs
A1: Quadro Tarifário | I1: Taxa de Disponibilidade (kWh/h) | L1: Estrutura | N1: ∆T
A2: Tarifa | C2: 1.25 | I2: Monofásica | J2: 30 | L2: a | M2: Estrutura Elevada | N2: -3
A3: Tipo de Ligação | C3: Trifásica | F3: Preencher | I3: Bifásica | J3: 50 | L3: b | M3: Laje ou Telhado | N3: 3
A4: Consumo Energético | F4: Escolher | I4: Trifásica | J4: 100 | L4: c | M4: Sobre telhado | N4: 4
A5: Mês | B5: Consumo | C5: Fatura | L5: d | M5: Integrado | N5: 7
A6: Janeiro | B6: 750 | C6: =B6*$C$2 -> 937.5 | I6: Outras Perdas
A7: Fevereiro | B7: 750 | C7: =B7*$C$2 -> 937.5 | I7: K somb | J7: 0
A8: Março | B8: 750 | C8: =B8*$C$2 -> 937.5 | I8: K suj | J8: 0.02
A9: Abril | B9: 750 | C9: =B9*$C$2 -> 937.5 | I9: K tol | J9: 0
A10: Maio | B10: 750 | C10: =B10*$C$2 -> 937.5 | I10: K mis | J10: 0
A11: Junho | B11: 750 | C11: =B11*$C$2 -> 937.5 | I11: K temp | J11: - | K11: Calculada à parte
A12: Julho | B12: 750 | C12: =B12*$C$2 -> 937.5 | I12: K cc | J12: 0.01
A13: Agosto | B13: 750 | C13: =B13*$C$2 -> 937.5 | I13: K spmp | J13: 0.02
A14: Setembro | B14: 750 | C14: =B14*$C$2 -> 937.5 | I14: K inv | J14: 0.04
A15: Outubro | B15: 750 | C15: =B15*$C$2 -> 937.5 | I15: K ca | J15: 0.01
A16: Novembro | B16: 750 | C16: =B16*$C$2 -> 937.5 | I16: Total | J16: =SUM(J7:J15) -> 0.1
A17: Dezembro | B17: 750 | C17: =B17*$C$2 -> 937.5
A18: Média | B18: =AVERAGE(B6:B17) -> 750 | C18: =AVERAGE(C6:C17) -> 937.5
B21: 450
F31: 590
O48: Inclinação
O49: 0
O50: 5
O51: 10
O52: 15
O53: 20
O54: 25
O55: 30
O56: 35
O57: 40
O58: 45
O59: 50
O60: 55
... O67: 90

Sheet Irradiação Solar
A2: 1. | B2: Encontre no Google Maps o local onde será feita a instalação
B3: https://maps.google.com/
A4: 2. | B4: Localize na barra de navegação as coordenadas geográficas do local da instalação
B5: Exemplo ao lado.
A6: 3. | B6: Insira as coordenadas no site do CRESESB para obter os níveis de radiação
B7: http://www.cresesb.cepel.br/index.php?section=sundata | H7: e clique em BUSCAR
B8: Obs.: Não precisa inserir o sinal de negativo
A9: 4. | B9: O site irá mostrar 3 opções para irradiação solar no Plano Horizontal
A10: 5. | B10: Escolha uma opção e cole os dados de irradiação abaixo:
B12: Jan | C12: Fev | D12: Mar | E12: Abr | F12: Mai | G12: Jun | H12: Jul | I12: Ago | J12: Set | K12: Out | L12: Nov | M12: Dez
B13: 6.18 | C13: 6.38 | D13: 5.15 | E13: 4.44 | F13: 3.59 | G13: 3.32 | H13: 3.35 | I13: 4.22 | J13: 4.41 | K13: 5.08 | L13: 5.22 | M13: 6.05
A15: 6. | B15: Insira aqui o valor da latitude: | E15: 22.916321

Sheet Análise Técnica
Y1: =ROUNDUP(U9/C22,0) -> 117
B2: Dimensionamento | H2: Correção HSP e Geração Estimada
B3: Consumo médio Mensal | C3: =Inputs!B18 -> 750 | D3: kWh/mês | I3: Janeiro | J3: Fevereiro | K3: Março | L3: Abril | M3: Maio | N3: Junho | O3: Julho | P3: Agosto | Q3: Setembro | R3: Outubro | S3: Novembro | T3: Dezembro | U3: Média | V3: Total
B4: Tipo de Ligação | C4: =Inputs!C3 -> Trifásica | H4: HSP | I4: ='Irradiação Solar'!B13 -> 6.18 | J4: ='Irradiação Solar'!C13 -> 6.38 | K4: ='Irradiação Solar'!D13 -> 5.15 | L4: ='Irradiação Solar'!E13 -> 4.44 | M4: ='Irradiação Solar'!F13 -> 3.59 | N4: ='Irradiação Solar'!G13 -> 3.32 | O4: ='Irradiação Solar'!H13 -> 3.35 | P4: ='Irradiação Solar'!I13 -> 4.22 | ... T4: ='Irradiação Solar'!M13 -> 6.05 | U4: =AVERAGE(I4:T4) -> 4.7825 | V4: -
B5: Custo de disponibilidade | C5: =VLOOKUP(C4,Inputs!I2:J4,2,FALSE) -> 100 | D5: kWh | H5: K | I5: ='Correção K'!T4 -> 0.99 | J5: ='Correção K'!U4 -> 1.01 | K5: ='Correção K'!V4 -> 1.05 | L5: ='Correção K'!W4 -> 1.08 | M5: ='Correção K'!X4 -> 1.1 | N5: ='Correção K'!Y4 -> 1.1 | O5: ='Correção K'!Z4 -> 1.09 | P5: ='Correção K'!AA4 -> 1.07 | ... T5: ='Correção K'!AE4 -> 0.98 | U5: =AVERAGE(I5:T5) -> 1.0425 | V5: -
B6: Energia de Compensação Mensal | C6: =C3-C5 -> 650 | D6: kWh/mês | H6: HSPk | I6: =I4*I5 -> 6.1182 | J6: =J4*J5 -> 6.4438 | K6: =K4*K5 -> 5.4075 | L6: =L4*L5 -> 4.7952 | M6: =M4*M5 -> 3.949 | N6: =N4*N5 -> 3.652 | O6: =O4*O5 -> 3.6515 | P6: =P4*P5 -> 4.5154 | ... T6: =T4*T5 -> 5.929 | U6: =AVERAGE(I6:T6) -> 4.94555 | V6: -
B7: Energia de Compensação Diária | C7: =C6/30 -> 21.666667 | D7: kWh/m²/dia | H7: Consumo | I7: =Inputs!B6 -> 750 | J7: =Inputs!B7 -> 750 | K7: =Inputs!B8 -> 750 | L7: =Inputs!B9 -> 750 | M7: =Inputs!B10 -> 750 | N7: =Inputs!B11 -> 750 | O7: =Inputs!B12 -> 750 | P7: =Inputs!B13 -> 750 | Q7: =Inputs!B14 -> 750 | R7: =Inputs!B15 -> 750 | S7: =Inputs!B16 -> 750 | T7: =Inputs!B17 -> 750 | U7: =AVERAGE(I7:T7) -> 750 | V7: =SUM(I7:T7) -> 9000
B8: Latitude (Nº inteiro) | C8: =ROUNDUP('Irradiação Solar'!E15,0) -> 23 | D8: ⁰ | H8: Consumo médio | I8: =$U$7 -> 750 | J8: =$U$7 -> 750 | K8: =$U$7 -> 750 | L8: =$U$7 -> 750 | M8: =$U$7 -> 750 | N8: =$U$7 -> 750 | O8: =$U$7 -> 750 | P8: =$U$7 -> 750 | ... T8: =$U$7 -> 750 | U8: =AVERAGE(I8:T8) -> 750 | V8: =SUM(I8:T8) -> 9000
B9: Potencial Solar - Dia | C9: =U6 -> 4.94555 | D9: kWh/m²/dia | H9: Energia Estimada | I9: =I$6*$C$28/1000*30*(1-$C$33) -> 911.2372 | J9: =J$6*$C$28/1000*30*(1-$C$33) -> 959.73166 | K9: =K$6*$C$28/1000*30*(1-$C$33) -> 805.38641 | L9: =L$6*$C$28/1000*30*(1-$C$33) -> 714.1912 | M9: =M$6*$C$28/1000*30*(1-$C$33) -> 588.15921 | N9: =N$6*$C$28/1000*30*(1-$C$33) -> 543.9244 | O9: =O$6*$C$28/1000*30*(1-$C$33) -> 543.84993 | P9: =P$6*$C$28/1000*30*(1-$C$33) -> 672.51813 | ... T9: =T$6*$C$28/1000*30*(1-$C$33) -> 883.05798 | U9: =AVERAGE(I9:T9) -> 736.58415 | V9: =SUM(I9:T9) -> 8839.0098
B10: Potencial Solar - Ano | C10: =C9*365 -> 1805.1257 | H10: Objetivo de Geração | I10: =I8-$C$5 -> 650 | J10: =J8-$C$5 -> 650 | K10: =K8-$C$5 -> 650 | L10: =L8-$C$5 -> 650 | M10: =M8-$C$5 -> 650 | N10: =N8-$C$5 -> 650 | O10: =O8-$C$5 -> 650 | P10: =P8-$C$5 -> 650 | ... T10: =T8-$C$5 -> 650 | U10: =AVERAGE(I10:T10) -> 650
B11: Inclinação ideal de projeto | C11: =3.7+(0.69*C8) -> 19.57 | D11: ⁰
B12: Inclinação Real (Escolha inclinação + Próxima) | C12: 10 | D12: ⁰
B13: Potencia Teórica | C13: =C7/C9 -> 4.3810429 | D13: Kwp teórico | G13: Preencher
B14: Perdas Totais | C14: =C33 -> 0.21196417 | G14: Escolher
B15: Geração desejada | C15: 1
B16: Sistema Real para Geração Máxima (100%) | C16: =(1+C14)*C13*C15 -> 5.309667 | D16: Kwp
B18: Característiccas Técnicas
B19: Potência nominal dos Módulos | C19: 700 | D19: W
B20: Número necessários de Módulos | C20: =ROUNDUP(C15*(C16*1000/C19),0)+C21 -> 9 | D20: un.
B21: Ajuste manual do número de módulos | C21: 1 | D21: un.
B22: Potência do Sistema | C22: =C20*C19/1000 -> 6.3 | D22: kWp
B23: Potência Nominal do Inversor que se pretende usar | C23: 6 | D23: kW
B24: Nº de Inversores | C24: 1 | D24: un. | E24: =IF(D25="OK","","O ideal é que o fator de dimensionamento Global fique entre 0,75 e 1,25")
B25: Fotor de Dimensionamento Global (Pcc/Pca) | C25: =C22/(C23*C24) -> 1.05 | D25: =IF(C25<0.75,"Atenção",IF(C25>1.3,"Atenção","OK")) -> OK
F26: 8
B27: Caracterização das Perdas
B28: Potência Instalada (Wp) | C28: =C22*1000 -> 6300 | D28: Wp
B29: Coef. Temp para Pmax | C29: -0.0041 | D29: %/°C
B30: Outras Perdas (Ver aba Inputs) | C30: =Inputs!J16 -> 0.1 | D30: %
B31: Perda média por temperatura | C31: =E69 -> 0.11196417 | D31: %
B32: Perda Transformador 380V/220V | C32: 0 | D32: %
B33: Fator de Perdas | C33: =C30+C31+C32 -> 0.21196417 | D33: %
B34: Selecione Tipo de Estrutura (Na ordem, a,b,c,d) | C34: Sobre telhado | D34: -
B35: Diferença à Tref | C35: =VLOOKUP($C34,Inputs!M2:N5,2,FALSE) -> 4 | D35: ºC
B36: ∆T | C36: =25+C35 -> 29 | D36: C
B55: Perdas por Temperatura (Selecione abaixo a cidade mais próxima, ver aba "Temp. Média"
B56: Rio de Janeiro | C56: Temp. Média | D56: Temp. calc | E56: K temp
B57: Janeiro | C57: =VLOOKUP($B56,'Temp. Média'!$A:$N,6,FALSE) -> 24.4 | D57: =C57+($C$36-25) -> 28.4 | E57: =-$C$29*D57 -> 0.11644
B58: Fevereiro | C58: =VLOOKUP($B56,'Temp. Média'!$A:$N,6,FALSE) -> 24.4 | D58: =C58+($C$36-25) -> 28.4 | E58: =-$C$29*D58 -> 0.11644
B59: Março | C59: =VLOOKUP($B56,'Temp. Média'!$A:$N,6,FALSE) -> 24.4 | D59: =C59+($C$36-25) -> 28.4 | E59: =-$C$29*D59 -> 0.11644
B60: Abril | C60: =VLOOKUP($B56,'Temp. Média'!$A:$N,6,FALSE) -> 24.4 | D60: =C60+($C$36-25) -> 28.4 | E60: =-$C$29*D60 -> 0.11644
B61: Maio | C61: =VLOOKUP($B56,'Temp. Média'!$A:$N,7,FALSE) -> 22.8 | D61: =C61+($C$36-25) -> 26.8 | E61: =-$C$29*D61 -> 0.10988
B62: Junho | C62: =VLOOKUP($B56,'Temp. Média'!$A:$N,8,FALSE) -> 21.8 | D62: =C62+($C$36-25) -> 25.8 | E62: =-$C$29*D62 -> 0.10578
B63: Julho | C63: =VLOOKUP($B56,'Temp. Média'!$A:$N,9,FALSE) -> 21.3 | D63: =C63+($C$36-25) -> 25.3 | E63: =-$C$29*D63 -> 0.10373
B64: Agosto | C64: =VLOOKUP($B56,'Temp. Média'!$A:$N,10,FALSE) -> 21.8 | D64: =C64+($C$36-25) -> 25.8 | E64: =-$C$29*D64 -> 0.10578
B65: Setembro | C65: =VLOOKUP($B56,'Temp. Média'!$A:$N,11,FALSE) -> 22.2 | D65: =C65+($C$36-25) -> 26.2 | E65: =-$C$29*D65 -> 0.10742
B66: Outubro | C66: =VLOOKUP($B56,'Temp. Média'!$A:$N,12,FALSE) -> 22.9 | D66: =C66+($C$36-25) -> 26.9 | E66: =-$C$29*D66 -> 0.11029
B67: Novembro | C67: =VLOOKUP($B56,'Temp. Média'!$A:$N,13,FALSE) -> 24 | D67: =C67+($C$36-25) -> 28 | E67: =-$C$29*D67 -> 0.1148
B68: Dezembro | C68: =VLOOKUP($B56,'Temp. Média'!$A:$N,14,FALSE) -> 25.3 | D68: =C68+($C$36-25) -> 29.3 | E68: =-$C$29*D68 -> 0.12013
B69: Média | C69: =AVERAGE(C57:C68) -> 23.308333 | D69: =AVERAGE(D57:D68) -> 27.308333 | E69: =AVERAGE(E57:E68) -> 0.11196417

Sheet Análise Financeira
B2: Custo Global do Projeto | E2: Demonstrativo Energético e Financeiro do primeiro ano com Energia Solar: | AO2: Mês | AP2: Poupança e Conta de Energia | AQ2: Energia Solar
B3: Potência Nominal do Sistema | C3: ='Análise Técnica'!C22 -> 6.3 | E3: Mês | F3: Consumo | G3: Geração | H3: Débito | I3: Crédito | J3: Disponibilidade | K3: Além da Disp. | L3: Créditos | M3: Faturaveis | N3: Sem Energia Solar | O3: Com Energia Solar | P3: Economia (R$) | Q3: Economia (%) | R3: Retorno Investimento | T3: Ano | U3: Mês | W3: Consumo | X3: Geração | Y3: Débito | Z3: Crédito mês | AA3: TD | AB3: Além TD | AC3: Créditos | AD3: Faturáveis | AE3: Sem Energia Solar | AF3: Com Energia Solar | AG3: Economia | AH3: Custos/Manutenção | AI3: Subtotal | AJ3: Fluxo Final | AK3: Economia | AL3: Gasto Acumulado | AM3: Retorno Inv. | AO3: 0 | AP3: =C4 -> 14234.494 | AQ3: =-AP3 -> -14234.494
B4: PREÇO TOTAL | C4: =Custos!D24 -> 14234.494 | E4: Janeiro | F4: =Inputs!B6 -> 750 | G4: ='Análise Técnica'!I9 -> 911.2372 | H4: =IF(G4-F4<0,F4-G4,0) -> 0 | I4: =IF(G4-F4>0,G4-F4,0) -> 161.2372 | J4: =$C$7 -> 100 | K4: =IF(H4-$C$7>0,H4-$C$7,0) -> 0 | L4: =I4 -> 161.2372 | M4: =K4 -> 0 | N4: =Inputs!C6 -> 937.5 | O4: =IF(I4>0, (J4*$C$8),(J4+M4)*$C$8) -> 125 | P4: =N4-O4 -> 812.5 | Q4: =1-(O4/N4) -> 0.86666667 | R4: =P4/$C$4 -> 0.057079654 | T4: 0 | U4: 1 | V4: Janeiro | W4: ='Análise Técnica'!$C$3 -> 750 | X4: =G4 -> 911.2372 | Y4: =IF(X4-W4<0,W4-X4,0) -> 0 | Z4: =IF(X4-W4>0,X4-W4,0) -> 161.2372 | AA4: =$C$7 -> 100 | AB4: =IF(Y4-$C$7>0,Y4-$C$7,0) -> 0 | AC4: =Z4 -> 161.2372 | AD4: =AB4 -> 0 | AE4: =($C$10*(1+$C$30)^T4) -> 937.5 | AF4: =IF(Z4>0,((AA4*$C$8)*((1+$C$30)^T4)),((AA4+AD4)*$C$8)*(1+$C$30)^T4) -> 125 | AG4: =AE4-AF4 -> 812.5 | AH4: =$C$4 -> 14234.494 | AI4: =AG4-AH4 -> -13421.994 | AK4: =1-(AF4/AE4) -> 0.86666667 | AL4: =AE4 -> 937.5 | AM4: =AG4/$C$4 -> 0.057079654 | AO4: 1 | AP4: =($C$4*(1+($C$36-$C$39))^AO4)-AE4 -> 13337.325 | AQ4: =AI4 -> -13421.994
B5: Conumo médio mensal | C5: =Inputs!B18 -> 750 | E5: Fevereiro | F5: =Inputs!B7 -> 750 | G5: ='Análise Técnica'!J9 -> 959.73166 | H5: =IF(G5-F5<0,F5-G5,0) -> 0 | I5: =IF(G5-F5>0,G5-F5,0) -> 209.73166 | J5: =$C$7 -> 100 | K5: =IF(H5-$C$7>0,H5-$C$7,0) -> 0 | L5: =IF(L4-(H5-$C$7)>0,IF(H5>0,IF(H5<$C$7,L4,L4-(H5-$C$7)),I5+L4),0) -> 370.96886 | M5: =K5 -> 0 | N5: =Inputs!C7 -> 937.5 | O5: =IF(I5>0, (J5*$C$8),(J5+M5)*$C$8) -> 125 | P5: =N5-O5 -> 812.5 | Q5: =1-(O5/N5) -> 0.86666667 | R5: =P5/$C$4 -> 0.057079654 | T5: 0 | U5: 2 | V5: Fevereiro | W5: ='Análise Técnica'!$C$3 -> 750 | X5: =G5 -> 959.73166 | Y5: =IF(X5-W5<0,W5-X5,0) -> 0 | Z5: =IF(X5-W5>0,X5-W5,0) -> 209.73166 | AA5: =$C$7 -> 100 | AB5: =IF(Y5-$C$7>0,Y5-$C$7,0) -> 0 | AC5: =IF(AC4-(Y5-$C$7)>0,IF(Y5>0,IF(Y5<$C$7,AC4,AC4-(Y5-$C$7)),Z5+AC4),0) -> 370.96886 | AD5: =IF(AB5-AC4<0,0,AB5-AC4) -> 0 | AE5: =($C$10*(1+$C$30)^T5) -> 937.5 | AF5: =IF(Z5>0,((AA5*$C$8)*((1+$C$30)^T5)),((AA5+AD5)*$C$8)*(1+$C$30)^T5) -> 125 | AG5: =AE5-AF5 -> 812.5 | AH5: =$C$28/12*($C$4*((1+$C$29)^T5))+IF($C$31=T5,$C$33/12,0) -> 0 | AI5: =AG5-AH5 -> 812.5 | AJ5: =AI4+AI5 -> -12609.494 | AK5: =1-(AF5/AE5) -> 0.86666667 | AL5: =AL4+AE5 -> 1875 | AM5: =AG5/$C$4 -> 0.057079654 | AO5: 2 | AP5: =($C$4*(1+($C$36-$C$39))^AO5)-AE5 -> 13377.771 | AQ5: =AJ5 -> -12609.494
B6: Percentual Médio de Geração em 25 anos | C6: =G47/F47 -> 0.90126451 | E6: Março | F6: =Inputs!B8 -> 750 | G6: ='Análise Técnica'!K9 -> 805.38641 | H6: =IF(G6-F6<0,F6-G6,0) -> 0 | I6: =IF(G6-F6>0,G6-F6,0) -> 55.386412 | J6: =$C$7 -> 100 | K6: =IF(H6-$C$7>0,H6-$C$7,0) -> 0 | L6: =IF(L5-(H6-$C$7)>0,IF(H6>0,IF(H6<$C$7,L5,L5-(H6-$C$7)),I6+L5),0) -> 426.35527 | M6: =K6 -> 0 | N6: =Inputs!C8 -> 937.5 | O6: =IF(I6>0, (J6*$C$8),(J6+M6)*$C$8) -> 125 | P6: =N6-O6 -> 812.5 | Q6: =1-(O6/N6) -> 0.86666667 | R6: =P6/$C$4 -> 0.057079654 | T6: 0 | U6: 3 | V6: Março | W6: ='Análise Técnica'!$C$3 -> 750 | X6: =G6 -> 805.38641 | Y6: =IF(X6-W6<0,W6-X6,0) -> 0 | Z6: =IF(X6-W6>0,X6-W6,0) -> 55.386412 | AA6: =$C$7 -> 100 | AB6: =IF(Y6-$C$7>0,Y6-$C$7,0) -> 0 | AC6: =IF(AC5-(Y6-$C$7)>0,IF(Y6>0,IF(Y6<$C$7,AC5,AC5-(Y6-$C$7)),Z6+AC5),0) -> 426.35527 | AD6: =IF(AB6-AC5<0,0,AB6-AC5) -> 0 | AE6: =($C$10*(1+$C$30)^T6) -> 937.5 | AF6: =IF(Z6>0,((AA6*$C$8)*((1+$C$30)^T6)),((AA6+AD6)*$C$8)*(1+$C$30)^T6) -> 125 | AG6: =AE6-AF6 -> 812.5 | AH6: =$C$28/12*($C$4*((1+$C$29)^T6))+IF($C$31=T6,$C$33/12,0) -> 0 | AI6: =AG6-AH6 -> 812.5 | AJ6: =AJ5+AI6 -> -11796.994 | AK6: =1-(AF6/AE6) -> 0.86666667 | AL6: =AL5+AE6 -> 2812.5 | AM6: =AG6/$C$4 -> 0.057079654 | AO6: 3 | AP6: =($C$4*(1+($C$36-$C$39))^AO6)-AE6 -> 13418.331 | AQ6: =AJ6 -> -11796.994
B7: Custo de Disponibilidade | C7: ='Análise Técnica'!C5 -> 100 | E7: Abril | F7: =Inputs!B9 -> 750 | G7: ='Análise Técnica'!L9 -> 714.1912 | H7: =IF(G7-F7<0,F7-G7,0) -> 35.808798 | I7: =IF(G7-F7>0,G7-F7,0) -> 0 | J7: =$C$7 -> 100 | K7: =IF(H7-$C$7>0,H7-$C$7,0) -> 0 | L7: =IF(L6-(H7-$C$7)>0,IF(H7>0,IF(H7<$C$7,L6,L6-(H7-$C$7)),I7+L6),0) -> 426.35527 | M7: =K7 -> 0 | N7: =Inputs!C9 -> 937.5 | O7: =IF(I7>0, (J7*$C$8),(J7+M7)*$C$8) -> 125 | P7: =N7-O7 -> 812.5 | Q7: =1-(O7/N7) -> 0.86666667 | R7: =P7/$C$4 -> 0.057079654 | T7: 0 | U7: 4 | V7: Abril | W7: ='Análise Técnica'!$C$3 -> 750 | X7: =G7 -> 714.1912 | Y7: =IF(X7-W7<0,W7-X7,0) -> 35.808798 | Z7: =IF(X7-W7>0,X7-W7,0) -> 0 | AA7: =$C$7 -> 100 | AB7: =IF(Y7-$C$7>0,Y7-$C$7,0) -> 0 | AC7: =IF(AC6-(Y7-$C$7)>0,IF(Y7>0,IF(Y7<$C$7,AC6,AC6-(Y7-$C$7)),Z7+AC6),0) -> 426.35527 | AD7: =IF(AB7-AC6<0,0,AB7-AC6) -> 0 | AE7: =($C$10*(1+$C$30)^T7) -> 937.5 | AF7: =IF(Z7>0,((AA7*$C$8)*((1+$C$30)^T7)),((AA7+AD7)*$C$8)*(1+$C$30)^T7) -> 125 | AG7: =AE7-AF7 -> 812.5 | AH7: =$C$28/12*($C$4*((1+$C$29)^T7))+IF($C$31=T7,$C$33/12,0) -> 0 | AI7: =AG7-AH7 -> 812.5 | AJ7: =AJ6+AI7 -> -10984.494 | AK7: =1-(AF7/AE7) -> 0.86666667 | AL7: =AL6+AE7 -> 3750 | AM7: =AG7/$C$4 -> 0.057079654 | AO7: 4 | AP7: =($C$4*(1+($C$36-$C$39))^AO7)-AE7 -> 13459.005 | AQ7: =AJ7 -> -10984.494
B8: Tarifa Energética | C8: =Inputs!C2 -> 1.25 | E8: Maio | F8: =Inputs!B10 -> 750 | G8: ='Análise Técnica'!M9 -> 588.15921 | H8: =IF(G8-F8<0,F8-G8,0) -> 161.84079 | I8: =IF(G8-F8>0,G8-F8,0) -> 0 | J8: =$C$7 -> 100 | K8: =IF(H8-$C$7>0,H8-$C$7,0) -> 61.840787 | L8: =IF(L7-(H8-$C$7)>0,IF(H8>0,IF(H8<$C$7,L7,L7-(H8-$C$7)),I8+L7),0) -> 364.51449 | M8: =K8 -> 61.840787 | N8: =Inputs!C10 -> 937.5 | O8: =IF(I8>0, (J8*$C$8),(J8+M8)*$C$8) -> 202.30098 | P8: =N8-O8 -> 735.19902 | Q8: =1-(O8/N8) -> 0.78421228 | R8: =P8/$C$4 -> 0.051649114 | T8: 0 | U8: 5 | V8: Maio | W8: ='Análise Técnica'!$C$3 -> 750 | X8: =G8 -> 588.15921 | Y8: =IF(X8-W8<0,W8-X8,0) -> 161.84079 | Z8: =IF(X8-W8>0,X8-W8,0) -> 0 | AA8: =$C$7 -> 100 | AB8: =IF(Y8-$C$7>0,Y8-$C$7,0) -> 61.840787 | AC8: =IF(AC7-(Y8-$C$7)>0,IF(Y8>0,IF(Y8<$C$7,AC7,AC7-(Y8-$C$7)),Z8+AC7),0) -> 364.51449 | AD8: =IF(AB8-AC7<0,0,AB8-AC7) -> 0 | AE8: =($C$10*(1+$C$30)^T8) -> 937.5 | AF8: =IF(Z8>0,((AA8*$C$8)*((1+$C$30)^T8)),((AA8+AD8)*$C$8)*(1+$C$30)^T8) -> 125 | AG8: =AE8-AF8 -> 812.5 | AH8: =$C$28/12*($C$4*((1+$C$29)^T8))+IF($C$31=T8,$C$33/12,0) -> 0 | AI8: =AG8-AH8 -> 812.5 | AJ8: =AJ7+AI8 -> -10171.994 | AK8: =1-(AF8/AE8) -> 0.86666667 | AL8: =AL7+AE8 -> 4687.5 | AM8: =AG8/$C$4 -> 0.057079654 | AO8: 5 | AP8: =($C$4*(1+($C$36-$C$39))^AO8)-AE8 -> 13499.796 | AQ8: =AJ8 -> -10171.994
B9: Tipo de Ligação | C9: =Inputs!C3 -> Trifásica | E9: Junho | F9: =Inputs!B11 -> 750 | G9: ='Análise Técnica'!N9 -> 543.9244 | H9: =IF(G9-F9<0,F9-G9,0) -> 206.0756 | I9: =IF(G9-F9>0,G9-F9,0) -> 0 | J9: =$C$7 -> 100 | K9: =IF(H9-$C$7>0,H9-$C$7,0) -> 106.0756 | L9: =IF(L8-(H9-$C$7)>0,IF(H9>0,IF(H9<$C$7,L8,L8-(H9-$C$7)),I9+L8),0) -> 258.43888 | M9: =K9 -> 106.0756 | N9: =Inputs!C11 -> 937.5 | O9: =IF(I9>0, (J9*$C$8),(J9+M9)*$C$8) -> 257.5945 | P9: =N9-O9 -> 679.9055 | Q9: =1-(O9/N9) -> 0.72523253 | R9: =P9/$C$4 -> 0.04776464 | T9: 0 | U9: 6 | V9: Junho | W9: ='Análise Técnica'!$C$3 -> 750 | X9: =G9 -> 543.9244 | Y9: =IF(X9-W9<0,W9-X9,0) -> 206.0756 | Z9: =IF(X9-W9>0,X9-W9,0) -> 0 | AA9: =$C$7 -> 100 | AB9: =IF(Y9-$C$7>0,Y9-$C$7,0) -> 106.0756 | AC9: =IF(AC8-(Y9-$C$7)>0,IF(Y9>0,IF(Y9<$C$7,AC8,AC8-(Y9-$C$7)),Z9+AC8),0) -> 258.43888 | AD9: =IF(AB9-AC8<0,0,AB9-AC8) -> 0 | AE9: =($C$10*(1+$C$30)^T9) -> 937.5 | AF9: =IF(Z9>0,((AA9*$C$8)*((1+$C$30)^T9)),((AA9+AD9)*$C$8)*(1+$C$30)^T9) -> 125 | AG9: =AE9-AF9 -> 812.5 | AH9: =$C$28/12*($C$4*((1+$C$29)^T9))+IF($C$31=T9,$C$33/12,0) -> 0 | AI9: =AG9-AH9 -> 812.5 | AJ9: =AJ8+AI9 -> -9359.4942 | AK9: =1-(AF9/AE9) -> 0.86666667 | AL9: =AL8+AE9 -> 5625 | AM9: =AG9/$C$4 -> 0.057079654 | AO9: 6 | AP9: =($C$4*(1+($C$36-$C$39))^AO9)-AE9 -> 13540.701 | AQ9: =AJ9 -> -9359.4942
B10: Fatura média atual | C10: =Inputs!C18 -> 937.5 | E10: Julho | F10: =Inputs!B12 -> 750 | G10: ='Análise Técnica'!O9 -> 543.84993 | H10: =IF(G10-F10<0,F10-G10,0) -> 206.15007 | I10: =IF(G10-F10>0,G10-F10,0) -> 0 | J10: =$C$7 -> 100 | K10: =IF(H10-$C$7>0,H10-$C$7,0) -> 106.15007 | L10: =IF(L9-(H10-$C$7)>0,IF(H10>0,IF(H10<$C$7,L9,L9-(H10-$C$7)),I10+L9),0) -> 152.28881 | M10: =K10 -> 106.15007 | N10: =Inputs!C12 -> 937.5 | O10: =IF(I10>0, (J10*$C$8),(J10+M10)*$C$8) -> 257.68759 | P10: =N10-O10 -> 679.81241 | Q10: =1-(O10/N10) -> 0.72513324 | R10: =P10/$C$4 -> 0.047758101 | T10: 0 | U10: 7 | V10: Julho | W10: ='Análise Técnica'!$C$3 -> 750 | X10: =G10 -> 543.84993 | Y10: =IF(X10-W10<0,W10-X10,0) -> 206.15007 | Z10: =IF(X10-W10>0,X10-W10,0) -> 0 | AA10: =$C$7 -> 100 | AB10: =IF(Y10-$C$7>0,Y10-$C$7,0) -> 106.15007 | AC10: =IF(AC9-(Y10-$C$7)>0,IF(Y10>0,IF(Y10<$C$7,AC9,AC9-(Y10-$C$7)),Z10+AC9),0) -> 152.28881 | AD10: =IF(AB10-AC9<0,0,AB10-AC9) -> 0 | AE10: =($C$10*(1+$C$30)^T10) -> 937.5 | AF10: =IF(Z10>0,((AA10*$C$8)*((1+$C$30)^T10)),((AA10+AD10)*$C$8)*(1+$C$30)^T10) -> 125 | AG10: =AE10-AF10 -> 812.5 | AH10: =$C$28/12*($C$4*((1+$C$29)^T10))+IF($C$31=T10,$C$33/12,0) -> 0 | AI10: =AG10-AH10 -> 812.5 | AJ10: =AJ9+AI10 -> -8546.9942 | AK10: =1-(AF10/AE10) -> 0.86666667 | AL10: =AL9+AE10 -> 6562.5 | AM10: =AG10/$C$4 -> 0.057079654 | AO10: 7 | AP10: =($C$4*(1+($C$36-$C$39))^AO10)-AE10 -> 13581.723 | AQ10: =AJ10 -> -8546.9942
B11: Outputs e Resultados | E11: Agosto | F11: =Inputs!B13 -> 750 | G11: ='Análise Técnica'!P9 -> 672.51813 | H11: =IF(G11-F11<0,F11-G11,0) -> 77.481867 | I11: =IF(G11-F11>0,G11-F11,0) -> 0 | J11: =$C$7 -> 100 | K11: =IF(H11-$C$7>0,H11-$C$7,0) -> 0 | L11: =IF(L10-(H11-$C$7)>0,IF(H11>0,IF(H11<$C$7,L10,L10-(H11-$C$7)),I11+L10),0) -> 152.28881 | M11: =K11 -> 0 | N11: =Inputs!C13 -> 937.5 | O11: =IF(I11>0, (J11*$C$8),(J11+M11)*$C$8) -> 125 | P11: =N11-O11 -> 812.5 | Q11: =1-(O11/N11) -> 0.86666667 | R11: =P11/$C$4 -> 0.057079654 | T11: 0 | U11: 8 | V11: Agosto | W11: ='Análise Técnica'!$C$3 -> 750 | X11: =G11 -> 672.51813 | Y11: =IF(X11-W11<0,W11-X11,0) -> 77.481867 | Z11: =IF(X11-W11>0,X11-W11,0) -> 0 | AA11: =$C$7 -> 100 | AB11: =IF(Y11-$C$7>0,Y11-$C$7,0) -> 0 | AC11: =IF(AC10-(Y11-$C$7)>0,IF(Y11>0,IF(Y11<$C$7,AC10,AC10-(Y11-$C$7)),Z11+AC10),0) -> 152.28881 | AD11: =IF(AB11-AC10<0,0,AB11-AC10) -> 0 | AE11: =($C$10*(1+$C$30)^T11) -> 937.5 | AF11: =IF(Z11>0,((AA11*$C$8)*((1+$C$30)^T11)),((AA11+AD11)*$C$8)*(1+$C$30)^T11) -> 125 | AG11: =AE11-AF11 -> 812.5 | AH11: =$C$28/12*($C$4*((1+$C$29)^T11))+IF($C$31=T11,$C$33/12,0) -> 0 | AI11: =AG11-AH11 -> 812.5 | AJ11: =AJ10+AI11 -> -7734.4942 | AK11: =1-(AF11/AE11) -> 0.86666667 | AL11: =AL10+AE11 -> 7500 | AM11: =AG11/$C$4 -> 0.057079654 | AO11: 8 | AP11: =($C$4*(1+($C$36-$C$39))^AO11)-AE11 -> 13622.861 | AQ11: =AJ11 -> -7734.4942
B12: Payback Ano | C12: =VLOOKUP("Payback",S4:T303,2,0) -> 1 | E12: Setembro | F12: =Inputs!B14 -> 750 | G12: ='Análise Técnica'!Q9 -> 683.09279 | H12: =IF(G12-F12<0,F12-G12,0) -> 66.907214 | I12: =IF(G12-F12>0,G12-F12,0) -> 0 | J12: =$C$7 -> 100 | K12: =IF(H12-$C$7>0,H12-$C$7,0) -> 0 | L12: =IF(L11-(H12-$C$7)>0,IF(H12>0,IF(H12<$C$7,L11,L11-(H12-$C$7)),I12+L11),0) -> 152.28881 | M12: =K12 -> 0 | N12: =Inputs!C14 -> 937.5 | O12: =IF(I12>0, (J12*$C$8),(J12+M12)*$C$8) -> 125 | P12: =N12-O12 -> 812.5 | Q12: =1-(O12/N12) -> 0.86666667 | R12: =P12/$C$4 -> 0.057079654 | T12: 0 | U12: 9 | V12: Setembro | W12: ='Análise Técnica'!$C$3 -> 750 | X12: =G12 -> 683.09279 | Y12: =IF(X12-W12<0,W12-X12,0) -> 66.907214 | Z12: =IF(X12-W12>0,X12-W12,0) -> 0 | AA12: =$C$7 -> 100 | AB12: =IF(Y12-$C$7>0,Y12-$C$7,0) -> 0 | AC12: =IF(AC11-(Y12-$C$7)>0,IF(Y12>0,IF(Y12<$C$7,AC11,AC11-(Y12-$C$7)),Z12+AC11),0) -> 152.28881 | AD12: =IF(AB12-AC11<0,0,AB12-AC11) -> 0 | AE12: =($C$10*(1+$C$30)^T12) -> 937.5 | AF12: =IF(Z12>0,((AA12*$C$8)*((1+$C$30)^T12)),((AA12+AD12)*$C$8)*(1+$C$30)^T12) -> 125 | AG12: =AE12-AF12 -> 812.5 | AH12: =$C$28/12*($C$4*((1+$C$29)^T12))+IF($C$31=T12,$C$33/12,0) -> 0 | AI12: =AG12-AH12 -> 812.5 | AJ12: =AJ11+AI12 -> -6921.9942 | AK12: =1-(AF12/AE12) -> 0.86666667 | AL12: =AL11+AE12 -> 8437.5 | AM12: =AG12/$C$4 -> 0.057079654 | AO12: 9 | AP12: =($C$4*(1+($C$36-$C$39))^AO12)-AE12 -> 13664.115 | AQ12: =AJ12 -> -6921.9942
B13: Payback Mês | C13: =VLOOKUP("Payback",S4:V303,3,0) -> 6 | E13: Outubro | F13: =Inputs!B15 -> 750 | G13: ='Análise Técnica'!R9 -> 764.17505 | H13: =IF(G13-F13<0,F13-G13,0) -> 0 | I13: =IF(G13-F13>0,G13-F13,0) -> 14.175054 | J13: =$C$7 -> 100 | K13: =IF(H13-$C$7>0,H13-$C$7,0) -> 0 | L13: =IF(L12-(H13-$C$7)>0,IF(H13>0,IF(H13<$C$7,L12,L12-(H13-$C$7)),I13+L12),0) -> 166.46386 | M13: =K13 -> 0 | N13: =Inputs!C15 -> 937.5 | O13: =IF(I13>0, (J13*$C$8),(J13+M13)*$C$8) -> 125 | P13: =N13-O13 -> 812.5 | Q13: =1-(O13/N13) -> 0.86666667 | R13: =P13/$C$4 -> 0.057079654 | T13: 0 | U13: 10 | V13: Outubro | W13: ='Análise Técnica'!$C$3 -> 750 | X13: =G13 -> 764.17505 | Y13: =IF(X13-W13<0,W13-X13,0) -> 0 | Z13: =IF(X13-W13>0,X13-W13,0) -> 14.175054 | AA13: =$C$7 -> 100 | AB13: =IF(Y13-$C$7>0,Y13-$C$7,0) -> 0 | AC13: =IF(AC12-(Y13-$C$7)>0,IF(Y13>0,IF(Y13<$C$7,AC12,AC12-(Y13-$C$7)),Z13+AC12),0) -> 166.46386 | AD13: =IF(AB13-AC12<0,0,AB13-AC12) -> 0 | AE13: =($C$10*(1+$C$30)^T13) -> 937.5 | AF13: =IF(Z13>0,((AA13*$C$8)*((1+$C$30)^T13)),((AA13+AD13)*$C$8)*(1+$C$30)^T13) -> 125 | AG13: =AE13-AF13 -> 812.5 | AH13: =$C$28/12*($C$4*((1+$C$29)^T13))+IF($C$31=T13,$C$33/12,0) -> 0 | AI13: =AG13-AH13 -> 812.5 | AJ13: =AJ12+AI13 -> -6109.4942 | AK13: =1-(AF13/AE13) -> 0.86666667 | AL13: =AL12+AE13 -> 9375 | AM13: =AG13/$C$4 -> 0.057079654 | AO13: 10 | AP13: =($C$4*(1+($C$36-$C$39))^AO13)-AE13 -> 13705.486 | AQ13: =AJ13 -> -6109.4942
B14: Retorno no Primeiro Ano | C14: =J22/C4 -> 0.68495584 | E14: Novembro | F14: =Inputs!B16 -> 750 | G14: ='Análise Técnica'!S9 -> 769.68579 | H14: =IF(G14-F14<0,F14-G14,0) -> 0 | I14: =IF(G14-F14>0,G14-F14,0) -> 19.685789 | J14: =$C$7 -> 100 | K14: =IF(H14-$C$7>0,H14-$C$7,0) -> 0 | L14: =IF(L13-(H14-$C$7)>0,IF(H14>0,IF(H14<$C$7,L13,L13-(H14-$C$7)),I14+L13),0) -> 186.14965 | M14: =K14 -> 0 | N14: =Inputs!C16 -> 937.5 | O14: =IF(I14>0, (J14*$C$8),(J14+M14)*$C$8) -> 125 | P14: =N14-O14 -> 812.5 | Q14: =1-(O14/N14) -> 0.86666667 | R14: =P14/$C$4 -> 0.057079654 | T14: 0 | U14: 11 | V14: Novembro | W14: ='Análise Técnica'!$C$3 -> 750 | X14: =G14 -> 769.68579 | Y14: =IF(X14-W14<0,W14-X14,0) -> 0 | Z14: =IF(X14-W14>0,X14-W14,0) -> 19.685789 | AA14: =$C$7 -> 100 | AB14: =IF(Y14-$C$7>0,Y14-$C$7,0) -> 0 | AC14: =IF(AC13-(Y14-$C$7)>0,IF(Y14>0,IF(Y14<$C$7,AC13,AC13-(Y14-$C$7)),Z14+AC13),0) -> 186.14965 | AD14: =IF(AB14-AC13<0,0,AB14-AC13) -> 0 | AE14: =($C$10*(1+$C$30)^T14) -> 937.5 | AF14: =IF(Z14>0,((AA14*$C$8)*((1+$C$30)^T14)),((AA14+AD14)*$C$8)*(1+$C$30)^T14) -> 125 | AG14: =AE14-AF14 -> 812.5 | AH14: =$C$28/12*($C$4*((1+$C$29)^T14))+IF($C$31=T14,$C$33/12,0) -> 0 | AI14: =AG14-AH14 -> 812.5 | AJ14: =AJ13+AI14 -> -5296.9942 | AK14: =1-(AF14/AE14) -> 0.86666667 | AL14: =AL13+AE14 -> 10312.5 | AM14: =AG14/$C$4 -> 0.057079654 | AO14: 11 | AP14: =($C$4*(1+($C$36-$C$39))^AO14)-AE14 -> 13746.975 | AQ14: =AJ14 -> -5296.9942
B15: Retorno no Primeiro Ano $ | C15: =J22 -> 9750 | E15: Dezembro | F15: =Inputs!B17 -> 750 | G15: ='Análise Técnica'!T9 -> 883.05798 | H15: =IF(G15-F15<0,F15-G15,0) -> 0 | I15: =IF(G15-F15>0,G15-F15,0) -> 133.05798 | J15: =$C$7 -> 100 | K15: =IF(H15-$C$7>0,H15-$C$7,0) -> 0 | L15: =IF(L14-(H15-$C$7)>0,IF(H15>0,IF(H15<$C$7,L14,L14-(H15-$C$7)),I15+L14),0) -> 319.20763 | M15: =K15 -> 0 | N15: =Inputs!C17 -> 937.5 | O15: =IF(I15>0, (J15*$C$8),(J15+M15)*$C$8) -> 125 | P15: =N15-O15 -> 812.5 | Q15: =1-(O15/N15) -> 0.86666667 | R15: =P15/$C$4 -> 0.057079654 | T15: 0 | U15: 12 | V15: Dezembro | W15: ='Análise Técnica'!$C$3 -> 750 | X15: =G15 -> 883.05798 | Y15: =IF(X15-W15<0,W15-X15,0) -> 0 | Z15: =IF(X15-W15>0,X15-W15,0) -> 133.05798 | AA15: =$C$7 -> 100 | AB15: =IF(Y15-$C$7>0,Y15-$C$7,0) -> 0 | AC15: =IF(AC14-(Y15-$C$7)>0,IF(Y15>0,IF(Y15<$C$7,AC14,AC14-(Y15-$C$7)),Z15+AC14),0) -> 319.20763 | AD15: =IF(AB15-AC14<0,0,AB15-AC14) -> 0 | AE15: =($C$10*(1+$C$30)^T15) -> 937.5 | AF15: =IF(Z15>0,((AA15*$C$8)*((1+$C$30)^T15)),((AA15+AD15)*$C$8)*(1+$C$30)^T15) -> 125 | AG15: =AE15-AF15 -> 812.5 | AH15: =$C$28/12*($C$4*((1+$C$29)^T15))+IF($C$31=T15,$C$33/12,0) -> 0 | AI15: =AG15-AH15 -> 812.5 | AJ15: =AJ14+AI15 -> -4484.4942 | AK15: =1-(AF15/AE15) -> 0.86666667 | AL15: =AL14+AE15 -> 11250 | AM15: =AG15/$C$4 -> 0.057079654 | AO15: 12 | AP15: =($C$4*(1+($C$36-$C$39))^AO15)-AE15 -> 13788.581 | AQ15: =AJ15 -> -4484.4942
B16: Reais por Watt Instalado | C16: =C4/C3/1000 -> 2.2594435 | E16: Média | F16: =AVERAGE(F4:F15) -> 750 | G16: =AVERAGE(G4:G15) -> 736.58415 | H16: =AVERAGE(H4:H15) -> 62.855362 | I16: =AVERAGE(I4:I15) -> 49.439508 | J16: =AVERAGE(J4:J15) -> 100 | K16: =AVERAGE(K4:K15) -> 22.838872 | L16: =AVERAGE(L4:L15) -> 261.3798 | M16: =AVERAGE(M4:M15) -> 22.838872 | N16: =AVERAGE(N4:N15) -> 937.5 | O16: =O17/12 -> 153.54859 | P16: =P17/12 -> 783.95141 | Q16: =AVERAGE(Q4:Q15) -> 0.83621484 | R16: =AVERAGE(R4:R15) -> 0.055074061 | S16: =IF(AND(AJ16>0,AJ15<0),"Payback","") | T16: 1 | U16: 1 | V16: Janeiro | W16: ='Análise Técnica'!$C$3 -> 750 | X16: =X4*(1-$C$26) -> 902.12483 | Y16: =IF(X16-W16<0,W16-X16,0) -> 0 | Z16: =IF(X16-W16>0,X16-W16,0) -> 152.12483 | AA16: =$C$7 -> 100 | AB16: =IF(Y16-$C$7>0,Y16-$C$7,0) -> 0 | AC16: =IF(AC15-(Y16-$C$7)>0,IF(Y16>0,IF(Y16<$C$7,AC15,AC15-(Y16-$C$7)),Z16+AC15),0) -> 471.33246 | AD16: =IF(AB16-AC15<0,0,AB16-AC15) -> 0 | AE16: =($C$10*(1+$C$30)^T16) -> 1012.5 | AF16: =IF(Z16>0,((AA16*$C$8)*((1+$C$30)^T16)),((AA16+AD16)*$C$8)*(1+$C$30)^T16) -> 135 | AG16: =AE16-AF16 -> 877.5 | AH16: =$C$28/12*($C$4*((1+$C$29)^T16))+IF($C$31=T16,$C$33/12,0) -> 0 | AI16: =AG16-AH16 -> 877.5 | AJ16: =AJ15+AI16 -> -3606.9942 | AK16: =1-(AF16/AE16) -> 0.86666667 | AL16: =AL15+AE16 -> 12262.5 | AM16: =AG16/$C$4 -> 0.061646026 | AO16: 13 | AP16: =($C$4*(1+($C$36-$C$39))^AO16)-AE16 -> 13755.305 | AQ16: =AJ16 -> -3606.9942
B17: VPL | C17: =NPV($C$34,M22:M46) -> 162106.77 | E17: Total | F17: =SUM(F4:F15) -> 9000 | G17: =SUM(G4:G15) -> 8839.0098 | H17: =SUM(H4:H15) -> 754.26434 | I17: =SUM(I4:I15) -> 593.2741 | J17: =SUM(J4:J15) -> 1200 | K17: =SUM(K4:K15) -> 274.06646 | L17: =SUM(L4:L15) -> 3136.5576 | M17: =SUM(M4:M15) -> 274.06646 | ... P17: =SUM(P4:P15) -> 9407.4169 | R17: =SUM(R4:R15) -> 0.66088874 | S17: =IF(AND(AJ17>0,AJ16<0),"Payback","") | T17: 1 | U17: 2 | V17: Fevereiro | W17: ='Análise Técnica'!$C$3 -> 750 | X17: =X5*(1-$C$26) -> 950.13435 | Y17: =IF(X17-W17<0,W17-X17,0) -> 0 | Z17: =IF(X17-W17>0,X17-W17,0) -> 200.13435 | AA17: =$C$7 -> 100 | AB17: =IF(Y17-$C$7>0,Y17-$C$7,0) -> 0 | AC17: =IF(AC16-(Y17-$C$7)>0,IF(Y17>0,IF(Y17<$C$7,AC16,AC16-(Y17-$C$7)),Z17+AC16),0) -> 671.46681 | AD17: =IF(AB17-AC16<0,0,AB17-AC16) -> 0 | AE17: =($C$10*(1+$C$30)^T17) -> 1012.5 | AF17: =IF(Z17>0,((AA17*$C$8)*((1+$C$30)^T17)),((AA17+AD17)*$C$8)*(1+$C$30)^T17) -> 135 | AG17: =AE17-AF17 -> 877.5 | AH17: =$C$28/12*($C$4*((1+$C$29)^T17))+IF($C$31=T17,$C$33/12,0) -> 0 | AI17: =AG17-AH17 -> 877.5 | AJ17: =AJ16+AI17 -> -2729.4942 | AK17: =1-(AF17/AE17) -> 0.86666667 | AL17: =AL16+AE17 -> 13275 | AM17: =AG17/$C$4 -> 0.061646026 | AO17: 14 | AP17: =($C$4*(1+($C$36-$C$39))^AO17)-AE17 -> 13797.147 | AQ17: =AJ17 -> -2729.4942
B18: TIR | C18: =IRR(M22:M46) -> 2.4280909 | S18: =IF(AND(AJ18>0,AJ17<0),"Payback","") | T18: 1 | U18: 3 | V18: Março | W18: ='Análise Técnica'!$C$3 -> 750 | X18: =X6*(1-$C$26) -> 797.33255 | Y18: =IF(X18-W18<0,W18-X18,0) -> 0 | Z18: =IF(X18-W18>0,X18-W18,0) -> 47.332548 | AA18: =$C$7 -> 100 | AB18: =IF(Y18-$C$7>0,Y18-$C$7,0) -> 0 | AC18: =IF(AC17-(Y18-$C$7)>0,IF(Y18>0,IF(Y18<$C$7,AC17,AC17-(Y18-$C$7)),Z18+AC17),0) -> 718.79935 | AD18: =IF(AB18-AC17<0,0,AB18-AC17) -> 0 | AE18: =($C$10*(1+$C$30)^T18) -> 1012.5 | AF18: =IF(Z18>0,((AA18*$C$8)*((1+$C$30)^T18)),((AA18+AD18)*$C$8)*(1+$C$30)^T18) -> 135 | AG18: =AE18-AF18 -> 877.5 | AH18: =$C$28/12*($C$4*((1+$C$29)^T18))+IF($C$31=T18,$C$33/12,0) -> 0 | AI18: =AG18-AH18 -> 877.5 | AJ18: =AJ17+AI18 -> -1851.9942 | AK18: =1-(AF18/AE18) -> 0.86666667 | AL18: =AL17+AE18 -> 14287.5 | AM18: =AG18/$C$4 -> 0.061646026 | AO18: 15 | AP18: =($C$4*(1+($C$36-$C$39))^AO18)-AE18 -> 13839.107 | AQ18: =AJ18 -> -1851.9942
B19: Lucro Final do Projeto após 25 anos | C19: =N46 -> 666757.49 | S19: =IF(AND(AJ19>0,AJ18<0),"Payback","") | T19: 1 | U19: 4 | V19: Abril | W19: ='Análise Técnica'!$C$3 -> 750 | X19: =X7*(1-$C$26) -> 707.04929 | Y19: =IF(X19-W19<0,W19-X19,0) -> 42.95071 | Z19: =IF(X19-W19>0,X19-W19,0) -> 0 | AA19: =$C$7 -> 100 | AB19: =IF(Y19-$C$7>0,Y19-$C$7,0) -> 0 | AC19: =IF(AC18-(Y19-$C$7)>0,IF(Y19>0,IF(Y19<$C$7,AC18,AC18-(Y19-$C$7)),Z19+AC18),0) -> 718.79935 | AD19: =IF(AB19-AC18<0,0,AB19-AC18) -> 0 | AE19: =($C$10*(1+$C$30)^T19) -> 1012.5 | AF19: =IF(Z19>0,((AA19*$C$8)*((1+$C$30)^T19)),((AA19+AD19)*$C$8)*(1+$C$30)^T19) -> 135 | AG19: =AE19-AF19 -> 877.5 | AH19: =$C$28/12*($C$4*((1+$C$29)^T19))+IF($C$31=T19,$C$33/12,0) -> 0 | AI19: =AG19-AH19 -> 877.5 | AJ19: =AJ18+AI19 -> -974.49424 | AK19: =1-(AF19/AE19) -> 0.86666667 | AL19: =AL18+AE19 -> 15300 | AM19: =AG19/$C$4 -> 0.061646026 | AO19: 16 | AP19: =($C$4*(1+($C$36-$C$39))^AO19)-AE19 -> 13881.187 | AQ19: =AJ19 -> -974.49424
B20: ROI | C20: =(N46-C4)/C4 -> 45.840968 | E20: Demonstrativo Energético e Financeiro dos 25 anos do projeto: | S20: =IF(AND(AJ20>0,AJ19<0),"Payback","") | T20: 1 | U20: 5 | V20: Maio | W20: ='Análise Técnica'!$C$3 -> 750 | X20: =X8*(1-$C$26) -> 582.27762 | Y20: =IF(X20-W20<0,W20-X20,0) -> 167.72238 | Z20: =IF(X20-W20>0,X20-W20,0) -> 0 | AA20: =$C$7 -> 100 | AB20: =IF(Y20-$C$7>0,Y20-$C$7,0) -> 67.72238 | AC20: =IF(AC19-(Y20-$C$7)>0,IF(Y20>0,IF(Y20<$C$7,AC19,AC19-(Y20-$C$7)),Z20+AC19),0) -> 651.07697 | AD20: =IF(AB20-AC19<0,0,AB20-AC19) -> 0 | AE20: =($C$10*(1+$C$30)^T20) -> 1012.5 | AF20: =IF(Z20>0,((AA20*$C$8)*((1+$C$30)^T20)),((AA20+AD20)*$C$8)*(1+$C$30)^T20) -> 135 | AG20: =AE20-AF20 -> 877.5 | AH20: =$C$28/12*($C$4*((1+$C$29)^T20))+IF($C$31=T20,$C$33/12,0) -> 0 | AI20: =AG20-AH20 -> 877.5 | AJ20: =AJ19+AI20 -> -96.994245 | AK20: =1-(AF20/AE20) -> 0.86666667 | AL20: =AL19+AE20 -> 16312.5 | AM20: =AG20/$C$4 -> 0.061646026 | AO20: 17 | AP20: =($C$4*(1+($C$36-$C$39))^AO20)-AE20 -> 13923.386 | AQ20: =AJ20 -> -96.994245
B21: Geração Diária Média de Energia (kWh/dia) | C21: =C23/365 -> 22.222961 | E21: Ano | F21: Consumo | G21: Geração | H21: Sem Energia Solar | I21: Com Energia Solar | J21: Economia | K21: Economia % | L21: Custos | M21: Subtotal | N21: Fluxo Final | O21: Acumulado Sem ES | P21: Retorno Invest. | S21: =IF(AND(AJ21>0,AJ20<0),"Payback","") -> Payback | T21: 1 | U21: 6 | V21: Junho | W21: ='Análise Técnica'!$C$3 -> 750 | X21: =X9*(1-$C$26) -> 538.48515 | Y21: =IF(X21-W21<0,W21-X21,0) -> 211.51485 | Z21: =IF(X21-W21>0,X21-W21,0) -> 0 | AA21: =$C$7 -> 100 | AB21: =IF(Y21-$C$7>0,Y21-$C$7,0) -> 111.51485 | AC21: =IF(AC20-(Y21-$C$7)>0,IF(Y21>0,IF(Y21<$C$7,AC20,AC20-(Y21-$C$7)),Z21+AC20),0) -> 539.56213 | AD21: =IF(AB21-AC20<0,0,AB21-AC20) -> 0 | AE21: =($C$10*(1+$C$30)^T21) -> 1012.5 | AF21: =IF(Z21>0,((AA21*$C$8)*((1+$C$30)^T21)),((AA21+AD21)*$C$8)*(1+$C$30)^T21) -> 135 | AG21: =AE21-AF21 -> 877.5 | AH21: =$C$28/12*($C$4*((1+$C$29)^T21))+IF($C$31=T21,$C$33/12,0) -> 0 | AI21: =AG21-AH21 -> 877.5 | AJ21: =AJ20+AI21 -> 780.50576 | AK21: =1-(AF21/AE21) -> 0.86666667 | AL21: =AL20+AE21 -> 17325 | AM21: =AG21/$C$4 -> 0.061646026 | AO21: 18 | AP21: =($C$4*(1+($C$36-$C$39))^AO21)-AE21 -> 13965.704 | AQ21: =AJ21 -> 780.50576
B22: Geração Mensal Média de Energia (kWh/mês) | C22: =C23/12 -> 675.94839 | E22: 0 | F22: =SUM(W4:W15) -> 9000 | G22: =SUM(X4:X15) -> 8839.0098 | H22: =SUM(AE4:AE15) -> 11250 | I22: =SUM(AF4:AF15) -> 1500 | J22: =SUM(AG4:AG15) -> 9750 | K22: =J22/H22 -> 0.86666667 | L22: =SUM(AH4:AH15) -> 14234.494 | M22: =SUM(AI4:AI15) -> -4484.4942 | N22: =M22 -> -4484.4942 | O22: =-H22 -> -11250 | P22: =J22/$C$4 -> 0.68495584 | S22: =IF(AND(AJ22>0,AJ21<0),"Payback","") | T22: 1 | U22: 7 | V22: Julho | W22: ='Análise Técnica'!$C$3 -> 750 | X22: =X10*(1-$C$26) -> 538.41143 | Y22: =IF(X22-W22<0,W22-X22,0) -> 211.58857 | Z22: =IF(X22-W22>0,X22-W22,0) -> 0 | AA22: =$C$7 -> 100 | AB22: =IF(Y22-$C$7>0,Y22-$C$7,0) -> 111.58857 | AC22: =IF(AC21-(Y22-$C$7)>0,IF(Y22>0,IF(Y22<$C$7,AC21,AC21-(Y22-$C$7)),Z22+AC21),0) -> 427.97356 | AD22: =IF(AB22-AC21<0,0,AB22-AC21) -> 0 | AE22: =($C$10*(1+$C$30)^T22) -> 1012.5 | AF22: =IF(Z22>0,((AA22*$C$8)*((1+$C$30)^T22)),((AA22+AD22)*$C$8)*(1+$C$30)^T22) -> 135 | AG22: =AE22-AF22 -> 877.5 | AH22: =$C$28/12*($C$4*((1+$C$29)^T22))+IF($C$31=T22,$C$33/12,0) -> 0 | AI22: =AG22-AH22 -> 877.5 | AJ22: =AJ21+AI22 -> 1658.0058 | AK22: =1-(AF22/AE22) -> 0.86666667 | AL22: =AL21+AE22 -> 18337.5 | AM22: =AG22/$C$4 -> 0.061646026 | AO22: 19 | AP22: =($C$4*(1+($C$36-$C$39))^AO22)-AE22 -> 14008.142 | AQ22: =AJ22 -> 1658.0058
B23: Geração Anual Média de Energia (kWh/ano) | C23: =AVERAGE(G22:G46) -> 8111.3806 | D23: =IF(AND(N23>0,N22<0),"Payback","") -> Payback | E23: 1 | F23: =SUM(W16:W27) -> 9000 | G23: =SUM(X16:X27) -> 8750.6197 | H23: =SUM(AE16:AE27) -> 12150 | I23: =SUM(AF16:AF27) -> 1620 | J23: =SUM(AG16:AG27) -> 10530 | K23: =J23/H23 -> 0.86666667 | L23: =SUM(AH16:AH27) -> 0 | M23: =SUM(AI16:AI27) -> 10530 | N23: =M22+M23 -> 6045.5058 | O23: =O22-H23 -> -23400 | P23: =J23/$C$4 -> 0.73975231 | S23: =IF(AND(AJ23>0,AJ22<0),"Payback","") | T23: 1 | U23: 8 | V23: Agosto | W23: ='Análise Técnica'!$C$3 -> 750 | X23: =X11*(1-$C$26) -> 665.79295 | Y23: =IF(X23-W23<0,W23-X23,0) -> 84.207048 | Z23: =IF(X23-W23>0,X23-W23,0) -> 0 | AA23: =$C$7 -> 100 | AB23: =IF(Y23-$C$7>0,Y23-$C$7,0) -> 0 | AC23: =IF(AC22-(Y23-$C$7)>0,IF(Y23>0,IF(Y23<$C$7,AC22,AC22-(Y23-$C$7)),Z23+AC22),0) -> 427.97356 | AD23: =IF(AB23-AC22<0,0,AB23-AC22) -> 0 | AE23: =($C$10*(1+$C$30)^T23) -> 1012.5 | AF23: =IF(Z23>0,((AA23*$C$8)*((1+$C$30)^T23)),((AA23+AD23)*$C$8)*(1+$C$30)^T23) -> 135 | AG23: =AE23-AF23 -> 877.5 | AH23: =$C$28/12*($C$4*((1+$C$29)^T23))+IF($C$31=T23,$C$33/12,0) -> 0 | AI23: =AG23-AH23 -> 877.5 | AJ23: =AJ22+AI23 -> 2535.5058 | AK23: =1-(AF23/AE23) -> 0.86666667 | AL23: =AL22+AE23 -> 19350 | AM23: =AG23/$C$4 -> 0.061646026 | AO23: 20 | AP23: =($C$4*(1+($C$36-$C$39))^AO23)-AE23 -> 14050.701 | AQ23: =AJ23 -> 2535.5058
B24: Custo do Kwh Solar (Valor Presente) | C24: =((I48+L48)/F48)/((1+$C$30)^25) -> 0.10103423 | D24: =IF(AND(N24>0,N23<0),"Payback","") | E24: 2 | F24: =SUM(W28:W39) -> 9000 | G24: =SUM(X28:X39) -> 8689.3653 | H24: =SUM(AE28:AE39) -> 13122 | I24: =SUM(AF28:AF39) -> 1749.6 | J24: =SUM(AG28:AG39) -> 11372.4 | K24: =J24/H24 -> 0.86666667 | L24: =SUM(AH28:AH39) -> 0 | M24: =SUM(AI28:AI39) -> 11372.4 | N24: =M24+N23 -> 17417.906 | O24: =O23-H24 -> -36522 | P24: =J24/$C$4 -> 0.79893249 | S24: =IF(AND(AJ24>0,AJ23<0),"Payback","") | T24: 1 | U24: 9 | V24: Setembro | W24: ='Análise Técnica'!$C$3 -> 750 | X24: =X12*(1-$C$26) -> 676.26186 | Y24: =IF(X24-W24<0,W24-X24,0) -> 73.738142 | Z24: =IF(X24-W24>0,X24-W24,0) -> 0 | AA24: =$C$7 -> 100 | AB24: =IF(Y24-$C$7>0,Y24-$C$7,0) -> 0 | AC24: =IF(AC23-(Y24-$C$7)>0,IF(Y24>0,IF(Y24<$C$7,AC23,AC23-(Y24-$C$7)),Z24+AC23),0) -> 427.97356 | AD24: =IF(AB24-AC23<0,0,AB24-AC23) -> 0 | AE24: =($C$10*(1+$C$30)^T24) -> 1012.5 | AF24: =IF(Z24>0,((AA24*$C$8)*((1+$C$30)^T24)),((AA24+AD24)*$C$8)*(1+$C$30)^T24) -> 135 | AG24: =AE24-AF24 -> 877.5 | AH24: =$C$28/12*($C$4*((1+$C$29)^T24))+IF($C$31=T24,$C$33/12,0) -> 0 | AI24: =AG24-AH24 -> 877.5 | AJ24: =AJ23+AI24 -> 3413.0058 | AK24: =1-(AF24/AE24) -> 0.86666667 | AL24: =AL23+AE24 -> 20362.5 | AM24: =AG24/$C$4 -> 0.061646026 | AO24: 21 | AP24: =($C$4*(1+($C$36-$C$39))^AO24)-AE24 -> 14093.38 | AQ24: =AJ24 -> 3413.0058
B25: Premissas e Taxas | D25: =IF(AND(N25>0,N24<0),"Payback","") | E25: 3 | F25: =SUM(W40:W51) -> 9000 | G25: =SUM(X40:X51) -> 8628.5398 | H25: =SUM(AE40:AE51) -> 14171.76 | I25: =SUM(AF40:AF51) -> 1889.568 | J25: =SUM(AG40:AG51) -> 12282.192 | K25: =J25/H25 -> 0.86666667 | L25: =SUM(AH40:AH51) -> 0 | M25: =SUM(AI40:AI51) -> 12282.192 | N25: =M25+N24 -> 29700.098 | O25: =O24-H25 -> -50693.76 | P25: =J25/$C$4 -> 0.86284709 | S25: =IF(AND(AJ25>0,AJ24<0),"Payback","") | T25: 1 | U25: 10 | V25: Outubro | W25: ='Análise Técnica'!$C$3 -> 750 | X25: =X13*(1-$C$26) -> 756.5333 | Y25: =IF(X25-W25<0,W25-X25,0) -> 0 | Z25: =IF(X25-W25>0,X25-W25,0) -> 6.5333034 | AA25: =$C$7 -> 100 | AB25: =IF(Y25-$C$7>0,Y25-$C$7,0) -> 0 | AC25: =IF(AC24-(Y25-$C$7)>0,IF(Y25>0,IF(Y25<$C$7,AC24,AC24-(Y25-$C$7)),Z25+AC24),0) -> 434.50686 | AD25: =IF(AB25-AC24<0,0,AB25-AC24) -> 0 | AE25: =($C$10*(1+$C$30)^T25) -> 1012.5 | AF25: =IF(Z25>0,((AA25*$C$8)*((1+$C$30)^T25)),((AA25+AD25)*$C$8)*(1+$C$30)^T25) -> 135 | AG25: =AE25-AF25 -> 877.5 | AH25: =$C$28/12*($C$4*((1+$C$29)^T25))+IF($C$31=T25,$C$33/12,0) -> 0 | AI25: =AG25-AH25 -> 877.5 | AJ25: =AJ24+AI25 -> 4290.5058 | AK25: =1-(AF25/AE25) -> 0.86666667 | AL25: =AL24+AE25 -> 21375 | AM25: =AG25/$C$4 -> 0.061646026 | AO25: 22 | AP25: =($C$4*(1+($C$36-$C$39))^AO25)-AE25 -> 14136.18 | AQ25: =AJ25 -> 4290.5058
B26: Degradação do Painéis Ano 1 | C26: 0.01 | D26: =IF(AND(N26>0,N25<0),"Payback","") | E26: 4 | F26: =SUM(W52:W63) -> 9000 | G26: =SUM(X52:X63) -> 8568.14 | H26: =SUM(AE52:AE63) -> 15305.501 | I26: =SUM(AF52:AF63) -> 2040.7334 | J26: =SUM(AG52:AG63) -> 13264.767 | K26: =J26/H26 -> 0.86666667 | L26: =SUM(AH52:AH63) -> 0 | M26: =SUM(AI52:AI63) -> 13264.767 | N26: =M26+N25 -> 42964.865 | O26: =O25-H26 -> -65999.261 | P26: =J26/$C$4 -> 0.93187486 | S26: =IF(AND(AJ26>0,AJ25<0),"Payback","") | T26: 1 | U26: 11 | V26: Novembro | W26: ='Análise Técnica'!$C$3 -> 750 | X26: =X14*(1-$C$26) -> 761.98893 | Y26: =IF(X26-W26<0,W26-X26,0) -> 0 | Z26: =IF(X26-W26>0,X26-W26,0) -> 11.988931 | AA26: =$C$7 -> 100 | AB26: =IF(Y26-$C$7>0,Y26-$C$7,0) -> 0 | AC26: =IF(AC25-(Y26-$C$7)>0,IF(Y26>0,IF(Y26<$C$7,AC25,AC25-(Y26-$C$7)),Z26+AC25),0) -> 446.49579 | AD26: =IF(AB26-AC25<0,0,AB26-AC25) -> 0 | AE26: =($C$10*(1+$C$30)^T26) -> 1012.5 | AF26: =IF(Z26>0,((AA26*$C$8)*((1+$C$30)^T26)),((AA26+AD26)*$C$8)*(1+$C$30)^T26) -> 135 | AG26: =AE26-AF26 -> 877.5 | AH26: =$C$28/12*($C$4*((1+$C$29)^T26))+IF($C$31=T26,$C$33/12,0) -> 0 | AI26: =AG26-AH26 -> 877.5 | AJ26: =AJ25+AI26 -> 5168.0058 | AK26: =1-(AF26/AE26) -> 0.86666667 | AL26: =AL25+AE26 -> 22387.5 | AM26: =AG26/$C$4 -> 0.061646026 | AO26: 23 | AP26: =($C$4*(1+($C$36-$C$39))^AO26)-AE26 -> 14179.101 | AQ26: =AJ26 -> 5168.0058
B27: Degradação outros anos | C27: 0.007 | D27: =IF(AND(N27>0,N26<0),"Payback","") | E27: 5 | F27: =SUM(W64:W75) -> 9000 | G27: =SUM(X64:X75) -> 8508.163 | H27: =SUM(AE64:AE75) -> 16529.941 | I27: =SUM(AF64:AF75) -> 2203.9921 | J27: =SUM(AG64:AG75) -> 14325.949 | K27: =J27/H27 -> 0.86666667 | L27: =SUM(AH64:AH75) -> 0 | M27: =SUM(AI64:AI75) -> 14325.949 | N27: =M27+N26 -> 57290.814 | O27: =O26-H27 -> -82529.202 | P27: =J27/$C$4 -> 1.0064249 | S27: =IF(AND(AJ27>0,AJ26<0),"Payback","") | T27: 1 | U27: 12 | V27: Dezembro | W27: ='Análise Técnica'!$C$3 -> 750 | X27: =X15*(1-$C$26) -> 874.2274 | Y27: =IF(X27-W27<0,W27-X27,0) -> 0 | Z27: =IF(X27-W27>0,X27-W27,0) -> 124.2274 | AA27: =$C$7 -> 100 | AB27: =IF(Y27-$C$7>0,Y27-$C$7,0) -> 0 | AC27: =IF(AC26-(Y27-$C$7)>0,IF(Y27>0,IF(Y27<$C$7,AC26,AC26-(Y27-$C$7)),Z27+AC26),0) -> 570.72319 | AD27: =IF(AB27-AC26<0,0,AB27-AC26) -> 0 | AE27: =($C$10*(1+$C$30)^T27) -> 1012.5 | AF27: =IF(Z27>0,((AA27*$C$8)*((1+$C$30)^T27)),((AA27+AD27)*$C$8)*(1+$C$30)^T27) -> 135 | AG27: =AE27-AF27 -> 877.5 | AH27: =$C$28/12*($C$4*((1+$C$29)^T27))+IF($C$31=T27,$C$33/12,0) -> 0 | AI27: =AG27-AH27 -> 877.5 | AJ27: =AJ26+AI27 -> 6045.5058 | AK27: =1-(AF27/AE27) -> 0.86666667 | AL27: =AL26+AE27 -> 23400 | AM27: =AG27/$C$4 -> 0.061646026 | AO27: 24 | AP27: =($C$4*(1+($C$36-$C$39))^AO27)-AE27 -> 14222.144 | AQ27: =AJ27 -> 6045.5058
B28: Custo de Manutenção / Ano | C28: 0 | D28: =IF(AND(N28>0,N27<0),"Payback","") | E28: 6 | F28: =SUM(W76:W87) -> 9000 | G28: =SUM(X76:X87) -> 8448.6059 | H28: =SUM(AE76:AE87) -> 17852.336 | I28: =SUM(AF76:AF87) -> 2380.3115 | J28: =SUM(AG76:AG87) -> 15472.025 | K28: =J28/H28 -> 0.86666667 | L28: =SUM(AH76:AH87) -> 0 | M28: =SUM(AI76:AI87) -> 15472.025 | N28: =M28+N27 -> 72762.839 | O28: =O27-H28 -> -100381.54 | P28: =J28/$C$4 -> 1.0869388 | S28: =IF(AND(AJ28>0,AJ27<0),"Payback","") | T28: 2 | U28: 1 | V28: Janeiro | W28: ='Análise Técnica'!$C$3 -> 750 | X28: =X16*((1-$C$27)) -> 895.80995 | Y28: =IF(X28-W28<0,W28-X28,0) -> 0 | Z28: =IF(X28-W28>0,X28-W28,0) -> 145.80995 | AA28: =$C$7 -> 100 | AB28: =IF(Y28-$C$7>0,Y28-$C$7,0) -> 0 | AC28: =IF(AC27-(Y28-$C$7)>0,IF(Y28>0,IF(Y28<$C$7,AC27,AC27-(Y28-$C$7)),Z28+AC27),0) -> 716.53315 | AD28: =IF(AB28-AC27<0,0,AB28-AC27) -> 0 | AE28: =($C$10*(1+$C$30)^T28) -> 1093.5 | AF28: =IF(Z28>0,((AA28*$C$8)*((1+$C$30)^T28)),((AA28+AD28)*$C$8)*(1+$C$30)^T28) -> 145.8 | AG28: =AE28-AF28 -> 947.7 | AH28: =$C$28/12*($C$4*((1+$C$29)^T28))+IF($C$31=T28,$C$33/12,0) -> 0 | AI28: =AG28-AH28 -> 947.7 | AJ28: =AJ27+AI28 -> 6993.2058 | AK28: =1-(AF28/AE28) -> 0.86666667 | AL28: =AL27+AE28 -> 24493.5 | AM28: =AG28/$C$4 -> 0.066577708 | AO28: 25 | AP28: =($C$4*(1+($C$36-$C$39))^AO28)-AE28 -> 14184.309 | AQ28: =AJ28 -> 6993.2058
B29: Inflação Projetada (%a.a.) | C29: 0.05 | D29: =IF(AND(N29>0,N28<0),"Payback","") | E29: 7 | F29: =SUM(W88:W99) -> 9000 | G29: =SUM(X88:X99) -> 8389.4656 | H29: =SUM(AE88:AE99) -> 19280.523 | I29: =SUM(AF88:AF99) -> 2570.7364 | J29: =SUM(AG88:AG99) -> 16709.787 | K29: =J29/H29 -> 0.86666667 | L29: =SUM(AH88:AH99) -> 0 | M29: =SUM(AI88:AI99) -> 16709.787 | N29: =M29+N28 -> 89472.625 | O29: =O28-H29 -> -119662.06 | P29: =J29/$C$4 -> 1.1738939 | S29: =IF(AND(AJ29>0,AJ28<0),"Payback","") | T29: 2 | U29: 2 | V29: Fevereiro | W29: ='Análise Técnica'!$C$3 -> 750 | X29: =X17*((1-$C$27)) -> 943.48341 | Y29: =IF(X29-W29<0,W29-X29,0) -> 0 | Z29: =IF(X29-W29>0,X29-W29,0) -> 193.48341 | AA29: =$C$7 -> 100 | AB29: =IF(Y29-$C$7>0,Y29-$C$7,0) -> 0 | AC29: =IF(AC28-(Y29-$C$7)>0,IF(Y29>0,IF(Y29<$C$7,AC28,AC28-(Y29-$C$7)),Z29+AC28),0) -> 910.01655 | AD29: =IF(AB29-AC28<0,0,AB29-AC28) -> 0 | AE29: =($C$10*(1+$C$30)^T29) -> 1093.5 | AF29: =IF(Z29>0,((AA29*$C$8)*((1+$C$30)^T29)),((AA29+AD29)*$C$8)*(1+$C$30)^T29) -> 145.8 | AG29: =AE29-AF29 -> 947.7 | AH29: =$C$28/12*($C$4*((1+$C$29)^T29))+IF($C$31=T29,$C$33/12,0) -> 0 | AI29: =AG29-AH29 -> 947.7 | AJ29: =AJ28+AI29 -> 7940.9058 | AK29: =1-(AF29/AE29) -> 0.86666667 | AL29: =AL28+AE29 -> 25587 | AM29: =AG29/$C$4 -> 0.066577708 | AO29: 26 | AP29: =($C$4*(1+($C$36-$C$39))^AO29)-AE29 -> 14227.596 | AQ29: =AJ29 -> 7940.9058
B30: Inflação Energética Projetada (%a.a.) | C30: 0.08 | D30: =IF(AND(N30>0,N29<0),"Payback","") | E30: 8 | F30: =SUM(W100:W111) -> 9000 | G30: =SUM(X100:X111) -> 8330.7394 | H30: =SUM(AE100:AE111) -> 20822.965 | I30: =SUM(AF100:AF111) -> 2776.3953 | J30: =SUM(AG100:AG111) -> 18046.57 | K30: =J30/H30 -> 0.86666667 | L30: =SUM(AH100:AH111) -> 0 | M30: =SUM(AI100:AI111) -> 18046.57 | N30: =M30+N29 -> 107519.19 | O30: =O29-H30 -> -140485.03 | P30: =J30/$C$4 -> 1.2678055 | S30: =IF(AND(AJ30>0,AJ29<0),"Payback","") | T30: 2 | U30: 3 | V30: Março | W30: ='Análise Técnica'!$C$3 -> 750 | X30: =X18*((1-$C$27)) -> 791.75122 | Y30: =IF(X30-W30<0,W30-X30,0) -> 0 | Z30: =IF(X30-W30>0,X30-W30,0) -> 41.75122 | AA30: =$C$7 -> 100 | AB30: =IF(Y30-$C$7>0,Y30-$C$7,0) -> 0 | AC30: =IF(AC29-(Y30-$C$7)>0,IF(Y30>0,IF(Y30<$C$7,AC29,AC29-(Y30-$C$7)),Z30+AC29),0) -> 951.76777 | AD30: =IF(AB30-AC29<0,0,AB30-AC29) -> 0 | AE30: =($C$10*(1+$C$30)^T30) -> 1093.5 | AF30: =IF(Z30>0,((AA30*$C$8)*((1+$C$30)^T30)),((AA30+AD30)*$C$8)*(1+$C$30)^T30) -> 145.8 | AG30: =AE30-AF30 -> 947.7 | AH30: =$C$28/12*($C$4*((1+$C$29)^T30))+IF($C$31=T30,$C$33/12,0) -> 0 | AI30: =AG30-AH30 -> 947.7 | AJ30: =AJ29+AI30 -> 8888.6058 | AK30: =1-(AF30/AE30) -> 0.86666667 | AL30: =AL29+AE30 -> 26680.5 | AM30: =AG30/$C$4 -> 0.066577708 | AO30: 27 | AP30: =($C$4*(1+($C$36-$C$39))^AO30)-AE30 -> 14271.006 | AQ30: =AJ30 -> 8888.6058
B31: Ano de troca do Inversor | C31: 15 | D31: =IF(AND(N31>0,N30<0),"Payback","") | E31: 9 | F31: =SUM(W112:W123) -> 9000 | G31: =SUM(X112:X123) -> 8272.4242 | H31: =SUM(AE112:AE123) -> 22488.802 | I31: =SUM(AF112:AF123) -> 2998.5069 | J31: =SUM(AG112:AG123) -> 19490.295 | K31: =J31/H31 -> 0.86666667 | L31: =SUM(AH112:AH123) -> 0 | M31: =SUM(AI112:AI123) -> 19490.295 | N31: =M31+N30 -> 127009.49 | O31: =O30-H31 -> -162973.83 | P31: =J31/$C$4 -> 1.3692299 | S31: =IF(AND(AJ31>0,AJ30<0),"Payback","") | T31: 2 | U31: 4 | V31: Abril | W31: ='Análise Técnica'!$C$3 -> 750 | X31: =X19*((1-$C$27)) -> 702.09994 | Y31: =IF(X31-W31<0,W31-X31,0) -> 47.900055 | Z31: =IF(X31-W31>0,X31-W31,0) -> 0 | AA31: =$C$7 -> 100 | AB31: =IF(Y31-$C$7>0,Y31-$C$7,0) -> 0 | AC31: =IF(AC30-(Y31-$C$7)>0,IF(Y31>0,IF(Y31<$C$7,AC30,AC30-(Y31-$C$7)),Z31+AC30),0) -> 951.76777 | AD31: =IF(AB31-AC30<0,0,AB31-AC30) -> 0 | AE31: =($C$10*(1+$C$30)^T31) -> 1093.5 | AF31: =IF(Z31>0,((AA31*$C$8)*((1+$C$30)^T31)),((AA31+AD31)*$C$8)*(1+$C$30)^T31) -> 145.8 | AG31: =AE31-AF31 -> 947.7 | AH31: =$C$28/12*($C$4*((1+$C$29)^T31))+IF($C$31=T31,$C$33/12,0) -> 0 | AI31: =AG31-AH31 -> 947.7 | AJ31: =AJ30+AI31 -> 9836.3058 | AK31: =1-(AF31/AE31) -> 0.86666667 | AL31: =AL30+AE31 -> 27774 | AM31: =AG31/$C$4 -> 0.066577708 | AO31: 28 | AP31: =($C$4*(1+($C$36-$C$39))^AO31)-AE31 -> 14314.538 | AQ31: =AJ31 -> 9836.3058
B32: Estimativa Custo % do Inversor no Sistema | C32: 0.15 | D32: =IF(AND(N32>0,N31<0),"Payback","") | E32: 10 | F32: =SUM(W124:W135) -> 9000 | G32: =SUM(X124:X135) -> 8214.5172 | H32: =SUM(AE124:AE135) -> 24287.906 | I32: =SUM(AF124:AF135) -> 3238.3875 | J32: =SUM(AG124:AG135) -> 21049.519 | K32: =J32/H32 -> 0.86666667 | L32: =SUM(AH124:AH135) -> 0 | M32: =SUM(AI124:AI135) -> 21049.519 | N32: =M32+N31 -> 148059.01 | O32: =O31-H32 -> -187261.73 | P32: =J32/$C$4 -> 1.4787683 | S32: =IF(AND(AJ32>0,AJ31<0),"Payback","") | T32: 2 | U32: 5 | V32: Maio | W32: ='Análise Técnica'!$C$3 -> 750 | X32: =X20*((1-$C$27)) -> 578.20168 | Y32: =IF(X32-W32<0,W32-X32,0) -> 171.79832 | Z32: =IF(X32-W32>0,X32-W32,0) -> 0 | AA32: =$C$7 -> 100 | AB32: =IF(Y32-$C$7>0,Y32-$C$7,0) -> 71.798323 | AC32: =IF(AC31-(Y32-$C$7)>0,IF(Y32>0,IF(Y32<$C$7,AC31,AC31-(Y32-$C$7)),Z32+AC31),0) -> 879.96945 | AD32: =IF(AB32-AC31<0,0,AB32-AC31) -> 0 | AE32: =($C$10*(1+$C$30)^T32) -> 1093.5 | AF32: =IF(Z32>0,((AA32*$C$8)*((1+$C$30)^T32)),((AA32+AD32)*$C$8)*(1+$C$30)^T32) -> 145.8 | AG32: =AE32-AF32 -> 947.7 | AH32: =$C$28/12*($C$4*((1+$C$29)^T32))+IF($C$31=T32,$C$33/12,0) -> 0 | AI32: =AG32-AH32 -> 947.7 | AJ32: =AJ31+AI32 -> 10784.006 | AK32: =1-(AF32/AE32) -> 0.86666667 | AL32: =AL31+AE32 -> 28867.5 | AM32: =AG32/$C$4 -> 0.066577708 | AO32: 29 | AP32: =($C$4*(1+($C$36-$C$39))^AO32)-AE32 -> 14358.195 | AQ32: =AJ32 -> 10784.006
B33: Estim. Custo % do Inversor no Sist. ano troca | C33: =C32*C4 -> 2135.1741 | D33: =IF(AND(N33>0,N32<0),"Payback","") | E33: 11 | F33: =SUM(W136:W147) -> 9000 | G33: =SUM(X136:X147) -> 8157.0156 | H33: =SUM(AE136:AE147) -> 26230.939 | I33: =SUM(AF136:AF147) -> 3497.4585 | J33: =SUM(AG136:AG147) -> 22733.48 | K33: =J33/H33 -> 0.86666667 | L33: =SUM(AH136:AH147) -> 0 | M33: =SUM(AI136:AI147) -> 22733.48 | N33: =M33+N32 -> 170792.49 | O33: =O32-H33 -> -213492.67 | P33: =J33/$C$4 -> 1.5970698 | S33: =IF(AND(AJ33>0,AJ32<0),"Payback","") | T33: 2 | U33: 6 | V33: Junho | W33: ='Análise Técnica'!$C$3 -> 750 | X33: =X21*((1-$C$27)) -> 534.71576 | Y33: =IF(X33-W33<0,W33-X33,0) -> 215.28424 | Z33: =IF(X33-W33>0,X33-W33,0) -> 0 | AA33: =$C$7 -> 100 | AB33: =IF(Y33-$C$7>0,Y33-$C$7,0) -> 115.28424 | AC33: =IF(AC32-(Y33-$C$7)>0,IF(Y33>0,IF(Y33<$C$7,AC32,AC32-(Y33-$C$7)),Z33+AC32),0) -> 764.6852 | AD33: =IF(AB33-AC32<0,0,AB33-AC32) -> 0 | AE33: =($C$10*(1+$C$30)^T33) -> 1093.5 | AF33: =IF(Z33>0,((AA33*$C$8)*((1+$C$30)^T33)),((AA33+AD33)*$C$8)*(1+$C$30)^T33) -> 145.8 | AG33: =AE33-AF33 -> 947.7 | AH33: =$C$28/12*($C$4*((1+$C$29)^T33))+IF($C$31=T33,$C$33/12,0) -> 0 | AI33: =AG33-AH33 -> 947.7 | AJ33: =AJ32+AI33 -> 11731.706 | AK33: =1-(AF33/AE33) -> 0.86666667 | AL33: =AL32+AE33 -> 29961 | AM33: =AG33/$C$4 -> 0.066577708 | AO33: 30 | AP33: =($C$4*(1+($C$36-$C$39))^AO33)-AE33 -> 14401.974 | AQ33: =AJ33 -> 11731.706
B34: Custo de Capital (Wacc) | C34: 0.1 | D34: =IF(AND(N34>0,N33<0),"Payback","") | E34: 12 | F34: =SUM(W148:W159) -> 9000 | G34: =SUM(X148:X159) -> 8099.9165 | H34: =SUM(AE148:AE159) -> 28329.414 | I34: =SUM(AF148:AF159) -> 3777.2552 | J34: =SUM(AG148:AG159) -> 24552.159 | K34: =J34/H34 -> 0.86666667 | L34: =SUM(AH148:AH159) -> 0 | M34: =SUM(AI148:AI159) -> 24552.159 | N34: =M34+N33 -> 195344.65 | O34: =O33-H34 -> -241822.09 | P34: =J34/$C$4 -> 1.7248353 | S34: =IF(AND(AJ34>0,AJ33<0),"Payback","") | T34: 2 | U34: 7 | V34: Julho | W34: ='Análise Técnica'!$C$3 -> 750 | X34: =X22*((1-$C$27)) -> 534.64255 | Y34: =IF(X34-W34<0,W34-X34,0) -> 215.35745 | Z34: =IF(X34-W34>0,X34-W34,0) -> 0 | AA34: =$C$7 -> 100 | AB34: =IF(Y34-$C$7>0,Y34-$C$7,0) -> 115.35745 | AC34: =IF(AC33-(Y34-$C$7)>0,IF(Y34>0,IF(Y34<$C$7,AC33,AC33-(Y34-$C$7)),Z34+AC33),0) -> 649.32775 | AD34: =IF(AB34-AC33<0,0,AB34-AC33) -> 0 | AE34: =($C$10*(1+$C$30)^T34) -> 1093.5 | AF34: =IF(Z34>0,((AA34*$C$8)*((1+$C$30)^T34)),((AA34+AD34)*$C$8)*(1+$C$30)^T34) -> 145.8 | AG34: =AE34-AF34 -> 947.7 | AH34: =$C$28/12*($C$4*((1+$C$29)^T34))+IF($C$31=T34,$C$33/12,0) -> 0 | AI34: =AG34-AH34 -> 947.7 | AJ34: =AJ33+AI34 -> 12679.406 | AK34: =1-(AF34/AE34) -> 0.86666667 | AL34: =AL33+AE34 -> 31054.5 | AM34: =AG34/$C$4 -> 0.066577708 | AO34: 31 | AP34: =($C$4*(1+($C$36-$C$39))^AO34)-AE34 -> 14445.878 | AQ34: =AJ34 -> 12679.406
B35: Indices Monetários | D35: =IF(AND(N35>0,N34<0),"Payback","") | E35: 13 | F35: =SUM(W160:W171) -> 9000 | G35: =SUM(X160:X171) -> 8043.2171 | H35: =SUM(AE160:AE171) -> 30595.767 | I35: =SUM(AF160:AF171) -> 4079.4356 | J35: =SUM(AG160:AG171) -> 26516.331 | K35: =J35/H35 -> 0.86666667 | L35: =SUM(AH160:AH171) -> 0 | M35: =SUM(AI160:AI171) -> 26516.331 | N35: =M35+N34 -> 221860.98 | O35: =O34-H35 -> -272417.85 | P35: =J35/$C$4 -> 1.8628222 | S35: =IF(AND(AJ35>0,AJ34<0),"Payback","") | T35: 2 | U35: 8 | V35: Agosto | W35: ='Análise Técnica'!$C$3 -> 750 | X35: =X23*((1-$C$27)) -> 661.1324 | Y35: =IF(X35-W35<0,W35-X35,0) -> 88.867599 | Z35: =IF(X35-W35>0,X35-W35,0) -> 0 | AA35: =$C$7 -> 100 | AB35: =IF(Y35-$C$7>0,Y35-$C$7,0) -> 0 | AC35: =IF(AC34-(Y35-$C$7)>0,IF(Y35>0,IF(Y35<$C$7,AC34,AC34-(Y35-$C$7)),Z35+AC34),0) -> 649.32775 | AD35: =IF(AB35-AC34<0,0,AB35-AC34) -> 0 | AE35: =($C$10*(1+$C$30)^T35) -> 1093.5 | AF35: =IF(Z35>0,((AA35*$C$8)*((1+$C$30)^T35)),((AA35+AD35)*$C$8)*(1+$C$30)^T35) -> 145.8 | AG35: =AE35-AF35 -> 947.7 | AH35: =$C$28/12*($C$4*((1+$C$29)^T35))+IF($C$31=T35,$C$33/12,0) -> 0 | AI35: =AG35-AH35 -> 947.7 | AJ35: =AJ34+AI35 -> 13627.106 | AK35: =1-(AF35/AE35) -> 0.86666667 | AL35: =AL34+AE35 -> 32148 | AM35: =AG35/$C$4 -> 0.066577708 | AO35: 32 | AP35: =($C$4*(1+($C$36-$C$39))^AO35)-AE35 -> 14489.906 | AQ35: =AJ35 -> 13627.106
B36: Poupança (a.m.) | C36: 0.007 | D36: =IF(AND(N36>0,N35<0),"Payback","") | E36: 14 | F36: =SUM(W172:W183) -> 9000 | G36: =SUM(X172:X183) -> 7986.9146 | H36: =SUM(AE172:AE183) -> 33043.428 | I36: =SUM(AF172:AF183) -> 4405.7904 | J36: =SUM(AG172:AG183) -> 28637.638 | K36: =J36/H36 -> 0.86666667 | L36: =SUM(AH172:AH183) -> 0 | M36: =SUM(AI172:AI183) -> 28637.638 | N36: =M36+N35 -> 250498.62 | O36: =O35-H36 -> -305461.28 | P36: =J36/$C$4 -> 2.0118479 | S36: =IF(AND(AJ36>0,AJ35<0),"Payback","") | T36: 2 | U36: 9 | V36: Setembro | W36: ='Análise Técnica'!$C$3 -> 750 | X36: =X24*((1-$C$27)) -> 671.52803 | Y36: =IF(X36-W36<0,W36-X36,0) -> 78.471975 | Z36: =IF(X36-W36>0,X36-W36,0) -> 0 | AA36: =$C$7 -> 100 | AB36: =IF(Y36-$C$7>0,Y36-$C$7,0) -> 0 | AC36: =IF(AC35-(Y36-$C$7)>0,IF(Y36>0,IF(Y36<$C$7,AC35,AC35-(Y36-$C$7)),Z36+AC35),0) -> 649.32775 | AD36: =IF(AB36-AC35<0,0,AB36-AC35) -> 0 | AE36: =($C$10*(1+$C$30)^T36) -> 1093.5 | AF36: =IF(Z36>0,((AA36*$C$8)*((1+$C$30)^T36)),((AA36+AD36)*$C$8)*(1+$C$30)^T36) -> 145.8 | AG36: =AE36-AF36 -> 947.7 | AH36: =$C$28/12*($C$4*((1+$C$29)^T36))+IF($C$31=T36,$C$33/12,0) -> 0 | AI36: =AG36-AH36 -> 947.7 | AJ36: =AJ35+AI36 -> 14574.806 | AK36: =1-(AF36/AE36) -> 0.86666667 | AL36: =AL35+AE36 -> 33241.5 | AM36: =AG36/$C$4 -> 0.066577708 | AO36: 33 | AP36: =($C$4*(1+($C$36-$C$39))^AO36)-AE36 -> 14534.059 | AQ36: =AJ36 -> 14574.806
B37: Poupança (a.a.) | C37: =12*C36 -> 0.084 | D37: =IF(AND(N37>0,N36<0),"Payback","") | E37: 15 | F37: =SUM(W184:W195) -> 9000 | G37: =SUM(X184:X195) -> 7931.0062 | H37: =SUM(AE184:AE195) -> 35686.903 | I37: =SUM(AF184:AF195) -> 5839.3016 | J37: =SUM(AG184:AG195) -> 29847.601 | K37: =J37/H37 -> 0.8363741 | L37: =SUM(AH184:AH195) -> 2135.1741 | M37: =SUM(AI184:AI195) -> 27712.427 | N37: =M37+N36 -> 278211.04 | O37: =O36-H37 -> -341148.18 | P37: =J37/$C$4 -> 2.0968501 | S37: =IF(AND(AJ37>0,AJ36<0),"Payback","") | T37: 2 | U37: 10 | V37: Outubro | W37: ='Análise Técnica'!$C$3 -> 750 | X37: =X25*((1-$C$27)) -> 751.23757 | Y37: =IF(X37-W37<0,W37-X37,0) -> 0 | Z37: =IF(X37-W37>0,X37-W37,0) -> 1.2375703 | AA37: =$C$7 -> 100 | AB37: =IF(Y37-$C$7>0,Y37-$C$7,0) -> 0 | AC37: =IF(AC36-(Y37-$C$7)>0,IF(Y37>0,IF(Y37<$C$7,AC36,AC36-(Y37-$C$7)),Z37+AC36),0) -> 650.56532 | AD37: =IF(AB37-AC36<0,0,AB37-AC36) -> 0 | AE37: =($C$10*(1+$C$30)^T37) -> 1093.5 | AF37: =IF(Z37>0,((AA37*$C$8)*((1+$C$30)^T37)),((AA37+AD37)*$C$8)*(1+$C$30)^T37) -> 145.8 | AG37: =AE37-AF37 -> 947.7 | AH37: =$C$28/12*($C$4*((1+$C$29)^T37))+IF($C$31=T37,$C$33/12,0) -> 0 | AI37: =AG37-AH37 -> 947.7 | AJ37: =AJ36+AI37 -> 15522.506 | AK37: =1-(AF37/AE37) -> 0.86666667 | AL37: =AL36+AE37 -> 34335 | AM37: =AG37/$C$4 -> 0.066577708 | AO37: 34 | AP37: =($C$4*(1+($C$36-$C$39))^AO37)-AE37 -> 14578.337 | AQ37: =AJ37 -> 15522.506
B38: Inflação (a.a) | C38: =C29 -> 0.05 | D38: =IF(AND(N38>0,N37<0),"Payback","") | E38: 16 | F38: =SUM(W196:W207) -> 9000 | G38: =SUM(X196:X207) -> 7875.4891 | H38: =SUM(AE196:AE207) -> 38541.855 | I38: =SUM(AF196:AF207) -> 6651.5346 | J38: =SUM(AG196:AG207) -> 31890.32 | K38: =J38/H38 -> 0.82742049 | L38: =SUM(AH196:AH207) -> 0 | M38: =SUM(AI196:AI207) -> 31890.32 | N38: =M38+N37 -> 310101.36 | O38: =O37-H38 -> -379690.04 | P38: =J38/$C$4 -> 2.240355 | S38: =IF(AND(AJ38>0,AJ37<0),"Payback","") | T38: 2 | U38: 11 | V38: Novembro | W38: ='Análise Técnica'!$C$3 -> 750 | X38: =X26*((1-$C$27)) -> 756.65501 | Y38: =IF(X38-W38<0,W38-X38,0) -> 0 | Z38: =IF(X38-W38>0,X38-W38,0) -> 6.6550081 | AA38: =$C$7 -> 100 | AB38: =IF(Y38-$C$7>0,Y38-$C$7,0) -> 0 | AC38: =IF(AC37-(Y38-$C$7)>0,IF(Y38>0,IF(Y38<$C$7,AC37,AC37-(Y38-$C$7)),Z38+AC37),0) -> 657.22033 | AD38: =IF(AB38-AC37<0,0,AB38-AC37) -> 0 | AE38: =($C$10*(1+$C$30)^T38) -> 1093.5 | AF38: =IF(Z38>0,((AA38*$C$8)*((1+$C$30)^T38)),((AA38+AD38)*$C$8)*(1+$C$30)^T38) -> 145.8 | AG38: =AE38-AF38 -> 947.7 | AH38: =$C$28/12*($C$4*((1+$C$29)^T38))+IF($C$31=T38,$C$33/12,0) -> 0 | AI38: =AG38-AH38 -> 947.7 | AJ38: =AJ37+AI38 -> 16470.206 | AK38: =1-(AF38/AE38) -> 0.86666667 | AL38: =AL37+AE38 -> 35428.5 | AM38: =AG38/$C$4 -> 0.066577708 | AO38: 35 | AP38: =($C$4*(1+($C$36-$C$39))^AO38)-AE38 -> 14622.741 | AQ38: =AJ38 -> 16470.206
B39: Inflação (a.m.) | C39: =C38/12 -> 0.0041666667 | D39: =IF(AND(N39>0,N38<0),"Payback","") | E39: 17 | F39: =SUM(W208:W219) -> 9000 | G39: =SUM(X208:X219) -> 7820.3607 | H39: =SUM(AE208:AE219) -> 41625.203 | I39: =SUM(AF208:AF219) -> 7371.3292 | J39: =SUM(AG208:AG219) -> 34253.874 | K39: =J39/H39 -> 0.82291188 | L39: =SUM(AH208:AH219) -> 0 | M39: =SUM(AI208:AI219) -> 34253.874 | N39: =M39+N38 -> 344355.24 | O39: =O38-H39 -> -421315.24 | P39: =J39/$C$4 -> 2.4063991 | S39: =IF(AND(AJ39>0,AJ38<0),"Payback","") | T39: 2 | U39: 12 | V39: Dezembro | W39: ='Análise Técnica'!$C$3 -> 750 | X39: =X27*((1-$C$27)) -> 868.10781 | Y39: =IF(X39-W39<0,W39-X39,0) -> 0 | Z39: =IF(X39-W39>0,X39-W39,0) -> 118.10781 | AA39: =$C$7 -> 100 | AB39: =IF(Y39-$C$7>0,Y39-$C$7,0) -> 0 | AC39: =IF(AC38-(Y39-$C$7)>0,IF(Y39>0,IF(Y39<$C$7,AC38,AC38-(Y39-$C$7)),Z39+AC38),0) -> 775.32814 | AD39: =IF(AB39-AC38<0,0,AB39-AC38) -> 0 | AE39: =($C$10*(1+$C$30)^T39) -> 1093.5 | AF39: =IF(Z39>0,((AA39*$C$8)*((1+$C$30)^T39)),((AA39+AD39)*$C$8)*(1+$C$30)^T39) -> 145.8 | AG39: =AE39-AF39 -> 947.7 | AH39: =$C$28/12*($C$4*((1+$C$29)^T39))+IF($C$31=T39,$C$33/12,0) -> 0 | AI39: =AG39-AH39 -> 947.7 | AJ39: =AJ38+AI39 -> 17417.906 | AK39: =1-(AF39/AE39) -> 0.86666667 | AL39: =AL38+AE39 -> 36522 | AM39: =AG39/$C$4 -> 0.066577708 | AO39: 36 | AP39: =($C$4*(1+($C$36-$C$39))^AO39)-AE39 -> 14667.27 | AQ39: =AJ39 -> 17417.906
D40: =IF(AND(N40>0,N39<0),"Payback","") | E40: 18 | F40: =SUM(W220:W231) -> 9000 | G40: =SUM(X220:X231) -> 7765.6182 | H40: =SUM(AE220:AE231) -> 44955.219 | I40: =SUM(AF220:AF231) -> 8162.3023 | J40: =SUM(AG220:AG231) -> 36792.917 | K40: =J40/H40 -> 0.81843483 | L40: =SUM(AH220:AH231) -> 0 | M40: =SUM(AI220:AI231) -> 36792.917 | N40: =M40+N39 -> 381148.15 | O40: =O39-H40 -> -466270.46 | P40: =J40/$C$4 -> 2.5847716 | S40: =IF(AND(AJ40>0,AJ39<0),"Payback","") | T40: 3 | U40: 1 | V40: Janeiro | W40: ='Análise Técnica'!$C$3 -> 750 | X40: =X28*((1-$C$27)) -> 889.53928 | Y40: =IF(X40-W40<0,W40-X40,0) -> 0 | Z40: =IF(X40-W40>0,X40-W40,0) -> 139.53928 | AA40: =$C$7 -> 100 | AB40: =IF(Y40-$C$7>0,Y40-$C$7,0) -> 0 | AC40: =IF(AC39-(Y40-$C$7)>0,IF(Y40>0,IF(Y40<$C$7,AC39,AC39-(Y40-$C$7)),Z40+AC39),0) -> 914.86742 | AD40: =IF(AB40-AC39<0,0,AB40-AC39) -> 0 | AE40: =($C$10*(1+$C$30)^T40) -> 1180.98 | AF40: =IF(Z40>0,((AA40*$C$8)*((1+$C$30)^T40)),((AA40+AD40)*$C$8)*(1+$C$30)^T40) -> 157.464 | AG40: =AE40-AF40 -> 1023.516 | AH40: =$C$28/12*($C$4*((1+$C$29)^T40))+IF($C$31=T40,$C$33/12,0) -> 0 | AI40: =AG40-AH40 -> 1023.516 | AJ40: =AJ39+AI40 -> 18441.422 | AK40: =1-(AF40/AE40) -> 0.86666667 | AL40: =AL39+AE40 -> 37702.98 | AM40: =AG40/$C$4 -> 0.071903925 | AO40: 37 | AP40: =($C$4*(1+($C$36-$C$39))^AO40)-AE40 -> 14624.446 | AQ40: =AJ40 -> 18441.422
D41: =IF(AND(N41>0,N40<0),"Payback","") | E41: 19 | F41: =SUM(W232:W243) -> 9000 | G41: =SUM(X232:X243) -> 7711.2588 | H41: =SUM(AE232:AE243) -> 48551.637 | I41: =SUM(AF232:AF243) -> 9031.133 | J41: =SUM(AG232:AG243) -> 39520.504 | K41: =J41/H41 -> 0.81398911 | L41: =SUM(AH232:AH243) -> 0 | M41: =SUM(AI232:AI243) -> 39520.504 | N41: =M41+N40 -> 420668.66 | O41: =O40-H41 -> -514822.1 | P41: =J41/$C$4 -> 2.7763898 | S41: =IF(AND(AJ41>0,AJ40<0),"Payback","") | T41: 3 | U41: 2 | V41: Fevereiro | W41: ='Análise Técnica'!$C$3 -> 750 | X41: =X29*((1-$C$27)) -> 936.87902 | Y41: =IF(X41-W41<0,W41-X41,0) -> 0 | Z41: =IF(X41-W41>0,X41-W41,0) -> 186.87902 | AA41: =$C$7 -> 100 | AB41: =IF(Y41-$C$7>0,Y41-$C$7,0) -> 0 | AC41: =IF(AC40-(Y41-$C$7)>0,IF(Y41>0,IF(Y41<$C$7,AC40,AC40-(Y41-$C$7)),Z41+AC40),0) -> 1101.7464 | AD41: =IF(AB41-AC40<0,0,AB41-AC40) -> 0 | AE41: =($C$10*(1+$C$30)^T41) -> 1180.98 | AF41: =IF(Z41>0,((AA41*$C$8)*((1+$C$30)^T41)),((AA41+AD41)*$C$8)*(1+$C$30)^T41) -> 157.464 | AG41: =AE41-AF41 -> 1023.516 | AH41: =$C$28/12*($C$4*((1+$C$29)^T41))+IF($C$31=T41,$C$33/12,0) -> 0 | AI41: =AG41-AH41 -> 1023.516 | AJ41: =AJ40+AI41 -> 19464.938 | AK41: =1-(AF41/AE41) -> 0.86666667 | AL41: =AL40+AE41 -> 38883.96 | AM41: =AG41/$C$4 -> 0.071903925 | AO41: 38 | AP41: =($C$4*(1+($C$36-$C$39))^AO41)-AE41 -> 14669.228 | AQ41: =AJ41 -> 19464.938
D42: =IF(AND(N42>0,N41<0),"Payback","") | E42: 20 | F42: =SUM(W244:W255) -> 9000 | G42: =SUM(X244:X255) -> 7657.28 | H42: =SUM(AE244:AE255) -> 52435.768 | I42: =SUM(AF244:AF255) -> 9985.106 | J42: =SUM(AG244:AG255) -> 42450.662 | K42: =J42/H42 -> 0.80957452 | L42: =SUM(AH244:AH255) -> 0 | M42: =SUM(AI244:AI255) -> 42450.662 | N42: =M42+N41 -> 463119.32 | O42: =O41-H42 -> -567257.87 | P42: =J42/$C$4 -> 2.9822389 | S42: =IF(AND(AJ42>0,AJ41<0),"Payback","") | T42: 3 | U42: 3 | V42: Março | W42: ='Análise Técnica'!$C$3 -> 750 | X42: =X30*((1-$C$27)) -> 786.20896 | Y42: =IF(X42-W42<0,W42-X42,0) -> 0 | Z42: =IF(X42-W42>0,X42-W42,0) -> 36.208962 | AA42: =$C$7 -> 100 | AB42: =IF(Y42-$C$7>0,Y42-$C$7,0) -> 0 | AC42: =IF(AC41-(Y42-$C$7)>0,IF(Y42>0,IF(Y42<$C$7,AC41,AC41-(Y42-$C$7)),Z42+AC41),0) -> 1137.9554 | AD42: =IF(AB42-AC41<0,0,AB42-AC41) -> 0 | AE42: =($C$10*(1+$C$30)^T42) -> 1180.98 | AF42: =IF(Z42>0,((AA42*$C$8)*((1+$C$30)^T42)),((AA42+AD42)*$C$8)*(1+$C$30)^T42) -> 157.464 | AG42: =AE42-AF42 -> 1023.516 | AH42: =$C$28/12*($C$4*((1+$C$29)^T42))+IF($C$31=T42,$C$33/12,0) -> 0 | AI42: =AG42-AH42 -> 1023.516 | AJ42: =AJ41+AI42 -> 20488.454 | AK42: =1-(AF42/AE42) -> 0.86666667 | AL42: =AL41+AE42 -> 40064.94 | AM42: =AG42/$C$4 -> 0.071903925 | AO42: 39 | AP42: =($C$4*(1+($C$36-$C$39))^AO42)-AE42 -> 14714.137 | AQ42: =AJ42 -> 20488.454
D43: =IF(AND(N43>0,N42<0),"Payback","") | E43: 21 | F43: =SUM(W256:W267) -> 9000 | G43: =SUM(X256:X267) -> 7603.6791 | H43: =SUM(AE256:AE267) -> 56630.629 | I43: =SUM(AF256:AF267) -> 11032.166 | J43: =SUM(AG256:AG267) -> 45598.464 | K43: =J43/H43 -> 0.80519084 | L43: =SUM(AH256:AH267) -> 0 | M43: =SUM(AI256:AI267) -> 45598.464 | N43: =M43+N42 -> 508717.78 | O43: =O42-H43 -> -623888.5 | P43: =J43/$C$4 -> 3.2033779 | S43: =IF(AND(AJ43>0,AJ42<0),"Payback","") | T43: 3 | U43: 4 | V43: Abril | W43: ='Análise Técnica'!$C$3 -> 750 | X43: =X31*((1-$C$27)) -> 697.18525 | Y43: =IF(X43-W43<0,W43-X43,0) -> 52.814755 | Z43: =IF(X43-W43>0,X43-W43,0) -> 0 | AA43: =$C$7 -> 100 | AB43: =IF(Y43-$C$7>0,Y43-$C$7,0) -> 0 | AC43: =IF(AC42-(Y43-$C$7)>0,IF(Y43>0,IF(Y43<$C$7,AC42,AC42-(Y43-$C$7)),Z43+AC42),0) -> 1137.9554 | AD43: =IF(AB43-AC42<0,0,AB43-AC42) -> 0 | AE43: =($C$10*(1+$C$30)^T43) -> 1180.98 | AF43: =IF(Z43>0,((AA43*$C$8)*((1+$C$30)^T43)),((AA43+AD43)*$C$8)*(1+$C$30)^T43) -> 157.464 | AG43: =AE43-AF43 -> 1023.516 | AH43: =$C$28/12*($C$4*((1+$C$29)^T43))+IF($C$31=T43,$C$33/12,0) -> 0 | AI43: =AG43-AH43 -> 1023.516 | AJ43: =AJ42+AI43 -> 21511.97 | AK43: =1-(AF43/AE43) -> 0.86666667 | AL43: =AL42+AE43 -> 41245.92 | AM43: =AG43/$C$4 -> 0.071903925 | AO43: 40 | AP43: =($C$4*(1+($C$36-$C$39))^AO43)-AE43 -> 14759.173 | AQ43: =AJ43 -> 21511.97
D44: =IF(AND(N44>0,N43<0),"Payback","") | E44: 22 | F44: =SUM(W268:W279) -> 9000 | G44: =SUM(X268:X279) -> 7550.4533 | H44: =SUM(AE268:AE279) -> 61161.08 | I44: =SUM(AF268:AF279) -> 12180.973 | J44: =SUM(AG268:AG279) -> 48980.107 | K44: =J44/H44 -> 0.80083783 | L44: =SUM(AH268:AH279) -> 0 | M44: =SUM(AI268:AI279) -> 48980.107 | N44: =M44+N43 -> 557697.89 | O44: =O43-H44 -> -685049.58 | P44: =J44/$C$4 -> 3.4409446 | S44: =IF(AND(AJ44>0,AJ43<0),"Payback","") | T44: 3 | U44: 5 | V44: Maio | W44: ='Análise Técnica'!$C$3 -> 750 | X44: =X32*((1-$C$27)) -> 574.15427 | Y44: =IF(X44-W44<0,W44-X44,0) -> 175.84573 | Z44: =IF(X44-W44>0,X44-W44,0) -> 0 | AA44: =$C$7 -> 100 | AB44: =IF(Y44-$C$7>0,Y44-$C$7,0) -> 75.845735 | AC44: =IF(AC43-(Y44-$C$7)>0,IF(Y44>0,IF(Y44<$C$7,AC43,AC43-(Y44-$C$7)),Z44+AC43),0) -> 1062.1097 | AD44: =IF(AB44-AC43<0,0,AB44-AC43) -> 0 | AE44: =($C$10*(1+$C$30)^T44) -> 1180.98 | AF44: =IF(Z44>0,((AA44*$C$8)*((1+$C$30)^T44)),((AA44+AD44)*$C$8)*(1+$C$30)^T44) -> 157.464 | AG44: =AE44-AF44 -> 1023.516 | AH44: =$C$28/12*($C$4*((1+$C$29)^T44))+IF($C$31=T44,$C$33/12,0) -> 0 | AI44: =AG44-AH44 -> 1023.516 | AJ44: =AJ43+AI44 -> 22535.486 | AK44: =1-(AF44/AE44) -> 0.86666667 | AL44: =AL43+AE44 -> 42426.9 | AM44: =AG44/$C$4 -> 0.071903925 | AO44: 41 | AP44: =($C$4*(1+($C$36-$C$39))^AO44)-AE44 -> 14804.337 | AQ44: =AJ44 -> 22535.486
D45: =IF(AND(N45>0,N44<0),"Payback","") | E45: 23 | F45: =SUM(W280:W291) -> 9000 | G45: =SUM(X280:X291) -> 7497.6001 | H45: =SUM(AE280:AE291) -> 66053.966 | I45: =SUM(AF280:AF291) -> 13454.155 | J45: =SUM(AG280:AG291) -> 52599.811 | K45: =J45/H45 -> 0.79631572 | L45: =SUM(AH280:AH291) -> 0 | M45: =SUM(AI280:AI291) -> 52599.811 | N45: =M45+N44 -> 610297.7 | O45: =O44-H45 -> -751103.54 | P45: =J45/$C$4 -> 3.6952357 | S45: =IF(AND(AJ45>0,AJ44<0),"Payback","") | T45: 3 | U45: 6 | V45: Junho | W45: ='Análise Técnica'!$C$3 -> 750 | X45: =X33*((1-$C$27)) -> 530.97275 | Y45: =IF(X45-W45<0,W45-X45,0) -> 219.02725 | Z45: =IF(X45-W45>0,X45-W45,0) -> 0 | AA45: =$C$7 -> 100 | AB45: =IF(Y45-$C$7>0,Y45-$C$7,0) -> 119.02725 | AC45: =IF(AC44-(Y45-$C$7)>0,IF(Y45>0,IF(Y45<$C$7,AC44,AC44-(Y45-$C$7)),Z45+AC44),0) -> 943.08242 | AD45: =IF(AB45-AC44<0,0,AB45-AC44) -> 0 | AE45: =($C$10*(1+$C$30)^T45) -> 1180.98 | AF45: =IF(Z45>0,((AA45*$C$8)*((1+$C$30)^T45)),((AA45+AD45)*$C$8)*(1+$C$30)^T45) -> 157.464 | AG45: =AE45-AF45 -> 1023.516 | AH45: =$C$28/12*($C$4*((1+$C$29)^T45))+IF($C$31=T45,$C$33/12,0) -> 0 | AI45: =AG45-AH45 -> 1023.516 | AJ45: =AJ44+AI45 -> 23559.002 | AK45: =1-(AF45/AE45) -> 0.86666667 | AL45: =AL44+AE45 -> 43607.88 | AM45: =AG45/$C$4 -> 0.071903925 | AO45: 42 | AP45: =($C$4*(1+($C$36-$C$39))^AO45)-AE45 -> 14849.628 | AQ45: =AJ45 -> 23559.002
D46: =IF(AND(N46>0,N45<0),"Payback","") | E46: 24 | F46: =SUM(W292:W303) -> 9000 | G46: =SUM(X292:X303) -> 7445.1169 | H46: =SUM(AE292:AE303) -> 71338.283 | I46: =SUM(AF292:AF303) -> 14878.498 | J46: =SUM(AG292:AG303) -> 56459.785 | K46: =J46/H46 -> 0.7914374 | L46: =SUM(AH292:AH303) -> 0 | M46: =SUM(AI292:AI303) -> 56459.785 | N46: =M46+N45 -> 666757.49 | O46: =O45-H46 -> -822441.82 | P46: =J46/$C$4 -> 3.9664061 | S46: =IF(AND(AJ46>0,AJ45<0),"Payback","") | T46: 3 | U46: 7 | V46: Julho | W46: ='Análise Técnica'!$C$3 -> 750 | X46: =X34*((1-$C$27)) -> 530.90005 | Y46: =IF(X46-W46<0,W46-X46,0) -> 219.09995 | Z46: =IF(X46-W46>0,X46-W46,0) -> 0 | AA46: =$C$7 -> 100 | AB46: =IF(Y46-$C$7>0,Y46-$C$7,0) -> 119.09995 | AC46: =IF(AC45-(Y46-$C$7)>0,IF(Y46>0,IF(Y46<$C$7,AC45,AC45-(Y46-$C$7)),Z46+AC45),0) -> 823.98247 | AD46: =IF(AB46-AC45<0,0,AB46-AC45) -> 0 | AE46: =($C$10*(1+$C$30)^T46) -> 1180.98 | AF46: =IF(Z46>0,((AA46*$C$8)*((1+$C$30)^T46)),((AA46+AD46)*$C$8)*(1+$C$30)^T46) -> 157.464 | AG46: =AE46-AF46 -> 1023.516 | AH46: =$C$28/12*($C$4*((1+$C$29)^T46))+IF($C$31=T46,$C$33/12,0) -> 0 | AI46: =AG46-AH46 -> 1023.516 | AJ46: =AJ45+AI46 -> 24582.518 | AK46: =1-(AF46/AE46) -> 0.86666667 | AL46: =AL45+AE46 -> 44788.86 | AM46: =AG46/$C$4 -> 0.071903925 | AO46: 43 | AP46: =($C$4*(1+($C$36-$C$39))^AO46)-AE46 -> 14895.049 | AQ46: =AJ46 -> 24582.518
E47: Média | F47: =AVERAGE(F22:F46) -> 9000 | G47: =AVERAGE(G22:G46) -> 8111.3806 | H47: =AVERAGE(H22:H46) -> 32897.673 | I47: =AVERAGE(I22:I46) -> 5572.5868 | J47: =AVERAGE(J22:J46) -> 27325.086 | K47: =AVERAGE(K22:K46) -> 0.84489947 | L47: =AVERAGE(L22:L46) -> 654.78674 | S47: =IF(AND(AJ47>0,AJ46<0),"Payback","") | T47: 3 | U47: 8 | V47: Agosto | W47: ='Análise Técnica'!$C$3 -> 750 | X47: =X35*((1-$C$27)) -> 656.50447 | Y47: =IF(X47-W47<0,W47-X47,0) -> 93.495525 | Z47: =IF(X47-W47>0,X47-W47,0) -> 0 | AA47: =$C$7 -> 100 | AB47: =IF(Y47-$C$7>0,Y47-$C$7,0) -> 0 | AC47: =IF(AC46-(Y47-$C$7)>0,IF(Y47>0,IF(Y47<$C$7,AC46,AC46-(Y47-$C$7)),Z47+AC46),0) -> 823.98247 | AD47: =IF(AB47-AC46<0,0,AB47-AC46) -> 0 | AE47: =($C$10*(1+$C$30)^T47) -> 1180.98 | AF47: =IF(Z47>0,((AA47*$C$8)*((1+$C$30)^T47)),((AA47+AD47)*$C$8)*(1+$C$30)^T47) -> 157.464 | AG47: =AE47-AF47 -> 1023.516 | AH47: =$C$28/12*($C$4*((1+$C$29)^T47))+IF($C$31=T47,$C$33/12,0) -> 0 | AI47: =AG47-AH47 -> 1023.516 | AJ47: =AJ46+AI47 -> 25606.034 | AK47: =1-(AF47/AE47) -> 0.86666667 | AL47: =AL46+AE47 -> 45969.84 | AM47: =AG47/$C$4 -> 0.071903925 | AO47: 44 | AP47: =($C$4*(1+($C$36-$C$39))^AO47)-AE47 -> 14940.597 | AQ47: =AJ47 -> 25606.034
E48: Total | F48: =SUM(F22:F46) -> 225000 | G48: =SUM(G22:G46) -> 202784.52 | H48: =SUM(H22:H46) -> 822441.82 | I48: =SUM(I22:I46) -> 139314.67 | J48: =SUM(J22:J46) -> 683127.16 | K48: =J48/H48 -> 0.83060848 | L48: =SUM(L22:L46) -> 16369.668 | M48: - | N48: - | O48: - | S48: =IF(AND(AJ48>0,AJ47<0),"Payback","") | T48: 3 | U48: 9 | V48: Setembro | W48: ='Análise Técnica'!$C$3 -> 750 | X48: =X36*((1-$C$27)) -> 666.82733 | Y48: =IF(X48-W48<0,W48-X48,0) -> 83.172671 | Z48: =IF(X48-W48>0,X48-W48,0) -> 0 | AA48: =$C$7 -> 100 | AB48: =IF(Y48-$C$7>0,Y48-$C$7,0) -> 0 | AC48: =IF(AC47-(Y48-$C$7)>0,IF(Y48>0,IF(Y48<$C$7,AC47,AC47-(Y48-$C$7)),Z48+AC47),0) -> 823.98247 | AD48: =IF(AB48-AC47<0,0,AB48-AC47) -> 0 | AE48: =($C$10*(1+$C$30)^T48) -> 1180.98 | AF48: =IF(Z48>0,((AA48*$C$8)*((1+$C$30)^T48)),((AA48+AD48)*$C$8)*(1+$C$30)^T48) -> 157.464 | AG48: =AE48-AF48 -> 1023.516 | AH48: =$C$28/12*($C$4*((1+$C$29)^T48))+IF($C$31=T48,$C$33/12,0) -> 0 | AI48: =AG48-AH48 -> 1023.516 | AJ48: =AJ47+AI48 -> 26629.55 | AK48: =1-(AF48/AE48) -> 0.86666667 | AL48: =AL47+AE48 -> 47150.82 | AM48: =AG48/$C$4 -> 0.071903925 | AO48: 45 | AP48: =($C$4*(1+($C$36-$C$39))^AO48)-AE48 -> 14986.275 | AQ48: =AJ48 -> 26629.55
S49: =IF(AND(AJ49>0,AJ48<0),"Payback","") | T49: 3 | U49: 10 | V49: Outubro | W49: ='Análise Técnica'!$C$3 -> 750 | X49: =X37*((1-$C$27)) -> 745.97891 | Y49: =IF(X49-W49<0,W49-X49,0) -> 4.0210927 | Z49: =IF(X49-W49>0,X49-W49,0) -> 0 | AA49: =$C$7 -> 100 | AB49: =IF(Y49-$C$7>0,Y49-$C$7,0) -> 0 | AC49: =IF(AC48-(Y49-$C$7)>0,IF(Y49>0,IF(Y49<$C$7,AC48,AC48-(Y49-$C$7)),Z49+AC48),0) -> 823.98247 | AD49: =IF(AB49-AC48<0,0,AB49-AC48) -> 0 | AE49: =($C$10*(1+$C$30)^T49) -> 1180.98 | AF49: =IF(Z49>0,((AA49*$C$8)*((1+$C$30)^T49)),((AA49+AD49)*$C$8)*(1+$C$30)^T49) -> 157.464 | AG49: =AE49-AF49 -> 1023.516 | AH49: =$C$28/12*($C$4*((1+$C$29)^T49))+IF($C$31=T49,$C$33/12,0) -> 0 | AI49: =AG49-AH49 -> 1023.516 | AJ49: =AJ48+AI49 -> 27653.066 | AK49: =1-(AF49/AE49) -> 0.86666667 | AL49: =AL48+AE49 -> 48331.8 | AM49: =AG49/$C$4 -> 0.071903925 | AO49: 46 | AP49: =($C$4*(1+($C$36-$C$39))^AO49)-AE49 -> 15032.082 | AQ49: =AJ49 -> 27653.066
S50: =IF(AND(AJ50>0,AJ49<0),"Payback","") | T50: 3 | U50: 11 | V50: Novembro | W50: ='Análise Técnica'!$C$3 -> 750 | X50: =X38*((1-$C$27)) -> 751.35842 | Y50: =IF(X50-W50<0,W50-X50,0) -> 0 | Z50: =IF(X50-W50>0,X50-W50,0) -> 1.3584231 | AA50: =$C$7 -> 100 | AB50: =IF(Y50-$C$7>0,Y50-$C$7,0) -> 0 | AC50: =IF(AC49-(Y50-$C$7)>0,IF(Y50>0,IF(Y50<$C$7,AC49,AC49-(Y50-$C$7)),Z50+AC49),0) -> 825.34089 | AD50: =IF(AB50-AC49<0,0,AB50-AC49) -> 0 | AE50: =($C$10*(1+$C$30)^T50) -> 1180.98 | AF50: =IF(Z50>0,((AA50*$C$8)*((1+$C$30)^T50)),((AA50+AD50)*$C$8)*(1+$C$30)^T50) -> 157.464 | AG50: =AE50-AF50 -> 1023.516 | AH50: =$C$28/12*($C$4*((1+$C$29)^T50))+IF($C$31=T50,$C$33/12,0) -> 0 | AI50: =AG50-AH50 -> 1023.516 | AJ50: =AJ49+AI50 -> 28676.582 | AK50: =1-(AF50/AE50) -> 0.86666667 | AL50: =AL49+AE50 -> 49512.78 | AM50: =AG50/$C$4 -> 0.071903925 | AO50: 47 | AP50: =($C$4*(1+($C$36-$C$39))^AO50)-AE50 -> 15078.019 | AQ50: =AJ50 -> 28676.582
S51: =IF(AND(AJ51>0,AJ50<0),"Payback","") | T51: 3 | U51: 12 | V51: Dezembro | W51: ='Análise Técnica'!$C$3 -> 750 | X51: =X39*((1-$C$27)) -> 862.03106 | Y51: =IF(X51-W51<0,W51-X51,0) -> 0 | Z51: =IF(X51-W51>0,X51-W51,0) -> 112.03106 | AA51: =$C$7 -> 100 | AB51: =IF(Y51-$C$7>0,Y51-$C$7,0) -> 0 | AC51: =IF(AC50-(Y51-$C$7)>0,IF(Y51>0,IF(Y51<$C$7,AC50,AC50-(Y51-$C$7)),Z51+AC50),0) -> 937.37195 | AD51: =IF(AB51-AC50<0,0,AB51-AC50) -> 0 | AE51: =($C$10*(1+$C$30)^T51) -> 1180.98 | AF51: =IF(Z51>0,((AA51*$C$8)*((1+$C$30)^T51)),((AA51+AD51)*$C$8)*(1+$C$30)^T51) -> 157.464 | AG51: =AE51-AF51 -> 1023.516 | AH51: =$C$28/12*($C$4*((1+$C$29)^T51))+IF($C$31=T51,$C$33/12,0) -> 0 | AI51: =AG51-AH51 -> 1023.516 | AJ51: =AJ50+AI51 -> 29700.098 | AK51: =1-(AF51/AE51) -> 0.86666667 | AL51: =AL50+AE51 -> 50693.76 | AM51: =AG51/$C$4 -> 0.071903925 | AO51: 48 | AP51: =($C$4*(1+($C$36-$C$39))^AO51)-AE51 -> 15124.086 | AQ51: =AJ51 -> 29700.098
S52: =IF(AND(AJ52>0,AJ51<0),"Payback","") | T52: 4 | U52: 1 | V52: Janeiro | W52: ='Análise Técnica'!$C$3 -> 750 | X52: =X40*((1-$C$27)) -> 883.31251 | Y52: =IF(X52-W52<0,W52-X52,0) -> 0 | Z52: =IF(X52-W52>0,X52-W52,0) -> 133.31251 | AA52: =$C$7 -> 100 | AB52: =IF(Y52-$C$7>0,Y52-$C$7,0) -> 0 | AC52: =IF(AC51-(Y52-$C$7)>0,IF(Y52>0,IF(Y52<$C$7,AC51,AC51-(Y52-$C$7)),Z52+AC51),0) -> 1070.6845 | AD52: =IF(AB52-AC51<0,0,AB52-AC51) -> 0 | AE52: =($C$10*(1+$C$30)^T52) -> 1275.4584 | AF52: =IF(Z52>0,((AA52*$C$8)*((1+$C$30)^T52)),((AA52+AD52)*$C$8)*(1+$C$30)^T52) -> 170.06112 | AG52: =AE52-AF52 -> 1105.3973 | AH52: =$C$28/12*($C$4*((1+$C$29)^T52))+IF($C$31=T52,$C$33/12,0) -> 0 | AI52: =AG52-AH52 -> 1105.3973 | AJ52: =AJ51+AI52 -> 30805.495 | AK52: =1-(AF52/AE52) -> 0.86666667 | AL52: =AL51+AE52 -> 51969.218 | AM52: =AG52/$C$4 -> 0.077656238 | AO52: 49 | AP52: =($C$4*(1+($C$36-$C$39))^AO52)-AE52 -> 15075.806 | AQ52: =AJ52 -> 30805.495
S53: =IF(AND(AJ53>0,AJ52<0),"Payback","") | T53: 4 | U53: 2 | V53: Fevereiro | W53: ='Análise Técnica'!$C$3 -> 750 | X53: =X41*((1-$C$27)) -> 930.32087 | Y53: =IF(X53-W53<0,W53-X53,0) -> 0 | Z53: =IF(X53-W53>0,X53-W53,0) -> 180.32087 | AA53: =$C$7 -> 100 | AB53: =IF(Y53-$C$7>0,Y53-$C$7,0) -> 0 | AC53: =IF(AC52-(Y53-$C$7)>0,IF(Y53>0,IF(Y53<$C$7,AC52,AC52-(Y53-$C$7)),Z53+AC52),0) -> 1251.0053 | AD53: =IF(AB53-AC52<0,0,AB53-AC52) -> 0 | AE53: =($C$10*(1+$C$30)^T53) -> 1275.4584 | AF53: =IF(Z53>0,((AA53*$C$8)*((1+$C$30)^T53)),((AA53+AD53)*$C$8)*(1+$C$30)^T53) -> 170.06112 | AG53: =AE53-AF53 -> 1105.3973 | AH53: =$C$28/12*($C$4*((1+$C$29)^T53))+IF($C$31=T53,$C$33/12,0) -> 0 | AI53: =AG53-AH53 -> 1105.3973 | AJ53: =AJ52+AI53 -> 31910.892 | AK53: =1-(AF53/AE53) -> 0.86666667 | AL53: =AL52+AE53 -> 53244.677 | AM53: =AG53/$C$4 -> 0.077656238 | AO53: 50 | AP53: =($C$4*(1+($C$36-$C$39))^AO53)-AE53 -> 15122.134 | AQ53: =AJ53 -> 31910.892
S54: =IF(AND(AJ54>0,AJ53<0),"Payback","") | T54: 4 | U54: 3 | V54: Março | W54: ='Análise Técnica'!$C$3 -> 750 | X54: =X42*((1-$C$27)) -> 780.7055 | Y54: =IF(X54-W54<0,W54-X54,0) -> 0 | Z54: =IF(X54-W54>0,X54-W54,0) -> 30.705499 | AA54: =$C$7 -> 100 | AB54: =IF(Y54-$C$7>0,Y54-$C$7,0) -> 0 | AC54: =IF(AC53-(Y54-$C$7)>0,IF(Y54>0,IF(Y54<$C$7,AC53,AC53-(Y54-$C$7)),Z54+AC53),0) -> 1281.7108 | AD54: =IF(AB54-AC53<0,0,AB54-AC53) -> 0 | AE54: =($C$10*(1+$C$30)^T54) -> 1275.4584 | AF54: =IF(Z54>0,((AA54*$C$8)*((1+$C$30)^T54)),((AA54+AD54)*$C$8)*(1+$C$30)^T54) -> 170.06112 | AG54: =AE54-AF54 -> 1105.3973 | AH54: =$C$28/12*($C$4*((1+$C$29)^T54))+IF($C$31=T54,$C$33/12,0) -> 0 | AI54: =AG54-AH54 -> 1105.3973 | AJ54: =AJ53+AI54 -> 33016.29 | AK54: =1-(AF54/AE54) -> 0.86666667 | AL54: =AL53+AE54 -> 54520.135 | AM54: =AG54/$C$4 -> 0.077656238 | AO54: 51 | AP54: =($C$4*(1+($C$36-$C$39))^AO54)-AE54 -> 15168.594 | AQ54: =AJ54 -> 33016.29
S55: =IF(AND(AJ55>0,AJ54<0),"Payback","") | T55: 4 | U55: 4 | V55: Abril | W55: ='Análise Técnica'!$C$3 -> 750 | X55: =X43*((1-$C$27)) -> 692.30495 | Y55: =IF(X55-W55<0,W55-X55,0) -> 57.695051 | Z55: =IF(X55-W55>0,X55-W55,0) -> 0 | AA55: =$C$7 -> 100 | AB55: =IF(Y55-$C$7>0,Y55-$C$7,0) -> 0 | AC55: =IF(AC54-(Y55-$C$7)>0,IF(Y55>0,IF(Y55<$C$7,AC54,AC54-(Y55-$C$7)),Z55+AC54),0) -> 1281.7108 | AD55: =IF(AB55-AC54<0,0,AB55-AC54) -> 0 | AE55: =($C$10*(1+$C$30)^T55) -> 1275.4584 | AF55: =IF(Z55>0,((AA55*$C$8)*((1+$C$30)^T55)),((AA55+AD55)*$C$8)*(1+$C$30)^T55) -> 170.06112 | AG55: =AE55-AF55 -> 1105.3973 | AH55: =$C$28/12*($C$4*((1+$C$29)^T55))+IF($C$31=T55,$C$33/12,0) -> 0 | AI55: =AG55-AH55 -> 1105.3973 | AJ55: =AJ54+AI55 -> 34121.687 | AK55: =1-(AF55/AE55) -> 0.86666667 | AL55: =AL54+AE55 -> 55795.594 | AM55: =AG55/$C$4 -> 0.077656238 | AO55: 52 | AP55: =($C$4*(1+($C$36-$C$39))^AO55)-AE55 -> 15215.186 | AQ55: =AJ55 -> 34121.687
S56: =IF(AND(AJ56>0,AJ55<0),"Payback","") | T56: 4 | U56: 5 | V56: Maio | W56: ='Análise Técnica'!$C$3 -> 750 | X56: =X44*((1-$C$27)) -> 570.13519 | Y56: =IF(X56-W56<0,W56-X56,0) -> 179.86481 | Z56: =IF(X56-W56>0,X56-W56,0) -> 0 | AA56: =$C$7 -> 100 | AB56: =IF(Y56-$C$7>0,Y56-$C$7,0) -> 79.864814 | AC56: =IF(AC55-(Y56-$C$7)>0,IF(Y56>0,IF(Y56<$C$7,AC55,AC55-(Y56-$C$7)),Z56+AC55),0) -> 1201.846 | AD56: =IF(AB56-AC55<0,0,AB56-AC55) -> 0 | AE56: =($C$10*(1+$C$30)^T56) -> 1275.4584 | AF56: =IF(Z56>0,((AA56*$C$8)*((1+$C$30)^T56)),((AA56+AD56)*$C$8)*(1+$C$30)^T56) -> 170.06112 | AG56: =AE56-AF56 -> 1105.3973 | AH56: =$C$28/12*($C$4*((1+$C$29)^T56))+IF($C$31=T56,$C$33/12,0) -> 0 | AI56: =AG56-AH56 -> 1105.3973 | AJ56: =AJ55+AI56 -> 35227.084 | AK56: =1-(AF56/AE56) -> 0.86666667 | AL56: =AL55+AE56 -> 57071.052 | AM56: =AG56/$C$4 -> 0.077656238 | AO56: 53 | AP56: =($C$4*(1+($C$36-$C$39))^AO56)-AE56 -> 15261.909 | AQ56: =AJ56 -> 35227.084
S57: =IF(AND(AJ57>0,AJ56<0),"Payback","") | T57: 4 | U57: 6 | V57: Junho | W57: ='Análise Técnica'!$C$3 -> 750 | X57: =X45*((1-$C$27)) -> 527.25594 | Y57: =IF(X57-W57<0,W57-X57,0) -> 222.74406 | Z57: =IF(X57-W57>0,X57-W57,0) -> 0 | AA57: =$C$7 -> 100 | AB57: =IF(Y57-$C$7>0,Y57-$C$7,0) -> 122.74406 | AC57: =IF(AC56-(Y57-$C$7)>0,IF(Y57>0,IF(Y57<$C$7,AC56,AC56-(Y57-$C$7)),Z57+AC56),0) -> 1079.1019 | AD57: =IF(AB57-AC56<0,0,AB57-AC56) -> 0 | AE57: =($C$10*(1+$C$30)^T57) -> 1275.4584 | AF57: =IF(Z57>0,((AA57*$C$8)*((1+$C$30)^T57)),((AA57+AD57)*$C$8)*(1+$C$30)^T57) -> 170.06112 | AG57: =AE57-AF57 -> 1105.3973 | AH57: =$C$28/12*($C$4*((1+$C$29)^T57))+IF($C$31=T57,$C$33/12,0) -> 0 | AI57: =AG57-AH57 -> 1105.3973 | AJ57: =AJ56+AI57 -> 36332.481 | AK57: =1-(AF57/AE57) -> 0.86666667 | AL57: =AL56+AE57 -> 58346.51 | AM57: =AG57/$C$4 -> 0.077656238 | AO57: 54 | AP57: =($C$4*(1+($C$36-$C$39))^AO57)-AE57 -> 15308.765 | AQ57: =AJ57 -> 36332.481
S58: =IF(AND(AJ58>0,AJ57<0),"Payback","") | T58: 4 | U58: 7 | V58: Julho | W58: ='Análise Técnica'!$C$3 -> 750 | X58: =X46*((1-$C$27)) -> 527.18375 | Y58: =IF(X58-W58<0,W58-X58,0) -> 222.81625 | Z58: =IF(X58-W58>0,X58-W58,0) -> 0 | AA58: =$C$7 -> 100 | AB58: =IF(Y58-$C$7>0,Y58-$C$7,0) -> 122.81625 | AC58: =IF(AC57-(Y58-$C$7)>0,IF(Y58>0,IF(Y58<$C$7,AC57,AC57-(Y58-$C$7)),Z58+AC57),0) -> 956.2857 | AD58: =IF(AB58-AC57<0,0,AB58-AC57) -> 0 | AE58: =($C$10*(1+$C$30)^T58) -> 1275.4584 | AF58: =IF(Z58>0,((AA58*$C$8)*((1+$C$30)^T58)),((AA58+AD58)*$C$8)*(1+$C$30)^T58) -> 170.06112 | AG58: =AE58-AF58 -> 1105.3973 | AH58: =$C$28/12*($C$4*((1+$C$29)^T58))+IF($C$31=T58,$C$33/12,0) -> 0 | AI58: =AG58-AH58 -> 1105.3973 | AJ58: =AJ57+AI58 -> 37437.879 | AK58: =1-(AF58/AE58) -> 0.86666667 | AL58: =AL57+AE58 -> 59621.969 | AM58: =AG58/$C$4 -> 0.077656238 | AO58: 55 | AP58: =($C$4*(1+($C$36-$C$39))^AO58)-AE58 -> 15355.754 | AQ58: =AJ58 -> 37437.879
S59: =IF(AND(AJ59>0,AJ58<0),"Payback","") | T59: 4 | U59: 8 | V59: Agosto | W59: ='Análise Técnica'!$C$3 -> 750 | X59: =X47*((1-$C$27)) -> 651.90894 | Y59: =IF(X59-W59<0,W59-X59,0) -> 98.091057 | Z59: =IF(X59-W59>0,X59-W59,0) -> 0 | AA59: =$C$7 -> 100 | AB59: =IF(Y59-$C$7>0,Y59-$C$7,0) -> 0 | AC59: =IF(AC58-(Y59-$C$7)>0,IF(Y59>0,IF(Y59<$C$7,AC58,AC58-(Y59-$C$7)),Z59+AC58),0) -> 956.2857 | AD59: =IF(AB59-AC58<0,0,AB59-AC58) -> 0 | AE59: =($C$10*(1+$C$30)^T59) -> 1275.4584 | AF59: =IF(Z59>0,((AA59*$C$8)*((1+$C$30)^T59)),((AA59+AD59)*$C$8)*(1+$C$30)^T59) -> 170.06112 | AG59: =AE59-AF59 -> 1105.3973 | AH59: =$C$28/12*($C$4*((1+$C$29)^T59))+IF($C$31=T59,$C$33/12,0) -> 0 | AI59: =AG59-AH59 -> 1105.3973 | AJ59: =AJ58+AI59 -> 38543.276 | AK59: =1-(AF59/AE59) -> 0.86666667 | AL59: =AL58+AE59 -> 60897.427 | AM59: =AG59/$C$4 -> 0.077656238 | AO59: 56 | AP59: =($C$4*(1+($C$36-$C$39))^AO59)-AE59 -> 15402.875 | AQ59: =AJ59 -> 38543.276
S60: =IF(AND(AJ60>0,AJ59<0),"Payback","") | T60: 4 | U60: 9 | V60: Setembro | W60: ='Análise Técnica'!$C$3 -> 750 | X60: =X48*((1-$C$27)) -> 662.15954 | Y60: =IF(X60-W60<0,W60-X60,0) -> 87.840462 | Z60: =IF(X60-W60>0,X60-W60,0) -> 0 | AA60: =$C$7 -> 100 | AB60: =IF(Y60-$C$7>0,Y60-$C$7,0) -> 0 | AC60: =IF(AC59-(Y60-$C$7)>0,IF(Y60>0,IF(Y60<$C$7,AC59,AC59-(Y60-$C$7)),Z60+AC59),0) -> 956.2857 | AD60: =IF(AB60-AC59<0,0,AB60-AC59) -> 0 | AE60: =($C$10*(1+$C$30)^T60) -> 1275.4584 | AF60: =IF(Z60>0,((AA60*$C$8)*((1+$C$30)^T60)),((AA60+AD60)*$C$8)*(1+$C$30)^T60) -> 170.06112 | AG60: =AE60-AF60 -> 1105.3973 | AH60: =$C$28/12*($C$4*((1+$C$29)^T60))+IF($C$31=T60,$C$33/12,0) -> 0 | AI60: =AG60-AH60 -> 1105.3973 | AJ60: =AJ59+AI60 -> 39648.673 | AK60: =1-(AF60/AE60) -> 0.86666667 | AL60: =AL59+AE60 -> 62172.886 | AM60: =AG60/$C$4 -> 0.077656238 | AO60: 57 | AP60: =($C$4*(1+($C$36-$C$39))^AO60)-AE60 -> 15450.131 | AQ60: =AJ60 -> 39648.673
... S303: =IF(AND(AJ303>0,AJ302<0),"Payback","") | T303: 24 | U303: 12 | V303: Dezembro | W303: ='Análise Técnica'!$C$3 -> 750 | X303: =X291*((1-$C$27)) -> 743.80164 | Y303: =IF(X303-W303<0,W303-X303,0) -> 6.1983618 | Z303: =IF(X303-W303>0,X303-W303,0) -> 0 | AA303: =$C$7 -> 100 | AB303: =IF(Y303-$C$7>0,Y303-$C$7,0) -> 0 | AC303: =IF(AC302-(Y303-$C$7)>0,IF(Y303>0,IF(Y303<$C$7,AC302,AC302-(Y303-$C$7)),Z303+AC302),0) -> 0 | AD303: =IF(AB303-AC302<0,0,AB303-AC302) -> 0 | AE303: =($C$10*(1+$C$30)^T303) -> 5944.8569 | AF303: =IF(Z303>0,((AA303*$C$8)*((1+$C$30)^T303)),((AA303+AD303)*$C$8)*(1+$C$30)^T303) -> 792.64759 | AG303: =AE303-AF303 -> 5152.2093 | AH303: =$C$28/12*($C$4*((1+$C$29)^T303))+IF($C$31=T303,$C$33/12,0) -> 0 | AI303: =AG303-AH303 -> 5152.2093 | AJ303: =AJ302+AI303 -> 666757.49 | AK303: =1-(AF303/AE303) -> 0.86666667 | AL303: =AL302+AE303 -> 822441.82 | AM303: =AG303/$C$4 -> 0.3619524 | AO303: 300 | AP303: =($C$4*(1+($C$36-$C$39))^AO303)-AE303 -> 27318.829 | AQ303: =AJ303 -> 666757.49

Sheet Correção K
A1: Cód. | B1: Latitude | C1: Inclnação | D1: Jan | E1: Fev | F1: Mar | G1: Abr | H1: Mai | I1: Jun | J1: Jul | K1: Ago | L1: Set | M1: Out | N1: Nov | O1: Dez | P1: Média
A2: =B2+(C2/100) -> 0 | B2: 0 | C2: 0 | D2: 1 | E2: 1 | F2: 1 | G2: 1 | H2: 1 | I2: 1 | J2: 0 | K2: 1 | L2: 1 | M2: 1 | N2: 1 | O2: 1 | P2: =AVERAGE(D2:O2) -> 0.91666667 | R2: Latitude do Projeto | S2: ='Análise Técnica'!C8 -> 23 | T2: Fator de Correção por Inclinação (K) para Tabela B1B3 normal
A3: =B3+(C3/100) -> 0.05 | B3: 0 | C3: 5 | D3: 0.97 | E3: 0.98 | F3: 1 | G3: 1.01 | H3: 1.02 | I3: 1.02 | J3: 1.02 | K3: 1.01 | L3: 1 | M3: 0.98 | N3: 0.97 | O3: 0.96 | P3: =AVERAGE(D3:O3) -> 0.995 | R3: Inclinação Real | S3: ='Análise Técnica'!C12 -> 10 | T3: Janeiro | U3: Fevereiro | V3: Março | W3: Abril | X3: Maio | Y3: Junho | Z3: Julho | AA3: Agosto | AB3: Setembro | AC3: Outubro | AD3: Novembro | AE3: Dezembro | AF3: Média
A4: =B4+(C4/100) -> 0.1 | B4: 0 | C4: 10 | D4: 0.93 | E4: 0.95 | F4: 0.99 | G4: 1.02 | H4: 1.04 | I4: 1.04 | J4: 1.03 | K4: 1.01 | L4: 0.99 | M4: 0.96 | N4: 0.93 | O4: 0.92 | P4: =AVERAGE(D4:O4) -> 0.98416667 | R4: Código Lat x Incl | S4: =S2+S3/100 -> 23.1 | T4: =VLOOKUP($S$4,$A$2:$P$856,4,FALSE) -> 0.99 | U4: =VLOOKUP($S$4,$A$2:$P$856,5,FALSE) -> 1.01 | V4: =VLOOKUP($S$4,$A$2:$P$856,6,FALSE) -> 1.05 | W4: =VLOOKUP($S$4,$A$2:$P$856,7,FALSE) -> 1.08 | X4: =VLOOKUP($S$4,$A$2:$P$856,8,FALSE) -> 1.1 | Y4: =VLOOKUP($S$4,$A$2:$P$856,9,FALSE) -> 1.1 | Z4: =VLOOKUP($S$4,$A$2:$P$856,10,FALSE) -> 1.09 | AA4: =VLOOKUP($S$4,$A$2:$P$856,11,FALSE) -> 1.07 | AB4: =VLOOKUP($S$4,$A$2:$P$856,12,FALSE) -> 1.04 | AC4: =VLOOKUP($S$4,$A$2:$P$856,13,FALSE) -> 1.01 | AD4: =VLOOKUP($S$4,$A$2:$P$856,14,FALSE) -> 0.99 | AE4: =VLOOKUP($S$4,$A$2:$P$856,15,FALSE) -> 0.98 | AF4: =VLOOKUP($S$4,$A$2:$P$856,16,FALSE) -> 1.0425
A5: =B5+(C5/100) -> 0.15 | B5: 0 | C5: 15 | D5: 0.88 | E5: 0.92 | F5: 0.97 | G5: 1.02 | H5: 1.05 | I5: 1.05 | J5: 1.04 | K5: 1.01 | L5: 0.97 | M5: 0.92 | N5: 0.88 | O5: 0.87 | P5: =AVERAGE(D5:O5) -> 0.965
A6: =B6+(C6/100) -> 0.2 | B6: 0 | C6: 20 | D6: 0.83 | E6: 0.88 | F6: 0.95 | G6: 1.01 | H6: 1.05 | I6: 1.06 | J6: 1.04 | K6: 1 | L6: 0.95 | M6: 0.88 | N6: 0.83 | O6: 0.81 | P6: =AVERAGE(D6:O6) -> 0.94083333
A7: =B7+(C7/100) -> 0.25 | B7: 0 | C7: 25 | D7: 0.77 | E7: 0.83 | F7: 0.92 | G7: 0.99 | H7: 1.04 | I7: 1.06 | J7: 1.03 | K7: 0.99 | L7: 0.92 | M7: 0.84 | N7: 0.77 | O7: 0.75 | P7: =AVERAGE(D7:O7) -> 0.90916667
A8: =B8+(C8/100) -> 0.3 | B8: 0 | C8: 30 | D8: 0.7 | E8: 0.78 | F8: 0.88 | G8: 0.97 | H8: 1.03 | I8: 1.05 | J8: 1.02 | K8: 0.97 | L8: 0.88 | M8: 0.79 | N8: 0.71 | O8: 0.68 | P8: =AVERAGE(D8:O8) -> 0.87166667
A9: =B9+(C9/100) -> 0.35 | B9: 0 | C9: 35 | D9: 0.64 | E9: 0.72 | F9: 0.84 | G9: 0.94 | H9: 1.02 | I9: 1.03 | J9: 1 | K9: 0.94 | L9: 0.84 | M9: 0.74 | N9: 0.64 | O9: 0.61 | P9: =AVERAGE(D9:O9) -> 0.83
A10: =B10+(C10/100) -> 0.4 | B10: 0 | C10: 40 | D10: 0.56 | E10: 0.66 | F10: 0.79 | G10: 0.91 | H10: 0.99 | I10: 1.01 | J10: 0.98 | K10: 0.9 | L10: 0.8 | M10: 0.68 | N10: 0.57 | O10: 0.53 | P10: =AVERAGE(D10:O10) -> 0.78166667
A11: =B11+(C11/100) -> 0.45 | B11: 0 | C11: 45 | D11: 0.49 | E11: 0.59 | F11: 0.73 | G11: 0.87 | H11: 0.96 | I11: 0.98 | J11: 0.95 | K11: 0.87 | L11: 0.75 | M11: 0.61 | N11: 0.5 | O11: 0.45 | P11: =AVERAGE(D11:O11) -> 0.72916667
A12: =B12+(C12/100) -> 0.5 | B12: 0 | C12: 50 | D12: 0.41 | E12: 0.52 | F12: 0.68 | G12: 0.82 | H12: 0.92 | I12: 0.95 | J12: 0.91 | K12: 0.82 | L12: 0.69 | M12: 0.54 | N12: 0.42 | O12: 0.37 | P12: =AVERAGE(D12:O12) -> 0.67083333
A13: =B13+(C13/100) -> 0.55 | B13: 0 | C13: 55 | D13: 0.33 | E13: 0.45 | F13: 0.61 | G13: 0.77 | H13: 0.88 | I13: 0.91 | J13: 0.87 | K13: 0.77 | L13: 0.63 | M13: 0.47 | N13: 0.34 | O13: 0.28 | P13: =AVERAGE(D13:O13) -> 0.60916667
A14: =B14+(C14/100) -> 0.6 | B14: 0 | C14: 60 | D14: 0.24 | E14: 0.37 | F14: 0.55 | G14: 0.71 | H14: 0.83 | I14: 0.86 | J14: 0.82 | K14: 0.72 | L14: 0.57 | M14: 0.4 | N14: 0.26 | O14: 0.2 | P14: =AVERAGE(D14:O14) -> 0.54416667
A15: =B15+(C15/100) -> 0.65 | B15: 0 | C15: 65 | D15: 0.16 | E15: 0.3 | F15: 0.48 | G15: 0.65 | H15: 0.77 | I15: 0.81 | J15: 0.77 | K15: 0.66 | L15: 0.5 | M15: 0.32 | N15: 0.18 | O15: 0.13 | P15: =AVERAGE(D15:O15) -> 0.4775
A16: =B16+(C16/100) -> 0.7 | B16: 0 | C16: 70 | D16: 0.11 | E16: 0.22 | F16: 0.4 | G16: 0.59 | H16: 0.72 | I16: 0.75 | J16: 0.71 | K16: 0.6 | L16: 0.43 | M16: 0.25 | N16: 0.13 | O16: 0.12 | P16: =AVERAGE(D16:O16) -> 0.41916667
... A24: =B24+(C24/100) -> 1.15 | B24: 1 | C24: 15 | D24: 0.88 | E24: 0.92 | F24: 0.97 | G24: 1.02 | H24: 1.05 | I24: 1.06 | J24: 1.04 | K24: 1.01 | L24: 0.97 | M24: 0.93 | N24: 0.89 | O24: 0.87 | P24: =AVERAGE(D24:O24) -> 0.9675
A25: =B25+(C25/100) -> 1.2 | B25: 1 | C25: 20 | D25: 0.83 | E25: ,88, | F25: 0.95 | G25: 1.01 | H25: 1.05 | I25: 1.06 | J25: 1.04 | K25: 1.01 | L25: 0.95 | M25: 0.89 | N25: 0.84 | O25: 0.81 | P25: =AVERAGE(D25:O25) -> 0.94909091
A26: =B26+(C26/100) -> 1.25 | B26: 1 | C26: 25 | D26: 0.77 | E26: 0.84 | F26: 0.92 | G26: 1 | H26: 1.05 | I26: 1.06 | J26: 1.04 | K26: 0.99 | L26: 0.92 | M26: 0.85 | N26: 0.78 | O26: 0.75 | P26: =AVERAGE(D26:O26) -> 0.91416667
A27: =B27+(C27/100) -> 1.3 | B27: 1 | C27: 30 | D27: 0.71 | E27: 0.79 | F27: 0.89 | G27: 0.98 | H27: 1.04 | I27: 1.05 | J27: 1.03 | K27: 0.97 | L27: 0.89 | M27: 0.8 | N27: 0.72 | O27: 0.69 | P27: =AVERAGE(D27:O27) -> 0.88
A28: =B28+(C28/100) -> 1.35 | B28: 1 | C28: 35 | D28: 0.65 | E28: 0.73 | F28: 0.84 | G28: 0.95 | H28: 1.02 | I28: 1.04 | J28: 1.01 | K28: 0.95 | L28: 0.85 | M28: 0.74 | N28: 0.65 | O28: 0.62 | P28: =AVERAGE(D28:O28) -> 0.8375
A29: =B29+(C29/100) -> 1.4 | B29: 1 | C29: 40 | D29: 0.57 | E29: 0.67 | F29: 0.8 | G29: 0.92 | H29: 1 | I29: 1.02 | J29: 0.98 | K29: 0.91 | L29: 0.81 | M29: 0.69 | N29: 0.58 | O29: 0.54 | P29: =AVERAGE(D29:O29) -> 0.79083333
A30: =B30+(C30/100) -> 1.45 | B30: 1 | C30: 45 | D30: 0.5 | E30: 0.61 | F30: 0.74 | G30: 0.88 | H30: 0.97 | I30: 0.99 | J30: 0.95 | K30: 0.87 | L30: 0.76 | M30: 0.62 | N30: 0.51 | O30: 0.46 | P30: =AVERAGE(D30:O30) -> 0.73833333
A31: =B31+(C31/100) -> 1.5 | B31: 1 | C31: 50 | D31: 0.42 | E31: 0.54 | F31: 0.69 | G31: 0.83 | H31: 0.93 | I31: 0.96 | J31: 0.92 | K31: 0.83 | L31: 0.7 | M31: 0.56 | N31: 0.43 | O31: 0.38 | P31: =AVERAGE(D31:O31) -> 0.6825
A32: =B32+(C32/100) -> 1.55 | B32: 1 | C32: 55 | D32: 0.34 | E32: 0.46 | F32: 0.63 | G32: 0.78 | H32: 0.89 | I32: 0.92 | J32: 0.88 | K32: 0.78 | L32: 0.64 | M32: 0.49 | N32: 0.35 | O32: 0.3 | P32: =AVERAGE(D32:O32) -> 0.62166667
A33: =B33+(C33/100) -> 1.6 | B33: 1 | C33: 60 | D33: 0.26 | E33: 0.39 | F33: 0.56 | G33: 0.73 | H33: 0.84 | I33: 0.87 | J33: 0.83 | K33: 0.73 | L33: 0.58 | M33: 0.41 | N33: 0.27 | O33: 0.21 | P33: =AVERAGE(D33:O33) -> 0.55666667
A34: =B34+(C34/100) -> 1.65 | B34: 1 | C34: 65 | D34: 0.17 | E34: 0.31 | F34: 0.49 | G34: 0.66 | H34: 0.79 | I34: 0.82 | J34: 0.78 | K34: 0.67 | L34: 0.51 | M34: 0.34 | N34: 0.19 | O34: 0.13 | P34: =AVERAGE(D34:O34) -> 0.48833333
A35: =B35+(C35/100) -> 1.7 | B35: 1 | C35: 70 | D35: 0.11 | E35: 0.23 | F35: 0.42 | G35: 0.6 | H35: 0.73 | I35: 0.77 | J35: 0.72 | K35: 0.61 | L35: 0.45 | M35: 0.26 | N35: 0.13 | O35: 0.12 | P35: =AVERAGE(D35:O35) -> 0.42916667
A36: =B36+(C36/100) -> 1.75 | B36: 1 | C36: 75 | D36: 0.11 | E36: 0.15 | F36: 0.34 | G36: 0.53 | H36: 0.67 | I36: 0.71 | J36: 0.66 | K36: 0.55 | L36: 0.37 | M36: 0.18 | N36: 0.12 | O36: 0.11 | P36: =AVERAGE(D36:O36) -> 0.375
A37: =B37+(C37/100) -> 1.8 | B37: 1 | C37: 80 | D37: 0.1 | E37: 0.1 | F37: 0.26 | G37: 0.46 | H37: 0.6 | I37: 0.64 | J37: 0.6 | K37: 0.48 | L37: 0.3 | M37: 0.13 | N37: 0.11 | O37: 0.1 | P37: =AVERAGE(D37:O37) -> 0.32333333
... A43: =B43+(C43/100) -> 2.15 | B43: 2 | C43: 15 | D43: 0.89 | E43: 0.93 | F43: 0.98 | G43: 1.02 | H43: 1.05 | I43: 1.06 | J43: 1.05 | K43: 1.02 | L43: 0.98 | M43: 0.93 | N43: 0.89 | O43: 0.87 | P43: =AVERAGE(D43:O43) -> 0.9725
A44: =B44+(C44/100) -> 2.2 | B44: 2 | C44: 20 | D44: 0.84 | E44: ,89, | F44: 0.96 | G44: 1.02 | H44: 1.06 | I44: 1.07 | J44: 1.05 | K44: 1.01 | L44: 0.96 | M44: 0.89 | N44: 0.84 | O44: 0.82 | P44: =AVERAGE(D44:O44) -> 0.95636364
A45: =B45+(C45/100) -> 2.25 | B45: 2 | C45: 25 | D45: 0.78 | E45: 0.84 | F45: 0.93 | G45: 1.01 | H45: 1.06 | I45: 1.07 | J45: 1.04 | K45: 1 | L45: 0.93 | M45: 0.85 | N45: 0.79 | O45: 0.76 | P45: =AVERAGE(D45:O45) -> 0.92166667
A46: =B46+(C46/100) -> 2.3 | B46: 2 | C46: 30 | D46: 0.72 | E46: 0.8 | F46: 0.89 | G46: 0.99 | H46: 1.05 | I46: 1.06 | J46: 1.03 | K46: 0.98 | L46: 0.9 | M46: 0.8 | N46: 0.73 | O46: 0.69 | P46: =AVERAGE(D46:O46) -> 0.88666667
A47: =B47+(C47/100) -> 2.35 | B47: 2 | C47: 35 | D47: 0.65 | E47: 0.74 | F47: 0.85 | G47: 0.96 | H47: 1.03 | I47: 1.05 | J47: 1.02 | K47: 0.95 | L47: 0.86 | M47: 0.75 | N47: 0.66 | O47: 0.62 | P47: =AVERAGE(D47:O47) -> 0.845
A48: =B48+(C48/100) -> 2.4 | B48: 2 | C48: 40 | D48: 0.58 | E48: 0.68 | F48: 0.81 | G48: 0.93 | H48: 1.01 | I48: 1.03 | J48: 0.99 | K48: 0.92 | L48: 0.81 | M48: 0.69 | N48: 0.59 | O48: 0.55 | P48: =AVERAGE(D48:O48) -> 0.79916667
A49: =B49+(C49/100) -> 2.45 | B49: 2 | C49: 45 | D49: 0.51 | E49: 0.62 | F49: 0.75 | G49: 0.89 | H49: 0.98 | I49: 1 | J49: 0.96 | K49: 0.88 | L49: 0.77 | M49: 0.63 | N49: 0.52 | O49: 0.47 | P49: =AVERAGE(D49:O49) -> 0.74833333
A50: =B50+(C50/100) -> 2.5 | B50: 2 | C50: 50 | D50: 0.43 | E50: 0.55 | F50: 0.7 | G50: 0.84 | H50: 0.94 | I50: 0.97 | J50: 0.93 | K50: 0.84 | L50: 0.71 | M50: 0.57 | N50: 0.45 | O50: 0.39 | P50: =AVERAGE(D50:O50) -> 0.69333333
A51: =B51+(C51/100) -> 2.55 | B51: 2 | C51: 55 | D51: 0.35 | E51: 0.48 | F51: 0.64 | G51: 0.79 | H51: 0.9 | I51: 0.93 | J51: 0.89 | K51: 0.79 | L51: 0.65 | M51: 0.5 | N51: 0.37 | O51: 0.31 | P51: =AVERAGE(D51:O51) -> 0.63333333
A52: =B52+(C52/100) -> 2.6 | B52: 2 | C52: 60 | D52: 0.27 | E52: 0.4 | F52: 0.57 | G52: 0.74 | H52: 0.85 | I52: 0.88 | J52: 0.84 | K52: 0.74 | L52: 0.59 | M52: 0.42 | N52: 0.29 | O52: 0.23 | P52: =AVERAGE(D52:O52) -> 0.56833333
A53: =B53+(C53/100) -> 2.65 | B53: 2 | C53: 65 | D53: 0.19 | E53: 0.32 | F53: 0.5 | G53: 0.68 | H53: 0.8 | I53: 0.84 | J53: 0.79 | K53: 0.68 | L53: 0.53 | M53: 0.35 | N53: 0.2 | O53: 0.14 | P53: =AVERAGE(D53:O53) -> 0.50166667
A54: =B54+(C54/100) -> 2.7 | B54: 2 | C54: 70 | D54: 0.11 | E54: 0.24 | F54: 0.43 | G54: 0.61 | H54: 0.74 | I54: 0.78 | J54: 0.73 | K54: 0.62 | L54: 0.46 | M54: 0.27 | N54: 0.13 | O54: 0.12 | P54: =AVERAGE(D54:O54) -> 0.43666667
A55: =B55+(C55/100) -> 2.75 | B55: 2 | C55: 75 | D55: 0.11 | E55: 0.16 | F55: 0.36 | G55: 0.55 | H55: 0.68 | I55: 0.72 | J55: 0.67 | K55: 0.56 | L55: 0.39 | M55: 0.19 | N55: 0.12 | O55: 0.11 | P55: =AVERAGE(D55:O55) -> 0.385
A56: =B56+(C56/100) -> 2.8 | B56: 2 | C56: 80 | D56: 0.1 | E56: 0.1 | F56: 0.28 | G56: 0.47 | H56: 0.61 | I56: 0.66 | J56: 0.61 | K56: 0.49 | L56: 0.31 | M56: 0.13 | N56: 0.11 | O56: 0.1 | P56: =AVERAGE(D56:O56) -> 0.33083333
... A233: =B233+(C233/100) -> 12.15 | B233: 12 | C233: 15 | D233: 0.87 | E233: 0.88 | F233: 0.92 | G233: 0.97 | H233: 1.02 | I233: 1.05 | J233: 1.08 | K233: 1.04 | L233: 1.01 | M233: 0.97 | N233: 0.92 | O233: 0.88 | P233: =AVERAGE(D233:O233) -> 0.9675
A234: =B234+(C234/100) -> 12.2 | B234: 12 | C234: 20 | D234: 0.81 | E234: 0.83 | F234: ,88, | G234: 0.95 | H234: 1.01 | I234: 1.05 | J234: 1.09 | K234: 1.04 | L234: 1 | M234: 0.95 | N234: 0.88 | O234: 0.83 | P234: =AVERAGE(D234:O234) -> 0.94909091
A235: =B235+(C235/100) -> 12.25 | B235: 12 | C235: 25 | D235: 0.75 | E235: 0.77 | F235: 0.83 | G235: 0.92 | H235: 0.99 | I235: 1.04 | J235: 1.1 | K235: 1.03 | L235: 0.99 | M235: 0.92 | N235: 0.84 | O235: 0.77 | P235: =AVERAGE(D235:O235) -> 0.9125
A236: =B236+(C236/100) -> 12.3 | B236: 12 | C236: 30 | D236: 0.68 | E236: 0.7 | F236: 0.78 | G236: 0.88 | H236: 0.97 | I236: 1.03 | J236: 1.1 | K236: 1.02 | L236: 0.97 | M236: 0.88 | N236: 0.79 | O236: 0.71 | P236: =AVERAGE(D236:O236) -> 0.87583333
A237: =B237+(C237/100) -> 12.35 | B237: 12 | C237: 35 | D237: 0.61 | E237: 0.64 | F237: 0.72 | G237: 0.84 | H237: 0.94 | I237: 1.02 | J237: 1.09 | K237: 1 | L237: 0.94 | M237: 0.84 | N237: 0.74 | O237: 0.64 | P237: =AVERAGE(D237:O237) -> 0.835
A238: =B238+(C238/100) -> 12.4 | B238: 12 | C238: 40 | D238: 0.53 | E238: 0.56 | F238: 0.66 | G238: 0.79 | H238: 0.91 | I238: 0.99 | J238: 1.08 | K238: 0.98 | L238: 0.9 | M238: 0.8 | N238: 0.68 | O238: 0.57 | P238: =AVERAGE(D238:O238) -> 0.7875
A239: =B239+(C239/100) -> 12.45 | B239: 12 | C239: 45 | D239: 0.45 | E239: 0.49 | F239: 0.59 | G239: 0.73 | H239: 0.87 | I239: 0.96 | J239: 1.06 | K239: 0.95 | L239: 0.87 | M239: 0.75 | N239: 0.61 | O239: 0.5 | P239: =AVERAGE(D239:O239) -> 0.73583333
A240: =B240+(C240/100) -> 12.5 | B240: 12 | C240: 50 | D240: 0.37 | E240: 0.41 | F240: 0.52 | G240: 0.68 | H240: 0.82 | I240: 0.92 | J240: 1.03 | K240: 0.91 | L240: 0.82 | M240: 0.69 | N240: 0.54 | O240: 0.42 | P240: =AVERAGE(D240:O240) -> 0.6775
A241: =B241+(C241/100) -> 12.55 | B241: 12 | C241: 55 | D241: 0.28 | E241: 0.33 | F241: 0.45 | G241: 0.61 | H241: 0.77 | I241: 0.88 | J241: 1 | K241: 0.87 | L241: 0.77 | M241: 0.63 | N241: 0.47 | O241: 0.34 | P241: =AVERAGE(D241:O241) -> 0.61666667
A242: =B242+(C242/100) -> 12.6 | B242: 12 | C242: 60 | D242: 0.2 | E242: 0.24 | F242: 0.37 | G242: 0.55 | H242: 0.71 | I242: 0.83 | J242: 0.96 | K242: 0.82 | L242: 0.72 | M242: 0.57 | N242: 0.4 | O242: 0.26 | P242: =AVERAGE(D242:O242) -> 0.5525
A243: =B243+(C243/100) -> 12.65 | B243: 12 | C243: 65 | D243: 0.13 | E243: 0.16 | F243: 0.3 | G243: 0.48 | H243: 0.65 | I243: 0.77 | J243: 0.91 | K243: 0.77 | L243: 0.66 | M243: 0.5 | N243: 0.32 | O243: 0.18 | P243: =AVERAGE(D243:O243) -> 0.48583333
A244: =B244+(C244/100) -> 12.7 | B244: 12 | C244: 70 | D244: 0.12 | E244: 0.11 | F244: 0.22 | G244: 0.4 | H244: 0.59 | I244: 0.72 | J244: 0.86 | K244: 0.71 | L244: 0.6 | M244: 0.43 | N244: 0.25 | O244: 0.13 | P244: =AVERAGE(D244:O244) -> 0.42833333
A245: =B245+(C245/100) -> 12.75 | B245: 12 | C245: 75 | D245: 0.11 | E245: 0.11 | F245: 0.13 | G245: 0.33 | H245: 0.52 | I245: 0.65 | J245: 0.81 | K245: 0.65 | L245: 0.53 | M245: 0.36 | N245: 0.17 | O245: 0.12 | P245: =AVERAGE(D245:O245) -> 0.37416667
A246: =B246+(C246/100) -> 12.8 | B246: 12 | C246: 80 | D246: 0.1 | E246: 0.1 | F246: 0.1 | G246: 0.25 | H246: 0.45 | I246: 0.58 | J246: 0.74 | K246: 0.58 | L246: 0.47 | M246: 0.29 | N246: 0.13 | O246: 0.12 | P246: =AVERAGE(D246:O246) -> 0.32583333
... A624: =B624+(C624/100) -> 32.7 | B624: 32 | C624: 70 | D624: 0.53 | E624: 0.66 | F624: 0.87 | G624: 1.11 | H624: 1.27 | I624: 1.28 | J624: 1.17 | K624: 1.03 | L624: 0.85 | M624: 0.66 | N624: 0.53 | O624: 0.48 | P624: =AVERAGE(D624:O624) -> 0.87
A625: =B625+(C625/100) -> 32.75 | B625: 32 | C625: 75 | D625: 0.45 | E625: 0.6 | F625: ,,81 | G625: 1.06 | H625: 1.23 | I625: 1.24 | J625: 1.13 | K625: 0.98 | L625: 0.79 | M625: 0.6 | N625: 0.46 | O625: 0.4 | P625: =AVERAGE(D625:O625) -> 0.81272727
A626: =B626+(C626/100) -> 32.8 | B626: 32 | C626: 80 | D626: 0.38 | E626: 0.52 | F626: 0.75 | G626: 1 | H626: 1.18 | I626: 1.19 | J626: 1.08 | K626: 0.92 | L626: 0.73 | M626: 0.53 | N626: 0.38 | O626: 0.33 | P626: =AVERAGE(D626:O626) -> 0.74916667
A627: =B627+(C627/100) -> 32.85 | B627: 32 | C627: 85 | D627: 0.3 | E627: 0.45 | F627: 0.67 | G627: 0.93 | H627: 1.12 | I627: 1.13 | J627: 1.02 | K627: 0.86 | L627: 0.66 | M627: 0.45 | N627: 0.31 | O627: 0.25 | P627: =AVERAGE(D627:O627) -> 0.67916667
A628: =B628+(C628/100) -> 32.9 | B628: 32 | C628: 90 | D628: 0.22 | E628: 0.37 | F628: 0.6 | G628: 0.86 | H628: 1.05 | I628: 1.07 | J628: 0.96 | K628: 0.79 | L628: 0.59 | M628: 0.38 | N628: 0.23 | O628: 0.17 | P628: =AVERAGE(D628:O628) -> 0.6075
A629: =B629+(C629/100) -> 33 | B629: 33 | C629: 0 | D629: 1 | E629: 1 | F629: 1 | G629: 1 | H629: 1 | I629: 1 | J629: 1 | K629: 1 | L629: 1 | M629: 1 | N629: 1 | O629: 1 | P629: =AVERAGE(D629:O629) -> 1
A630: =B630+(C630/100) -> 33.05 | B630: 33 | C630: 5 | D630: 1.01 | E630: 1.02 | F630: 1.04 | G630: 1.06 | H630: 1.07 | I630: 1.07 | J630: 1.06 | K630: 1.05 | L630: 1.04 | M630: 1.02 | N630: 1.01 | O630: 1.01 | P630: =AVERAGE(D630:O630) -> 1.0383333
A631: =B631+(C631/100) -> 33.1 | B631: 33 | C631: 10 | D631: 1.01 | E631: 1.04 | F631: 1.07 | G631: 1.12 | H631: 1.14 | I631: 1.14 | J631: 1.12 | K631: 1.09 | L631: 1.06 | M631: 1.03 | N631: 1.01 | O631: 1 | P631: =AVERAGE(D631:O631) -> 1.0691667
A632: =B632+(C632/100) -> 33.15 | B632: 33 | C632: 15 | D632: 1.01 | E632: 1.05 | F632: 1.1 | G632: 1.16 | H632: 1.2 | I632: 1.19 | J632: 1.16 | K632: 1.13 | L632: 1.09 | M632: 1.04 | N632: 1.01 | O632: 1 | P632: =AVERAGE(D632:O632) -> 1.095
A633: =B633+(C633/100) -> 33.2 | B633: 33 | C633: 20 | D633: 1 | E633: 1.05 | F633: 1.12 | G633: 1.2 | H633: 1.25 | I633: 1.24 | J633: 1.2 | K633: 1.16 | L633: 1.1 | M633: 1.04 | N633: 1 | O633: 0.98 | P633: =AVERAGE(D633:O633) -> 1.1116667
A634: =B634+(C634/100) -> 33.25 | B634: 33 | C634: 25 | D634: 0.98 | E634: 1.04 | F634: 1.13 | G634: 1.23 | H634: 1.3 | I634: 1.29 | J634: 1.24 | K634: 1.18 | L634: 1.11 | M634: 1.03 | N634: 0.98 | O634: 0.96 | P634: =AVERAGE(D634:O634) -> 1.1225
A635: =B635+(C635/100) -> 33.3 | B635: 33 | C635: 30 | D635: 0.95 | E635: 1.03 | F635: 1.14 | G635: 1.25 | H635: 1.33 | I635: 1.32 | J635: 1.26 | K635: 1.2 | L635: 1.11 | M635: 1.02 | N635: 0.95 | O635: 0.93 | P635: =AVERAGE(D635:O635) -> 1.1241667
A636: =B636+(C636/100) -> 33.35 | B636: 33 | C636: 35 | D636: 0.92 | E636: 1.01 | F636: 1.13 | G636: 1.27 | H636: 1.36 | I636: 1.35 | J636: 1.28 | K636: 1.2 | L636: 1.1 | M636: 1 | N636: 0.92 | O636: 0.89 | P636: =AVERAGE(D636:O636) -> 1.1191667
A637: =B637+(C637/100) -> 33.4 | B637: 33 | C637: 40 | D637: 0.88 | E637: 0.98 | F637: 1.12 | G637: 1.27 | H637: 1.38 | I637: 1.37 | J637: 1.29 | K637: 1.2 | L637: 1.09 | M637: 0.97 | N637: 0.88 | O637: 0.85 | P637: =AVERAGE(D637:O637) -> 1.1066667
... A662: =B662+(C662/100) -> 34.7 | B662: 34 | C662: 70 | D662: 0.53 | E662: 0.66 | F662: 0.87 | G662: 1.11 | H662: 1.27 | I662: 1.28 | J662: 1.17 | K662: 1.03 | L662: 0.85 | M662: 0.66 | N662: 0.53 | O662: 0.48 | P662: =AVERAGE(D662:O662) -> 0.87
A663: =B663+(C663/100) -> 34.75 | B663: 34 | C663: 75 | D663: 0.45 | E663: 0.6 | F663: ,,81 | G663: 1.06 | H663: 1.23 | I663: 1.24 | J663: 1.13 | K663: 0.98 | L663: 0.79 | M663: 0.6 | N663: 0.46 | O663: 0.4 | P663: =AVERAGE(D663:O663) -> 0.81272727
A664: =B664+(C664/100) -> 34.8 | B664: 34 | C664: 80 | D664: 0.38 | E664: 0.52 | F664: 0.75 | G664: 1 | H664: 1.18 | I664: 1.19 | J664: 1.08 | K664: 0.92 | L664: 0.73 | M664: 0.53 | N664: 0.38 | O664: 0.33 | P664: =AVERAGE(D664:O664) -> 0.74916667
A665: =B665+(C665/100) -> 34.85 | B665: 34 | C665: 85 | D665: 0.3 | E665: 0.45 | F665: 0.67 | G665: 0.93 | H665: 1.12 | I665: 1.13 | J665: 1.02 | K665: 0.86 | L665: 0.66 | M665: 0.45 | N665: 0.31 | O665: 0.25 | P665: =AVERAGE(D665:O665) -> 0.67916667
A666: =B666+(C666/100) -> 34.9 | B666: 34 | C666: 90 | D666: 0.22 | E666: 0.37 | F666: 0.6 | G666: 0.86 | H666: 1.05 | I666: 1.07 | J666: 0.96 | K666: 0.79 | L666: 0.59 | M666: 0.38 | N666: 0.23 | O666: 0.17 | P666: =AVERAGE(D666:O666) -> 0.6075
A667: =B667+(C667/100) -> 35 | B667: 35 | C667: 0 | D667: 1 | E667: 1 | F667: 1 | G667: 1 | H667: 1 | I667: 1 | J667: 1 | K667: 1 | L667: 1 | M667: 1 | N667: 1 | O667: 1 | P667: =AVERAGE(D667:O667) -> 1
A668: =B668+(C668/100) -> 35.05 | B668: 35 | C668: 5 | D668: 1.01 | E668: 1.03 | F668: 1.04 | G668: 1.06 | H668: 1.08 | I668: 1.07 | J668: 1.06 | K668: 1.05 | L668: 1.04 | M668: 1.02 | N668: 1.01 | O668: 1.01 | P668: =AVERAGE(D668:O668) -> 1.04
A669: =B669+(C669/100) -> 35.1 | B669: 35 | C669: 10 | D669: 1.02 | E669: 1.04 | F669: 1.08 | G669: 1.12 | H669: 1.15 | I669: 1.14 | J669: 1.12 | K669: 1.1 | L669: 1.07 | M669: 1.04 | N669: 1.02 | O669: 1.01 | P669: =AVERAGE(D669:O669) -> 1.0758333
A670: =B670+(C670/100) -> 35.15 | B670: 35 | C670: 15 | D670: 1.02 | E670: 1.05 | F670: 1.11 | G670: 1.17 | H670: 1.21 | I670: 1.21 | J670: 1.17 | K670: 1.14 | L670: 1.09 | M670: 1.05 | N670: 1.02 | O670: 1 | P670: =AVERAGE(D670:O670) -> 1.1033333
A671: =B671+(C671/100) -> 35.2 | B671: 35 | C671: 20 | D671: 1.01 | E671: 1.06 | F671: 1.13 | G671: 1.22 | H671: 1.27 | I671: 1.26 | J671: 1.22 | K671: 1.17 | L671: 1.11 | M671: 1.05 | N671: 1.01 | O671: 0.99 | P671: =AVERAGE(D671:O671) -> 1.125
A672: =B672+(C672/100) -> 35.25 | B672: 35 | C672: 25 | D672: 0.99 | E672: 1.05 | F672: 1.15 | G672: 1.25 | H672: 1.32 | I672: 1.31 | J672: 1.25 | K672: 1.2 | L672: 1.12 | M672: 1.05 | N672: 0.99 | O672: 0.97 | P672: =AVERAGE(D672:O672) -> 1.1375
A673: =B673+(C673/100) -> 35.3 | B673: 35 | C673: 30 | D673: 0.97 | E673: 1.04 | F673: 1.15 | G673: 1.28 | H673: 1.36 | I673: 1.35 | J673: 1.28 | K673: 1.21 | L673: 1.13 | M673: 1.04 | N673: 0.97 | O673: 0.94 | P673: =AVERAGE(D673:O673) -> 1.1433333
A674: =B674+(C674/100) -> 35.35 | B674: 35 | C674: 35 | D674: 0.94 | E674: 1.02 | F674: 1.15 | G674: 1.29 | H674: 1.39 | I674: 1.38 | J674: 1.31 | K674: 1.22 | L674: 1.12 | M674: 1.02 | N674: 0.94 | O674: 0.91 | P674: =AVERAGE(D674:O674) -> 1.1408333
A675: =B675+(C675/100) -> 35.4 | B675: 35 | C675: 40 | D675: 0.9 | E675: 1 | F675: 1.14 | G675: 1.3 | H675: 1.41 | I675: 1.4 | J675: 1.32 | K675: 1.23 | L675: 1.11 | M675: 0.99 | N675: 0.9 | O675: 0.87 | P675: =AVERAGE(D675:O675) -> 1.1308333
... A781: =B781+(C781/100) -> 41 | B781: 41 | C781: 0 | D781: 1 | E781: 1 | F781: 1 | G781: 1 | H781: 1 | I781: 1 | J781: 1 | K781: 1 | L781: 1 | M781: 1 | N781: 1 | O781: 1 | P781: =AVERAGE(D781:O781) -> 1
A782: =B782+(C782/100) -> 41.05 | B782: 41 | C782: 5 | D782: 1.02 | E782: 1.03 | F782: 1.05 | G782: 1.08 | H782: 1,,09 | I782: 1.09 | J782: 1.07 | K782: 1.06 | L782: 1.05 | M782: 1.03 | N782: 1.02 | O782: 1.02 | P782: =AVERAGE(D782:O782) -> 1.0472727
A783: =B783+(C783/100) -> 41.1 | B783: 41 | C783: 10 | D783: 1.03 | E783: 1.06 | F783: 1.1 | G783: 1.15 | H783: 1.18 | I783: 1.17 | J783: 1.14 | K783: 1.12 | L783: 1.09 | M783: 1.06 | N783: 1.03 | O783: 1.02 | P783: =AVERAGE(D783:O783) -> 1.0958333
A784: =B784+(C784/100) -> 41.15 | B784: 41 | C784: 15 | D784: 1.04 | E784: 1.08 | F784: 1.14 | G784: 1.21 | H784: 1.26 | I784: 1.24 | J784: 1.21 | K784: 1.17 | L784: 1.12 | M784: 1.07 | N784: 1.04 | O784: 1.03 | P784: =AVERAGE(D784:O784) -> 1.1341667
A785: =B785+(C785/100) -> 41.2 | B785: 41 | C785: 20 | D785: 1.04 | E785: 1.09 | F785: 1.17 | G785: 1.27 | H785: 1.33 | I785: 1.31 | J785: 1.26 | K785: 1.21 | L785: 1.15 | M785: 1.08 | N785: 1.04 | O785: 1.02 | P785: =AVERAGE(D785:O785) -> 1.1641667
A786: =B786+(C786/100) -> 41.25 | B786: 41 | C786: 25 | D786: 1.03 | E786: 1.1 | F786: 1.2 | G786: 1.32 | H786: 1.39 | I786: 1.37 | J786: 1.31 | K786: 1.24 | L786: 1.17 | M786: 1.09 | N786: 1.03 | O786: 1.01 | P786: =AVERAGE(D786:O786) -> 1.1883333
A787: =B787+(C787/100) -> 41.3 | B787: 41 | C787: 30 | D787: 1.02 | E787: 1.09 | F787: 1.21 | G787: 1.35 | H787: 1.44 | I787: 1.42 | J787: 1.35 | K787: 1.27 | L787: 1.18 | M787: 1.08 | N787: 1.01 | O787: 0.99 | P787: =AVERAGE(D787:O787) -> 1.2008333
A788: =B788+(C788/100) -> 41.35 | B788: 41 | C788: 35 | D788: 0.99 | E788: 1.08 | F788: 1.22 | G788: 1.38 | H788: 1.49 | I788: 1.47 | J788: 1.38 | K788: 1.29 | L788: 1.18 | M788: 1.07 | N788: 0.99 | O788: 0.96 | P788: =AVERAGE(D788:O788) -> 1.2083333
A789: =B789+(C789/100) -> 41.4 | B789: 41 | C789: 40 | D789: 0.96 | E789: 1.06 | F789: 1.22 | G789: 1.4 | H789: 1.52 | I789: 1.5 | J789: 1.4 | K789: 1.3 | L789: 1.18 | M789: 1.05 | N789: 0.96 | O789: 0.93 | P789: =AVERAGE(D789:O789) -> 1.2066667
A790: =B790+(C790/100) -> 41.45 | B790: 41 | C790: 45 | D790: 0.93 | E790: 1.04 | F790: 1.21 | G790: 1.41 | H790: 1.55 | I790: 1.52 | J790: 1.42 | K790: 1.3 | L790: 1.16 | M790: 1.03 | N790: 0.93 | O790: 0.89 | P790: =AVERAGE(D790:O790) -> 1.1991667
A791: =B791+(C791/100) -> 41.5 | B791: 41 | C791: 50 | D791: 0.88 | E791: 1.01 | F791: 1.19 | G791: 1.41 | H791: 1.56 | I791: 1.54 | J791: 1.42 | K791: 1.3 | L791: 1.14 | M791: 0.99 | N791: 0.88 | O791: 0.84 | P791: =AVERAGE(D791:O791) -> 1.18
A792: =B792+(C792/100) -> 41.55 | B792: 41 | C792: 55 | D792: 0.84 | E792: 0.97 | F792: 1.17 | G792: 1.41 | H792: 1.57 | I792: 1.54 | J792: 1.42 | K792: 1.28 | L792: 1.12 | M792: 0.95 | N792: 0.83 | O792: 0.79 | P792: =AVERAGE(D792:O792) -> 1.1575
A793: =B793+(C793/100) -> 41.6 | B793: 41 | C793: 60 | D793: 0.78 | E793: 0.92 | F793: 1.14 | G793: 1.39 | H793: 1.56 | I793: 1.54 | J793: 1.41 | K793: 1.26 | L793: 1.08 | M793: 0.91 | N793: 0.78 | O793: 0.73 | P793: =AVERAGE(D793:O793) -> 1.125
A794: =B794+(C794/100) -> 41.65 | B794: 41 | C794: 65 | D794: 0.72 | E794: 0.87 | F794: 1.09 | G794: 1.36 | H794: 1.54 | I794: 1.53 | J794: 1.39 | K794: 1.23 | L794: 1.04 | M794: 0.85 | N794: 0.72 | O794: 0.67 | P794: =AVERAGE(D794:O794) -> 1.0841667
...

Sheet Temp. Média
A1: Normais Climatológicas do Brasil 1961-1990
A3: Temperatura Média (°C)
A4: Nome da Estação | B4: UF | C4: Janeiro | D4: Fevereiro | E4: Março | F4: Abril | G4: Maio | H4: Junho | I4: Julho | J4: Agosto | K4: Setembro | L4: Outubro | M4: Novembro | N4: Dezembro | O4: Ano
A5: Araranguá | B5: SC | C5: 24 | D5: 24.1 | E5: 22.8 | F5: 20.2 | G5: 17.8 | H5: 15.6 | I5: 15.2 | J5: 16 | K5: 17.4 | L5: 19.1 | M5: 21.1 | N5: 22.9 | O5: 19.7
A6: Alagoinhas | B6: BA | C6: 25.9 | D6: 25.7 | E6: 25.5 | F6: 25 | G6: 23.6 | H6: 22.5 | I6: 21.5 | J6: 21.5 | K6: 22.6 | L6: 24.3 | M6: 25.1 | N6: 25.5 | O6: 24.1
A7: Alegrete | B7: RS | C7: 24.7 | D7: 24.4 | E7: 22.3 | F7: 18.7 | G7: 15.8 | H7: 13.7 | I7: 13.7 | J7: 14.6 | K7: 16.5 | L7: 18.9 | M7: 21.5 | N7: 24 | O7: 19.1
A8: Altamira | B8: PA | C8: 25.7 | D8: 25.4 | E8: 25.4 | F8: 25.7 | G8: 25.9 | H8: 25.7 | I8: 25.6 | J8: 26.2 | K8: 26.8 | L8: 27 | M8: 26.8 | N8: 26.4 | O8: 26.1
A9: Alto da Boa Vista | B9: RJ | C9: 24.5 | D9: 24.6 | E9: - | F9: 21.2 | G9: 19.5 | H9: 19 | I9: 18.5 | J9: 19 | K9: 19.3 | L9: 20.2 | M9: 21.3 | N9: 22.8 | O9: -
A10: Alto Tapajós | B10: PA | C10: 25.3 | D10: 25.2 | E10: 25.4 | F10: 25.5 | G10: 25.5 | H10: 25 | I10: 24.4 | J10: 25.5 | K10: 25.7 | L10: 25.8 | M10: 25.6 | N10: 25.5 | O10: 25.4
A11: Angra dos Reis | B11: RJ | C11: 25.9 | D11: 26.4 | E11: 25.7 | F11: 23.8 | G11: 22.1 | H11: 20.7 | I11: 20.2 | J11: 20.8 | K11: 21.4 | L11: 22.3 | M11: 23.5 | N11: 24.9 | O11: 23.1
A12: Apodí | B12: RN | C12: 28.1 | D12: 27.3 | E12: 26.4 | F12: 26.8 | G12: 26.3 | H12: 26.2 | I12: 26 | J12: 26.7 | K12: 27.3 | L12: 27.9 | M12: 28 | N12: 27.9 | O12: 27.1
A13: Aracaju | B13: SE | C13: 27 | D13: 27.1 | E13: 27.1 | F13: 26.7 | G13: 26 | H13: 25.1 | I13: 24.4 | J13: 24.4 | K13: 25 | L13: 25.9 | M13: 26.3 | N13: 26.6 | O13: 26
A14: Araçatuba | B14: SP | C14: 25.2 | D14: 25.3 | E14: 24.9 | F14: 22.9 | G14: 20.2 | H14: 19.2 | I14: 18.8 | J14: 21.1 | K14: 23.2 | L14: 23.8 | M14: 24.5 | N14: 24.8 | O14: 22.8
A15: Araçuaí | B15: MG | C15: 25.6 | D15: 26 | E15: 25.9 | F15: 24.6 | G15: 22.8 | H15: 21.5 | I15: 21.3 | J15: 22.5 | K15: 24.5 | L15: 25.3 | M15: 25 | N15: 24.9 | O15: 24.2
A16: Aragarças | B16: GO | C16: 25.3 | D16: 25.4 | E16: 25.5 | F16: 25.3 | G16: 23.8 | H16: 22.5 | I16: 22.2 | J16: 24.3 | K16: 26.1 | L16: 26.7 | M16: 25.9 | N16: 25.4 | O16: 24.9
A17: Araras | B17: RJ | C17: 21.7 | D17: 21.9 | E17: 21.1 | F17: 18.9 | G17: 15.9 | H17: 14.8 | I17: 14 | J17: 15.5 | K17: 17.7 | L17: 19 | M17: 19.8 | N17: 21 | O17: 18.4
A18: Araxá | B18: MG | C18: 21.5 | D18: 22 | E18: 22 | F18: 20.3 | G18: 18.7 | H18: 17.9 | I18: 17.5 | J18: 19.4 | K18: 20 | L18: 21.1 | M18: 21 | N18: 21 | O18: 20.2
A19: Arcoverde | B19: PE | C19: 24.5 | D19: 24.2 | E19: 24.2 | F19: 23.3 | G19: 21.9 | H19: 20.8 | I19: 20.2 | J19: 20.7 | K19: 22.1 | L19: 23.8 | M19: 24.5 | N19: 24.7 | O19: 22.9
A20: Avaré | B20: SP | C20: 22.5 | D20: 22.8 | E20: 22.1 | F20: 19.6 | G20: 17.8 | H20: 16.9 | I20: 16.8 | J20: 17.5 | K20: 18.3 | L20: 20.1 | M20: 20.9 | N20: 21.7 | O20: 19.8
A21: Bagé | B21: RS | C21: 23.9 | D21: 23.3 | E21: 21.4 | F21: 17.8 | G21: 15 | H21: 12.4 | I21: 12.5 | J21: 13.1 | K21: 15.1 | L21: 17.5 | M21: 20 | N21: 22.8 | O21: 17.9
A22: Bambuí | B22: MG | C22: 23.2 | D22: 23.4 | E22: 23.1 | F22: 20.9 | G22: 18.2 | H22: 16.6 | I22: 16.1 | J22: 18.4 | K22: 20.2 | L22: 22.2 | M22: 22.4 | N22: 22.6 | O22: 20.6
A23: Bananal | B23: SP | C23: 24.3 | D23: 24.2 | E23: 23.7 | F23: 22.2 | G23: 19.4 | H23: 17.7 | I23: 17.2 | J23: 18.1 | K23: - | L23: 20.7 | M23: 22.1 | N23: 23.2 | O23: -
A24: Bangu | B24: RJ | C24: 27 | D24: 27.1 | E24: 26.4 | F24: 24.2 | G24: 22 | H24: 21.1 | I24: 20.5 | J24: 21.8 | K24: 22.5 | L24: 23.4 | M24: 24.3 | N24: 25.9 | O24: 23.9
A25: Barbacena | B25: MG | C25: 20.2 | D25: 20.5 | E25: 20 | F25: 18.1 | G25: 16.3 | H25: 15.2 | I25: 14.7 | J25: 16.1 | K25: 17 | L25: 18.1 | M25: 18.9 | N25: 19.5 | O25: 17.9
A26: Barbalha | B26: CE | C26: 25.3 | D26: 24.6 | E26: 24.2 | F26: 24 | G26: 23.9 | H26: 23.7 | I26: 23.7 | J26: 24.6 | K26: 26 | L26: 26.4 | M26: 26.5 | N26: 26.2 | O26: 24.9
A27: Barcelos | B27: AM | C27: 25.9 | D27: 26.3 | E27: 26.3 | F27: 26 | G27: 25.6 | H27: 25.4 | I27: 25.4 | J27: 25.7 | K27: 25.9 | L27: 26.2 | M27: 26.3 | N27: 26.3 | O27: 25.9
A28: Barra do Corda | B28: MA | C28: 25.1 | D28: 25 | E28: 25 | F28: 25.2 | G28: 24.9 | H28: 24.6 | I28: 24.4 | J28: 25.5 | K28: 27 | L28: 27.4 | M28: 26.5 | N28: 25.8 | O28: 25.5
A29: Barreiras | B29: BA | C29: 24.7 | D29: 24.7 | E29: 24.5 | F29: 24.4 | G29: 23.4 | H29: 22 | I29: 21.9 | J29: 23.6 | K29: 25.9 | L29: 26.4 | M29: 25.3 | N29: 24.6 | O29: 24.3
A30: Barreirinha | B30: RJ | C30: 21.8 | D30: 22 | E30: 21.3 | F30: 19.2 | G30: 17 | H30: 16.2 | I30: 15.5 | J30: 17.1 | K30: 18.3 | L30: 19 | M30: 20 | N30: 21 | O30: 19
A31: Belém | B31: PA | C31: 25.6 | D31: 25.4 | E31: 25.5 | F31: 25.6 | G31: 25.8 | H31: 26 | I31: 25.7 | J31: 26 | K31: 26 | L31: 26.4 | M31: 26.5 | N31: 26.2 | O31: 25.9
A32: Belo Horizonte | B32: MG | C32: 22.8 | D32: 23 | E32: 22.9 | F32: 21.7 | G32: 19.6 | H32: 18.5 | I32: 18 | J32: 19.7 | K32: 21.1 | L32: 21.7 | M32: 22.2 | N32: 22.2 | O32: 21.1
A33: Belterra | B33: PA | C33: 24.8 | D33: 24.5 | E33: 24.6 | F33: 24.7 | G33: 24.6 | H33: 24.4 | I33: 24.3 | J33: 24.8 | K33: 25.4 | L33: 25.8 | M33: 25.8 | N33: 25.3 | O33: 24.9
A34: Benjamin Constant | B34: AM | C34: 25.5 | D34: 25.5 | E34: 25.7 | F34: 25.7 | G34: 25.5 | H34: 25.2 | I34: 25.1 | J34: 25.4 | K34: 25.7 | L34: 25.9 | M34: 25.7 | N34: 25.5 | O34: 25.5
A35: Bento Gonçalves | B35: RS | C35: 21.7 | D35: 21.8 | E35: 20.2 | F35: 17.3 | G35: 14.9 | H35: 13 | I35: 13.1 | J35: 13.5 | K35: 15.3 | L35: 17 | M35: 18.8 | N35: 20.8 | O35: 17.3
... A66: Carolina | B66: MA | C66: 25 | D66: 25.1 | E66: 25.3 | F66: 25.8 | G66: 26.1 | H66: 26 | I66: 26.2 | J66: 27.1 | K66: 28 | L66: 26.7 | M66: 26 | N66: 25.5 | O66: 26.1
A67: Caruaru | B67: PE | C67: 23.9 | D67: 24.1 | E67: 24.1 | F67: 23.6 | G67: 22.7 | H67: 21.6 | I67: 20.6 | J67: 20.9 | K67: 21.7 | L67: 23.1 | M67: - | N67: 24.2 | O67: -
A68: Castro | B68: PR | C68: 20.5 | D68: 20.6 | E68: 19.6 | F68: 17.1 | G68: 14.1 | H68: 12.6 | I68: 12.5 | J68: 13.7 | K68: 15.3 | L68: 17 | M68: 18.6 | N68: 19.6 | O68: 16.8
A69: Cataguases | B69: MG | C69: 26 | D69: 26.1 | E69: 25.6 | F69: 23.5 | G69: 21.1 | H69: 19.7 | I69: 19.4 | J69: 20.6 | K69: 22.2 | L69: 23.6 | M69: 24.5 | N69: 25.3 | O69: 23.1
A70: Catalão | B70: GO | C70: 23 | D70: 23.1 | E70: 23.2 | F70: 22.4 | G70: 20.6 | H70: 19.5 | I70: 19.2 | J70: 21.4 | K70: 23 | L70: 23.3 | M70: 23 | N70: 22.6 | O70: 22
A71: Catanduva | B71: SP | C71: 24.9 | D71: 25 | E71: 24.6 | F71: 23.1 | G71: 20.5 | H71: 19.5 | I71: 19.1 | J71: 21.1 | K71: 22.9 | L71: 23.9 | M71: 24.6 | N71: 24.4 | O71: 22.8
A72: Caxambu | B72: MG | C72: 22 | D72: 22.2 | E72: 21.4 | F72: 19.6 | G72: 16.9 | H72: 15.2 | I72: 14.8 | J72: 16.8 | K72: 18.9 | L72: 20.6 | M72: 21.1 | N72: 21.3 | O72: 19.2
A73: Caxias | B73: MA | C73: 26.6 | D73: 26.2 | E73: 25.9 | F73: 26.2 | G73: 26.1 | H73: 25.7 | I73: 25.8 | J73: 26.7 | K73: 28.2 | L73: 28.6 | M73: 28.3 | N73: 27.6 | O73: 26.8
A74: Caxias do Sul | B74: RS | C74: 20.6 | D74: 20.6 | E74: 19.1 | F74: 16.2 | G74: 14.3 | H74: 12.1 | I74: 12.3 | J74: 12.7 | K74: 14.4 | L74: 15.8 | M74: 17.8 | N74: 19.6 | O74: 16.3
A75: Ceará Mirim | B75: RN | C75: 26.4 | D75: 26.3 | E75: 26.1 | F75: 25.9 | G75: 25.3 | H75: 24.5 | I75: 23.8 | J75: 23.8 | K75: 24.3 | L75: 25 | M75: 25.6 | N75: 25.8 | O75: 25.2
A76: Chapecó | B76: SC | C76: 22.8 | D76: 22.9 | E76: 21.5 | F76: 18.5 | G76: 16 | H76: 14.1 | I76: 15 | J76: 15.6 | K76: 16.4 | L76: 19.1 | M76: 20.6 | N76: 22.2 | O76: 18.7
A77: Cipó | B77: BA | C77: 26.7 | D77: 26.8 | E77: 26.4 | F77: 25.8 | G77: 24.5 | H77: 23.1 | I77: 22.6 | J77: 22.5 | K77: 23.8 | L77: 25.3 | M77: 26.2 | N77: 26.5 | O77: 25
A78: Coari | B78: AM | C78: 25.8 | D78: 25.8 | E78: 26 | F78: 26 | G78: 26.1 | H78: 26 | I78: 26 | J78: 26.6 | K78: 26.7 | L78: 26.6 | M78: 26.5 | N78: 26.3 | O78: 26.2
A79: Conceição do Araguaia | B79: PA | C79: 25.1 | D79: 25.1 | E79: 25.3 | F79: 25.6 | G79: 25.9 | H79: 25.3 | I79: 25.1 | J79: 25.9 | K79: 26.4 | L79: 25.8 | M79: 25.6 | N79: 25.2 | O79: 25.5
... A303: Zé Doca | B303: MA | C303: 25.6 | D303: 25.7 | E303: 25.6 | F303: 26.1 | G303: 26.3 | H303: 26 | I303: 25.8 | J303: 25.9 | K303: 26.4 | L303: 27.3 | M303: 27.4 | N303: 26.6 | O303: 26.2

Sheet Gráficos
I2: Previsão de Geração em kWh/mês
I3: Janeiro | J3: ='Análise Técnica'!I9 -> 911.2372
I4: Fevereiro | J4: ='Análise Técnica'!J9 -> 959.73166
I5: Março | J5: ='Análise Técnica'!K9 -> 805.38641
I6: Abril | J6: ='Análise Técnica'!L9 -> 714.1912
I7: Maio | J7: ='Análise Técnica'!M9 -> 588.15921
I8: Junho | J8: ='Análise Técnica'!N9 -> 543.9244
I9: Julho | J9: ='Análise Técnica'!O9 -> 543.84993
I10: Agosto | J10: ='Análise Técnica'!P9 -> 672.51813
I11: Setembro | J11: ='Análise Técnica'!Q9 -> 683.09279
I12: Outubro | J12: ='Análise Técnica'!R9 -> 764.17505
I13: Novembro | J13: ='Análise Técnica'!S9 -> 769.68579
I14: Dezembro | J14: ='Análise Técnica'!T9 -> 883.05798
J15: =SUM(J3:J14)/12 -> 736.58415

Sheet Custos
A1: Descrição | B1: Quant. | C1: Valor Unit. | D1: Total | E1: cartão
A2: ='Análise Técnica'!C22 -> 6.3 | B2: 1 | C2: 9726.46 | D2: 9641.68 | E2: =(C2*7%)+ C2 -> 10407.312
A4: Cabos CA | B4: 100 | C4: 3 | D4: =C4*B4 -> 300 | E4: 300
A5: Protetor Surto CA | B5: 0 | C5: 50 | D5: =C5*B5 -> 0 | E5: 150
A6: aterramento Cabo | B6: 0 | C6: 4 | D6: =C6*B6 -> 0 | E6: 400
A7: Caixa CA | B7: 0 | C7: 1 | D7: =C7*B7 -> 0 | E7: 60
A8: Caixa CC | B8: 0 | C8: 1 | D8: =C8*B8 -> 0 | E8: 800 | F8: 4219
A9: Combustivel | B9: 0 | C9: 80 | D9: =C9*B9 -> 0
A10: Instaladores | B10: 0 | C10: 130 | D10: =C10*B10 -> 0 | F10: https://www.aldo.com.br/loja/produto/127999-7/gerador-de-energia-solar-growatt-colonial-solar-group-aldo-solar-on-grid-gf-9kwp-jinko-tiger-pro-mono-450w-mtl-s-8kw-2mppt-mono-220v
A11: ART | B11: 0 | C11: 70 | D11: =C11*B11 -> 0 | E11: 70 | F11: 1054
A12: Despesas diversas | B12: 0 | C12: 200 | D12: =C12*B12 -> 0 | F12: 22300
A13: Disjuntor CA | B13: 0 | C13: 60 | D13: =C13*B13 -> 0 | E13: 60 | F13: 15000 | G13: contraposta
A14: Eletrocalhas | B14: 0 | C14: 150 | D14: =C14*B14 -> 0 | E14: 300
A15: Frete | B15: 0 | C15: 0 | D15: =D2*3% -> 289.2504
A16: Andaimes | B16: 0 | C16: 200 | D16: =C16*B16 -> 0
A17: Engenheiro | B17: 0 | C17: 1200 | D17: =C17*B17 -> 0 | E17: =SUM(E4:E16) -> 2140
A18: Transformador 25KVA | B18: 0 | C18: 4000 | D18: =C18*B18 -> 0
A19: SubTotal | D19: =SUM(D2:D18) -> 10230.93
A20: Margem % | D20: 0.36 | F20: Nota
A21: Lucro | D21: =D19*D20 -> 3683.1349 | E21: 28998.02 | F21: =E21-D2 -> 19356.34 | H21: Despesas Diretas e Indiretas | I21: =D19 -> 10230.93
A22: Comissao | D22: 0
A23: Imposto sobre emissao nota 5% | D23: =((D19+D21+D22)-D2)*7.5% -> 320.4289 | E23: A Vista | G23: Normal | H23: Imposto Nota | I23: =D23 -> 320.4289
A24: Valor Final Cliente | D24: =D19+D21+D23+D22 -> 14234.494 | E24: =$D$24-$D$2 -> 4592.8142 | G24: 7269.9729 | H24: Lucro | I24: =D21 -> 3683.1349
B25: 12 | D25: =B25*C25 -> 0 | E25: =E17+D10+D2 -> 11781.68 | H25: Valor Cliente | I25: =SUM(I21:I24) -> 14234.494
B26: 24 | D26: =B26*C26 -> 0
B27: 36 | D27: =B27*C27 -> 0 | E27: 29000
B28: 48 | D28: =B28*C28 -> 0
B29: 60 | D29: =B29*C29 -> 0
B30: 72 | D30: =B30*C30 -> 0 | F30: 999668608
B31: 84 | D31: =B31*C31 -> 0 | F31: uba 790, casa37
C33: 90 dias
